Workbook

Sheet Banking Sector - PSU
B2: PSU BANKING SECTOR INDIA
I4: WEEK 1 | AI4: WEEK 2 | BH4: WEEK 3 | CB4: WEEK 4 | DA4: WEEK 5 | DZ4: WEEK 6 | EY4: WEEK 7 | FS4: WEEK 8 | GR4: WEEK 9
E5: 46142 | I5: 11-05-2026 (Mon) | O5: 12-05-2026 (Tues) | T5: 13-05-2026 (Wed) | Y5: 14-05-2026 (Thurs) | AD5: 15-05-2026 (Fri) | AI5: 18-05-2026 (Mon) | AN5: 19-05-2026 (Tues) | AS5: 20-05-2026 (Wed) | AX5: 21-05-2026 (Thurs) | BC5: 22-05-2026 (Fri) | BH5: 25-05-2026 (Mon) | BM5: 26-05-2026 (Tues) | BR5: 27-05-2026 (Wed) | BW5: 29-05-2026 (Fri) | CB5: 01-06-2026 (Mon) | CG5: 02-06-2026 (Tues) | CL5: 03-06-2026 (Wed) | CQ5: 04-06-2026 (Thurs) | CV5: 05-06-2026 (Fri) | DA5: 08-06-2026 (Mon) | DF5: 09-06-2026 (Tues) | DK5: 10-06-2026 (Wed) | DP5: 11-06-2026 (Thurs) | DU5: 12-06-2026 (Fri) | DZ5: 15-06-2026 (Mon) | EE5: 16-06-2026 (Tues) | EJ5: 17-06-2026 (Wed) | EO5: 18-06-2026 (Thurs) | ET5: 19-06-2026 (Fri) | EY5: 22-06-2026 (Mon) | FD5: 23-06-2026 (Tues) | FI5: 24-06-2026 (Wed) | FN5: 25-06-2026 (Thurs) | FS5: 29-06-2026 (Mon) | FX5: 30-06-2026 (Tues) | GC5: 01-07-2026 (Wed) | GH5: 02-07-2026 (Thurs) | GM5: 03-07-2026 (Fri) | GR5: 06-07-2026 (Mon) | GW5: 07-07-2026 (Tues) | HB5: 08-07-2026 (Wed) | HG5: 09-07-2026 (Thurs) | HL5: 10-07-2026 (Fri)
B6: S. No. | C6: Company Name | D6: Symbol | E6: Price (₹) | F6: Market Cap (₹ Cr.) | G6: Days weight | H6: PE Ratio | I6: Closing Price | J6: Percentage Change | K6: Net Change | L6: No. Of Shares | M6: New Market Cap | N6: New Weight | O6: Closing Price | P6: Percentage Change | Q6: Net Change | R6: New Market Cap | S6: New Weight | T6: Closing Price | U6: Percentage Change | V6: Net Change | W6: New Market Cap | X6: New Weight | Y6: Closing Price | Z6: Percentage Change | AA6: Net Change | AB6: New Market Cap | AC6: New Weight | AD6: Closing Price | AE6: Percentage Change | AF6: Net Change | AG6: New Market Cap | AH6: New Weight | AI6: Closing Price | AJ6: Percentage Change | AK6: Net Change | AL6: New Market Cap | AM6: New Weight | AN6: Closing Price | AO6: Percentage Change | AP6: Net Change | AQ6: New Market Cap | AR6: New Weight | AS6: Closing Price | AT6: Percentage Change | AU6: Net Change | AV6: New Market Cap | AW6: New Weight | AX6: Closing Price | AY6: Percentage Change | AZ6: Net Change | BA6: New Market Cap | BB6: New Weight | BC6: Closing Price | BD6: Percentage Change | BE6: Net Change | BF6: New Market Cap | BG6: New Weight | BH6: Closing Price | BI6: Percentage Change | BJ6: Net Change | BK6: New Market Cap | BL6: New Weight | BM6: Closing Price | BN6: Percentage Change | BO6: Net Change | BP6: New Market Cap | BQ6: New Weight | BR6: Closing Price | BS6: Percentage Change | BT6: Net Change | BU6: New Market Cap | BV6: New Weight | BW6: Closing Price | BX6: Percentage Change | BY6: Net Change | BZ6: New Market Cap | CA6: New Weight | CB6: Closing Price | CC6: Percentage Change | CD6: Net Change | CE6: New Market Cap | CF6: New Weight | CG6: Closing Price | CH6: Percentage Change | CI6: Net Change | CJ6: New Market Cap | CK6: New Weight | CL6: Closing Price | CM6: Percentage Change | CN6: Net Change | CO6: New Market Cap | CP6: New Weight | CQ6: Closing Price | CR6: Percentage Change | CS6: Net Change | CT6: New Market Cap | CU6: New Weight | CV6: Closing Price | CW6: Percentage Change | CX6: Net Change | CY6: New Market Cap | CZ6: New Weight | DA6: Closing Price | DB6: Percentage Change | DC6: Net Change | DD6: New Market Cap | DE6: New Weight | DF6: Closing Price | DG6: Percentage Change | DH6: Net Change | DI6: New Market Cap | DJ6: New Weight | DK6: Closing Price | DL6: Percentage Change | DM6: Net Change | DN6: New Market Cap | DO6: New Weight | DP6: Closing Price | DQ6: Percentage Change | DR6: Net Change | DS6: New Market Cap | DT6: New Weight | DU6: Closing Price | DV6: Percentage Change | DW6: Net Change | DX6: New Market Cap | DY6: New Weight | DZ6: Closing Price | EA6: Percentage Change | EB6: Net Change | EC6: New Market Cap | ED6: New Weight | EE6: Closing Price | EF6: Percentage Change | EG6: Net Change | EH6: New Market Cap | EI6: New Weight | EJ6: Closing Price | EK6: Percentage Change | EL6: Net Change | EM6: New Market Cap | EN6: New Weight | EO6: Closing Price | EP6: Percentage Change | EQ6: Net Change | ER6: New Market Cap | ES6: New Weight | ET6: Closing Price | EU6: Percentage Change | EV6: Net Change | EW6: New Market Cap | EX6: New Weight | EY6: Closing Price | EZ6: Percentage Change | FA6: Net Change | FB6: New Market Cap | FC6: New Weight | FD6: Closing Price | FE6: Percentage Change | FF6: Net Change | FG6: New Market Cap | FH6: New Weight | FI6: Closing Price | FJ6: Percentage Change | FK6: Net Change | FL6: New Market Cap | FM6: New Weight | FN6: Closing Price | FO6: Percentage Change | FP6: Net Change | FQ6: New Market Cap | FR6: New Weight | FS6: Closing Price | FT6: Percentage Change | FU6: Net Change | FV6: New Market Cap | FW6: New Weight | FX6: Closing Price | FY6: Percentage Change | FZ6: Net Change | GA6: New Market Cap | GB6: New Weight | GC6: Closing Price | GD6: Percentage Change | GE6: Net Change | GF6: New Market Cap | GG6: New Weight | GH6: Closing Price | GI6: Percentage Change | GJ6: Net Change | GK6: New Market Cap | GL6: New Weight | GM6: Closing Price | GN6: Percentage Change | GO6: Net Change | GP6: New Market Cap | GQ6: New Weight | GR6: Closing Price | GS6: Percentage Change | GT6: Net Change | GU6: New Market Cap | GV6: New Weight | GW6: Closing Price | GX6: Percentage Change | GY6: Net Change | GZ6: New Market Cap | HA6: New Weight | HB6: Closing Price | HC6: Percentage Change | HD6: Net Change | HE6: New Market Cap | HF6: New Weight | HG6: Closing Price | HH6: Percentage Change | HI6: Net Change | HJ6: New Market Cap | HK6: New Weight | HL6: Closing Price | HM6: Percentage Change | HN6: Net Change | HO6: New Market Cap | HP6: New Weight
B7: 1 | C7: State Bank of India (SBI) | D7: SBIN | E7: 1068 | F7: 986245 | G7: =(F7/$F$19) -> 0.52256153 | H7: 12.17 | I7: 973.6 | J7: =(I7-E7)/E7 -> -0.088389513 | K7: =G7*J7 -> -0.046188959 | L7: =F7/E7 -> 923.45037 | M7: =L7*I7 -> 899071.28 | N7: =(M7/$M$19) -> 0.50234922 | O7: 974.6 | P7: =(O7-I7)/I7 -> 0.0010271159 | Q7: =N7*P7 -> 0.00051597086 | R7: =O7*L7 -> 899994.74 | S7: =R7/$R$19 -> 0.50730024 | T7: 970.45 | U7: =(T7-O7)/O7 -> -0.0042581572 | V7: =U7*S7 -> -0.0021601642 | W7: =T7*$L7 -> 896162.42 | X7: =W7/$W$19 -> 0.50592414 | Y7: 979.9 | Z7: =(Y7-T7)/T7 -> 0.0097377505 | AA7: =Z7*X7 -> 0.0049265631 | AB7: =Y7*$L7 -> 904889.02 | AC7: =AB7/$AB$19 -> 0.50502143 | AD7: 963.2 | AE7: =(AD7-Y7)/Y7 -> -0.017042555 | AF7: =AE7*AC7 -> -0.0086068557 | AG7: =AD7*$L7 -> 889467.4 | AH7: =AG7/$AG$19 -> 0.50492384 | AI7: 939.4 | AJ7: =(AI7-AD7)/AD7 -> -0.024709302 | AK7: =AJ7*AH7 -> -0.012476316 | AL7: =AI7*$L7 -> 867489.28 | AM7: =AL7/$AL$19 -> 0.50275626 | AN7: 948.8 | AO7: =(AN7-AI7)/AI7 -> 0.010006387 | AP7: =AO7*AM7 -> 0.0050307737 | AQ7: =AN7*$L7 -> 876169.72 | AR7: =AQ7/$AQ$19 -> 0.50248693 | AS7: 950.9 | AT7: =(AS7-AN7)/AN7 -> 0.0022133221 | AU7: =AT7*AR7 -> 0.0011121654 | AV7: =AS7*$L7 -> 878108.96 | AW7: =AV7/$AV$19 -> 0.50323621 | AX7: 950.9 | AY7: =(AX7-AS7)/AS7 -> 0 | AZ7: =AY7*AW7 -> 0 | BA7: =AX7*$L7 -> 878108.96 | BB7: =BA7/$BA$19 -> 0.50210583 | BC7: 949.2 | BD7: =(BC7-AX7)/AX7 -> -0.00178778 | BE7: =BD7*BB7 -> -0.00089765477 | BF7: =BC7*$L7 -> 876539.1 | BG7: =BF7/$BF$19 -> 0.50146097 | BH7: 969.6 | BI7: =(BH7-BC7)/BC7 -> 0.021491783 | BJ7: =BI7*BG7 -> 0.01077729 | BK7: =BH7*$L7 -> 895377.48 | BL7: =BK7/$BK$19 -> 0.49937826 | BM7: 968.6 | BN7: =(BM7-BH7)/BH7 -> -0.0010313531 | BO7: =BN7*BL7 -> -0.00051503533 | BP7: =BM7*$L7 -> 894454.03 | BQ7: =BP7/$BP$19 -> 0.50046484 | BR7: 967.8 | BS7: =(BR7-BM7)/BM7 -> -0.00082593434 | BT7: =BS7*BQ7 -> -0.00041335109 | BU7: =BR7*$L7 -> 893715.27 | BV7: =BU7/$BU$19 -> 0.49919925 | BW7: 964.4 | BX7: =(BW7-BR7)/BR7 -> -0.0035131225 | BY7: =BX7*BV7 -> -0.0017537481 | BZ7: =BW7*$L7 -> 890575.54 | CA7: =BZ7/$BZ$19 -> 0.50144743 | CB7: 954.1 | CC7: =(CB7-BW7)/BW7 -> -0.010680216 | CD7: =CC7*CA7 -> -0.0053555667 | CE7: =CB7*$L7 -> 881064 | CF7: =CE7/$CE$19 -> 0.50422423 | CG7: 956.65 | CH7: =(CG7-CB7)/CB7 -> 0.0026726758 | CI7: =CH7*CF7 -> 0.0013476279 | CJ7: =CG7*$L7 -> 883418.8 | CK7: =CJ7/$CJ$19 -> 0.49931446 | CL7: 954.1 | CM7: =(CL7-CG7)/CG7 -> -0.0026655517 | CN7: =CM7*CK7 -> -0.0013309485 | CO7: =CL7*$L7 -> 881064 | CP7: =CO7/$CO$19 -> 0.49860177 | CQ7: 979.25 | CR7: =(CQ7-CL7)/CL7 -> 0.02635992 | CS7: =CR7*CP7 -> 0.013143103 | CT7: =CQ7*$L7 -> 904288.78 | CU7: =CT7/$CT$19 -> 0.50412026 | CV7: 978 | CW7: =(CV7-CQ7)/CQ7 -> -0.0012764871 | CX7: =CW7*CW7 -> 1.6294193e-06 | CY7: =CV7*$L7 -> 903134.47 | CZ7: =CY7/$CY$19 -> 0.50417757 | DA7: 981.95 | DB7: =(DA7-CV7)/CV7 -> 0.0040388548 | DC7: =DB7*CZ7 -> 0.0020363 | DD7: =DA7*$L7 -> 906782.1 | DE7: =DD7/$DD$19 -> 0.50794075 | DF7: 1002.7 | DG7: =(DF7-DA7)/DA7 -> 0.021131422 | DH7: =DG7*DE7 -> 0.01073351 | DI7: =DF7*$L7 -> 925943.69 | DJ7: =DI7/$DI$19 -> 0.50305786 | DK7: 1003.25 | DL7: =(DK7-DF7)/DF7 -> 0.000548519 | DM7: =DL7*DJ7 -> 0.00027593679 | DN7: =DK7*$L7 -> 926451.59 | DO7: =DN7/$DN$19 -> 0.50859775 | DP7: 1000.7 | DQ7: =(DP7-DK7)/DK7 -> -0.0025417393 | DR7: =DQ7*DO7 -> -0.0012927229 | DS7: =DP7*$L7 -> 924096.79 | DT7: =DS7/$DS$19 -> 0.51123715 | DU7: 1017.15 | DV7: =(DU7-DP7)/DP7 -> 0.016438493 | DW7: =DV7*DV7 -> 0.00027022405 | DX7: =DU7*$L7 -> 939287.55 | DY7: =DX7/$DX$19 -> 0.5096491 | DZ7: 1020.85 | EA7: =(DZ7-DU7)/DU7 -> 0.0036376149 | EB7: =EA7*DY7 -> 0.0018539072 | EC7: =DZ7*$L7 -> 942704.31 | ED7: =EC7/$EC$19 -> 0.50850706 | EE7: 1015.3 | EF7: =(EE7-DZ7)/DZ7 -> -0.0054366459 | EG7: =EF7*ED7 -> -0.0027645729 | EH7: =EE7*$L7 -> 937579.17 | EI7: =EH7/$EH$19 -> 0.50718644 | EJ7: 1026.5 | EK7: =(EJ7-EE7)/EE7 -> 0.011031222 | EL7: =EK7*EI7 -> 0.0055948863 | EM7: =EJ7*$L7 -> 947921.81 | EN7: =EM7/$EM$19 -> 0.50386615 | EO7: 1042.7 | EP7: =(EO7-EJ7)/EJ7 -> 0.015781783 | EQ7: =EP7*EN7 -> 0.0079519061 | ER7: =EO7*$L7 -> 962881.71 | ES7: =ER7/$ER$19 -> 0.50757381 | ET7: 1035.1 | EU7: =(ET7-EO7)/EO7 -> -0.0072887695 | EV7: =EU7*EU7 -> 5.3126161e-05 | EW7: =ET7*$L7 -> 955863.48 | EX7: =EW7/$EW$19 -> 0.50709839 | EY7: 1040.75 | EZ7: =(EY7-ET7)/ET7 -> 0.0054584098 | FA7: =EZ7*EX7 -> 0.0027679508 | FB7: =EY7*$L7 -> 961080.98 | FC7: =FB7/$FB$19 -> 0.50736996 | FD7: 1024.2 | FE7: =(FD7-EY7)/EY7 -> -0.015901994 | FF7: =FE7*FC7 -> -0.008068194 | FG7: =FD7*$L7 -> 945797.87 | FH7: =FG7/$FG$19 -> 0.50835859 | FI7: 1034.6 | FJ7: =(FI7-FD7)/FD7 -> 0.010154267 | FK7: =FJ7*FH7 -> 0.0051620087 | FL7: =FI7*$L7 -> 955401.76 | FM7: =FL7/$FL$19 -> 0.51052637 | FN7: 1045 | FO7: =(FN7-FI7)/FI7 -> 0.010052194 | FP7: =FO7*FM7 -> 0.0051319102 | FQ7: =FN7*$L7 -> 965005.64 | FR7: =FQ7/$FQ$19 -> 0.51406065 | FS7: 1036.1 | FT7: =(FS7-FN7)/FN7 -> -0.0085167464 | FU7: =FT7*FR7 -> -0.0043781242 | FV7: =FS7*$L7 -> 956786.93 | FW7: =FV7/$FQ$19 -> 0.50968252 | FX7: 1026.9 | FY7: =(FX7-FS7)/FS7 -> -0.0088794518 | FZ7: =FY7*FW7 -> -0.0045257014 | GA7: =FX7*$L7 -> 948291.19 | GB7: =GA7/$GA$19 -> 0.51328814 | GC7: 1047.4 | GD7: =(GC7-FX7)/FX7 -> 0.019962995 | GE7: =GD7*GB7 -> 0.010246769 | GF7: =GC7*$L7 -> 967221.92 | GG7: =GF7/$GF$19 -> 0.51966887 | GH7: 1051.6 | GI7: =(GH7-GC7)/GC7 -> 0.0040099293 | GJ7: =GI7*GG7 -> 0.0020838354 | GK7: =GH7*$L7 -> 971100.41 | GL7: =GK7/$GK$19 -> 0.52077716 | GM7: 1040 | GN7: =(GM7-GH7)/GH7 -> -0.01103081 | GO7: =GN7*GN7 -> 0.00012167877 | GP7: =GM7*$L7 -> 960388.39 | GQ7: =GP7/$GP$19 -> 0.52245499 | GR7: 1037.7 | GS7: =(GR7-GM7)/GM7 -> -0.0022115385 | GT7: =GS7*GQ7 -> -0.0011554293 | GU7: =GR7*$L7 -> 958264.45 | GV7: =GU7/$GU$19 -> 0.52429642 | GW7: 1038.1 | GX7: =(GW7-GR7)/GR7 -> 0.00038546786 | GY7: =GX7*GV7 -> 0.00020209942 | GZ7: =GW7*$L7 -> 958633.83 | HA7: =GZ7/$GZ$19 -> 0.52596206 | HB7: 1016.9 | HC7: =(HB7-GW7)/GW7 -> -0.020421925 | HD7: =HC7*HA7 -> -0.010741158 | HE7: =HB7*$L7 -> 939056.69 | HF7: =HE7/$HE$19 -> 0.52830364 | HG7: 1022.1 | HH7: =(HG7-HB7)/HB7 -> 0.0051135805 | HI7: =HH7*HF7 -> 0.0027015232 | HJ7: =HG7*$L7 -> 943858.63 | HK7: =HJ7/$HJ$19 -> 0.52360454 | HL7: 1036 | HM7: =(HL7-HG7)/HG7 -> 0.013599452 | HN7: =HM7*HM7 -> 0.0001849451 | HO7: =HL7*$L7 -> 956694.59 | HP7: =HO7/$HO$19 -> 0.51959155
B8: 2 | C8: Bank of Baroda (BOB) | D8: BANKBARODA | E8: 263 | F8: 136245 | G8: =(F8/$F$19) -> 0.07218936 | H8: 7 | I8: 266 | J8: =(I8-E8)/E8 -> 0.011406844 | K8: =G8*J8 -> 0.00082345277 | L8: =F8/E8 -> 518.04183 | M8: =L8*I8 -> 137799.13 | N8: =(M8/$M$19) -> 0.076994211 | O8: 259.95 | P8: =(O8-I8)/I8 -> -0.022744361 | Q8: =N8*P8 -> -0.0017511841 | R8: =O8*L8 -> 134664.97 | S8: =R8/$R$19 -> 0.075906636 | T8: 261.65 | U8: =(T8-O8)/O8 -> 0.0065397192 | V8: =U8*S8 -> 0.00049640808 | W8: =T8*$L8 -> 135545.64 | X8: =W8/$W$19 -> 0.076521635 | Y8: 267.8 | Z8: =(Y8-T8)/T8 -> 0.023504682 | AA8: =Z8*X8 -> 0.0017986167 | AB8: =Y8*$L8 -> 138731.6 | AC8: =AB8/$AB$19 -> 0.077426546 | AD8: 261.4 | AE8: =(AD8-Y8)/Y8 -> -0.023898432 | AF8: =AE8*AC8 -> -0.001850373 | AG8: =AD8*$L8 -> 135416.13 | AH8: =AG8/$AG$19 -> 0.076871659 | AI8: 260.05 | AJ8: =(AI8-AD8)/AD8 -> -0.0051644989 | AK8: =AJ8*AH8 -> -0.00039700359 | AL8: =AI8*$L8 -> 134716.78 | AM8: =AL8/$AL$19 -> 0.078075549 | AN8: 260.6 | AO8: =(AN8-AI8)/AI8 -> 0.0021149779 | AP8: =AO8*AM8 -> 0.00016512806 | AQ8: =AN8*$L8 -> 135001.7 | AR8: =AQ8/$AQ$19 -> 0.07742403 | AS8: 263.55 | AT8: =(AS8-AN8)/AN8 -> 0.011320031 | AU8: =AT8*AR8 -> 0.00087644239 | AV8: =AS8*$L8 -> 136529.92 | AW8: =AV8/$AV$19 -> 0.078244049 | AX8: 263.1 | AY8: =(AX8-AS8)/AS8 -> -0.0017074559 | AZ8: =AY8*AW8 -> -0.00013359826 | BA8: =AX8*$L8 -> 136296.8 | BB8: =BA8/$BA$19 -> 0.077934999 | BC8: 265.4 | BD8: =(BC8-AX8)/AX8 -> 0.0087419232 | BE8: =BD8*BB8 -> 0.00068130177 | BF8: =BC8*$L8 -> 137488.3 | BG8: =BF8/$BF$19 -> 0.078655952 | BH8: 272.25 | BI8: =(BH8-BC8)/BC8 -> 0.025810098 | BJ8: =BI8*BG8 -> 0.0020301178 | BK8: =BH8*$L8 -> 141036.89 | BL8: =BK8/$BK$19 -> 0.078660405 | BM8: 270.5 | BN8: =(BM8-BH8)/BH8 -> -0.0064279155 | BO8: =BN8*BL8 -> -0.00050562244 | BP8: =BM8*$L8 -> 140130.31 | BQ8: =BP8/$BP$19 -> 0.0784057 | BR8: 270.95 | BS8: =(BR8-BM8)/BM8 -> 0.001663586 | BT8: =BS8*BQ8 -> 0.00013043462 | BU8: =BR8*$L8 -> 140363.43 | BV8: =BU8/$BU$19 -> 0.078402286 | BW8: 268.5 | BX8: =(BW8-BR8)/BR8 -> -0.0090422587 | BY8: =BX8*BV8 -> -0.00070893375 | BZ8: =BW8*$L8 -> 139094.23 | CA8: =BZ8/$BZ$19 -> 0.078318391 | CB8: 264.35 | CC8: =(CB8-BW8)/BW8 -> -0.015456238 | CD8: =CC8*CA8 -> -0.0012105077 | CE8: =CB8*$L8 -> 136944.36 | CF8: =CE8/$CE$19 -> 0.078371904 | CG8: 265.8 | CH8: =(CG8-CB8)/CB8 -> 0.0054851523 | CI8: =CH8*CF8 -> 0.00042988182 | CJ8: =CG8*$L8 -> 137695.52 | CK8: =CJ8/$CJ$19 -> 0.077826465 | CL8: 268.85 | CM8: =(CL8-CG8)/CG8 -> 0.011474793 | CN8: =CM8*CK8 -> 0.00089304258 | CO8: =CL8*$L8 -> 139275.54 | CP8: =CO8/$CO$19 -> 0.078817241 | CQ8: 271.3 | CR8: =(CQ8-CL8)/CL8 -> 0.0091128882 | CS8: =CR8*CP8 -> 0.0007182527 | CT8: =CQ8*$L8 -> 140544.75 | CU8: =CT8/$CT$19 -> 0.078350475 | CV8: 263.7 | CW8: =(CV8-CQ8)/CQ8 -> -0.028013269 | CX8: =CW8*CW8 -> 0.00078474326 | CY8: =CV8*$L8 -> 136607.63 | CZ8: =CY8/$CY$19 -> 0.076261626 | DA8: 259.25 | DB8: =(DA8-CV8)/CV8 -> -0.016875237 | DC8: =DB8*CZ8 -> -0.001286933 | DD8: =DA8*$L8 -> 134302.34 | DE8: =DD8/$DD$19 -> 0.075230459 | DF8: 273.8 | DG8: =(DF8-DA8)/DA8 -> 0.056123433 | DH8: =DG8*DE8 -> 0.0042221916 | DI8: =DF8*$L8 -> 141839.85 | DJ8: =DI8/$DI$19 -> 0.077060465 | DK8: 269.3 | DL8: =(DK8-DF8)/DF8 -> -0.016435354 | DM8: =DL8*DJ8 -> -0.0012665161 | DN8: =DK8*$L8 -> 139508.66 | DO8: =DN8/$DN$19 -> 0.076586616 | DP8: 267.6 | DQ8: =(DP8-DK8)/DK8 -> -0.0063126625 | DR8: =DQ8*DO8 -> -0.00048346546 | DS8: =DP8*$L8 -> 138627.99 | DT8: =DS8/$DS$19 -> 0.076693026 | DU8: 274.75 | DV8: =(DU8-DP8)/DP8 -> 0.026718984 | DW8: =DV8*DV8 -> 0.00071390408 | DX8: =DU8*$L8 -> 142331.99 | DY8: =DX8/$DX$19 -> 0.077228077 | DZ8: 276.05 | EA8: =(DZ8-DU8)/DU8 -> 0.0047315742 | EB8: =EA8*DY8 -> 0.00036541038 | EC8: =DZ8*$L8 -> 143005.45 | ED8: =EC8/$EC$19 -> 0.077139012 | EE8: 275.35 | EF8: =(EE8-DZ8)/DZ8 -> -0.0025357725 | EG8: =EF8*ED8 -> -0.00019560699 | EH8: =EE8*$L8 -> 142642.82 | EI8: =EH8/$EH$19 -> 0.077163086 | EJ8: 281.85 | EK8: =(EJ8-EE8)/EE8 -> 0.023606319 | EL8: =EK8*EI8 -> 0.0018215364 | EM8: =EJ8*$L8 -> 146010.09 | EN8: =EM8/$EM$19 -> 0.077611402 | EO8: 283 | EP8: =(EO8-EJ8)/EJ8 -> 0.0040801845 | EQ8: =EP8*EN8 -> 0.00031666884 | ER8: =EO8*$L8 -> 146605.84 | ES8: =ER8/$ER$19 -> 0.077281854 | ET8: 281.05 | EU8: =(ET8-EO8)/EO8 -> -0.0068904594 | EV8: =EU8*EU8 -> 4.747843e-05 | EW8: =ET8*$L8 -> 145595.65 | EX8: =EW8/$EW$19 -> 0.077240446 | EY8: 286.05 | EZ8: =(EY8-ET8)/ET8 -> 0.017790429 | FA8: =EZ8*EX8 -> 0.0013741407 | FB8: =EY8*$L8 -> 148185.86 | FC8: =FB8/$FB$19 -> 0.078229679 | FD8: 277.8 | FE8: =(FD8-EY8)/EY8 -> -0.028841112 | FF8: =FE8*FC8 -> -0.0022562309 | FG8: =FD8*$L8 -> 143912.02 | FH8: =FG8/$FG$19 -> 0.077351528 | FI8: 279.9 | FJ8: =(FI8-FD8)/FD8 -> 0.0075593952 | FK8: =FJ8*FH8 -> 0.00058473077 | FL8: =FI8*$L8 -> 144999.91 | FM8: =FL8/$FL$19 -> 0.07748183 | FN8: 279.15 | FO8: =(FN8-FI8)/FI8 -> -0.0026795284 | FP8: =FO8*FM8 -> -0.00020761476 | FQ8: =FN8*$L8 -> 144611.38 | FR8: =FQ8/$FQ$19 -> 0.077034801 | FS8: 272.8 | FT8: =(FS8-FN8)/FN8 -> -0.022747627 | FU8: =FT8*FR8 -> -0.0017523589 | FV8: =FS8*$L8 -> 141321.81 | FW8: =FV8/$FQ$19 -> 0.075282442 | FX8: 271.65 | FY8: =(FX8-FS8)/FS8 -> -0.0042155425 | FZ8: =FY8*FW8 -> -0.00031735634 | GA8: =FX8*$L8 -> 140726.06 | GB8: =GA8/$GA$19 -> 0.07617177 | GC8: 252.2 | GD8: =(GC8-FX8)/FX8 -> -0.071599485 | GE8: =GD8*GB8 -> -0.0054538594 | GF8: =GC8*$L8 -> 130650.15 | GG8: =GF8/$GF$19 -> 0.070195695 | GH8: 249.95 | GI8: =(GH8-GC8)/GC8 -> -0.0089214909 | GJ8: =GI8*GG8 -> -0.00062625025 | GK8: =GH8*$L8 -> 129484.55 | GL8: =GK8/$GK$19 -> 0.069439367 | GM8: 247.85 | GN8: =(GM8-GH8)/GH8 -> -0.0084016803 | GO8: =GN8*GN8 -> 7.0588232e-05 | GP8: =GM8*$L8 -> 128396.67 | GQ8: =GP8/$GP$19 -> 0.069848282 | GR8: 249.95 | GS8: =(GR8-GM8)/GM8 -> 0.0084728667 | GT8: =GS8*GQ8 -> 0.00059181518 | GU8: =GR8*$L8 -> 129484.55 | GV8: =GU8/$GU$19 -> 0.070845045 | GW8: 247.85 | GX8: =(GW8-GR8)/GR8 -> -0.0084016803 | GY8: =GX8*GV8 -> -0.00059521742 | GZ8: =GW8*$L8 -> 128396.67 | HA8: =GZ8/$GZ$19 -> 0.07044585 | HB8: 240.45 | HC8: =(HB8-GW8)/GW8 -> -0.029856768 | HD8: =HC8*HA8 -> -0.0021032854 | HE8: =HB8*$L8 -> 124563.16 | HF8: =HE8/$GF$19 -> 0.066925277 | HG8: 250.95 | HH8: =(HG8-HB8)/HB8 -> 0.043668122 | HI8: =HH8*HF8 -> 0.0029225012 | HJ8: =HG8*$L8 -> 130002.6 | HK8: =HJ8/$HJ$19 -> 0.072118798 | HL8: 244.6 | HM8: =(HL8-HG8)/HG8 -> -0.025303845 | HN8: =HM8*HM8 -> 0.00064028459 | HO8: =HL8*$L8 -> 126713.03 | HP8: =HO8/$HO$19 -> 0.068819267
B9: 3 | C9: Union Bank of India | D9: UNIONBANK | E9: 166 | F9: 126672 | G9: =(F9/$F$19) -> 0.067117109 | H9: 6.52 | I9: 163.81 | J9: =(I9-E9)/E9 -> -0.013192771 | K9: =G9*J9 -> -0.00088546066 | L9: =F9/E9 -> 763.08434 | M9: =L9*I9 -> 125000.85 | N9: =(M9/$M$19) -> 0.069843269 | O9: 162.19 | P9: =(O9-I9)/I9 -> -0.0098895061 | Q9: =N9*P9 -> -0.00069071544 | R9: =O9*L9 -> 123764.65 | S9: =R9/$R$19 -> 0.069762448 | T9: 162.9 | U9: =(T9-O9)/O9 -> 0.0043775818 | V9: =U9*S9 -> 0.00030539083 | W9: =T9*$L9 -> 124306.44 | X9: =W9/$W$19 -> 0.070176596 | Y9: 164.9 | Z9: =(Y9-T9)/T9 -> 0.012277471 | AA9: =Z9*X9 -> 0.00086159111 | AB9: =Y9*$L9 -> 125832.61 | AC9: =AB9/$AB$19 -> 0.070227577 | AD9: 161.94 | AE9: =(AD9-Y9)/Y9 -> -0.017950273 | AF9: =AE9*AC9 -> -0.0012606042 | AG9: =AD9*$L9 -> 123573.88 | AH9: =AG9/$AG$19 -> 0.070149167 | AI9: 158.89 | AJ9: =(AI9-AD9)/AD9 -> -0.018834136 | AK9: =AJ9*AH9 -> -0.001321199 | AL9: =AI9*$L9 -> 121246.47 | AM9: =AL9/$AL$19 -> 0.070268789 | AN9: 158.96 | AO9: =(AN9-AI9)/AI9 -> 0.00044055636 | AP9: =AO9*AM9 -> 3.0957362e-05 | AQ9: =AN9*$L9 -> 121299.89 | AR9: =AQ9/$AQ$19 -> 0.069565983 | AS9: 159 | AT9: =(AS9-AN9)/AN9 -> 0.00025163563 | AU9: =AT9*AR9 -> 1.750528e-05 | AV9: =AS9*$L9 -> 121330.41 | AW9: =AV9/$AV$19 -> 0.069533347 | AX9: 160.12 | AY9: =(AX9-AS9)/AS9 -> 0.0070440252 | AZ9: =AY9*AW9 -> 0.00048979465 | BA9: =AX9*$L9 -> 122185.06 | BB9: =BA9/$BA$19 -> 0.069865855 | BC9: 160.72 | BD9: =(BC9-AX9)/AX9 -> 0.0037471896 | BE9: =BD9*BB9 -> 0.00026180061 | BF9: =BC9*$L9 -> 122642.91 | BG9: =BF9/$BF$19 -> 0.070163026 | BH9: 168.87 | BI9: =(BH9-BC9)/BC9 -> 0.050709308 | BJ9: =BI9*BG9 -> 0.0035579185 | BK9: =BH9*$L9 -> 128862.05 | BL9: =BK9/$BK$19 -> 0.071870142 | BM9: 167.55 | BN9: =(BM9-BH9)/BH9 -> -0.0078166637 | BO9: =BN9*BL9 -> -0.00056178473 | BP9: =BM9*$L9 -> 127854.78 | BQ9: =BP9/$BP$19 -> 0.071537295 | BR9: 168.72 | BS9: =(BR9-BM9)/BM9 -> 0.0069829902 | BT9: =BS9*BQ9 -> 0.00049954422 | BU9: =BR9*$L9 -> 128747.59 | BV9: =BU9/$BU$19 -> 0.071914067 | BW9: 167.88 | BX9: =(BW9-BR9)/BR9 -> -0.0049786629 | BY9: =BX9*BV9 -> -0.00035803589 | BZ9: =BW9*$L9 -> 128106.6 | CA9: =BZ9/$BZ$19 -> 0.072131696 | CB9: 162.54 | CC9: =(CB9-BW9)/BW9 -> -0.031808435 | CD9: =CC9*CA9 -> -0.0022943963 | CE9: =CB9*$L9 -> 124031.73 | CF9: =CE9/$CE$19 -> 0.070982134 | CG9: 162.56 | CH9: =(CG9-CB9)/CB9 -> 0.00012304663 | CI9: =CH9*CF9 -> 8.7341127e-06 | CJ9: =CG9*$L9 -> 124046.99 | CK9: =CJ9/$CJ$19 -> 0.070112222 | CL9: 166.7 | CM9: =(CL9-CG9)/CG9 -> 0.02546752 | CN9: =CM9*CK9 -> 0.0017855844 | CO9: =CL9*$L9 -> 127206.16 | CP9: =CO9/$CO$19 -> 0.07198707 | CQ9: 166.54 | CR9: =(CQ9-CL9)/CL9 -> -0.00095980804 | CS9: =CR9*CP9 -> -6.9093769e-05 | CT9: =CQ9*$L9 -> 127084.07 | CU9: =CT9/$CT$19 -> 0.070846453 | CV9: 167 | CW9: =(CV9-CQ9)/CQ9 -> 0.0027620992 | CX9: =CW9*CW9 -> 7.629192e-06 | CY9: =CV9*$L9 -> 127435.08 | CZ9: =CY9/$CY$19 -> 0.071141025 | DA9: 165.18 | DB9: =(DA9-CV9)/CV9 -> -0.010898204 | DC9: =DB9*CZ9 -> -0.00077530937 | DD9: =DA9*$L9 -> 126046.27 | DE9: =DD9/$DD$19 -> 0.070605758 | DF9: 170.44 | DG9: =(DF9-DA9)/DA9 -> 0.031844049 | DH9: =DG9*DE9 -> 0.0022483732 | DI9: =DF9*$L9 -> 130060.09 | DJ9: =DI9/$DI$19 -> 0.070660617 | DK9: 166.45 | DL9: =(DK9-DF9)/DF9 -> -0.023409998 | DM9: =DL9*DJ9 -> -0.0016541649 | DN9: =DK9*$L9 -> 127015.39 | DO9: =DN9/$DN$19 -> 0.069728134 | DP9: 164.54 | DQ9: =(DP9-DK9)/DK9 -> -0.011474917 | DR9: =DQ9*DO9 -> -0.00080012457 | DS9: =DP9*$L9 -> 125557.9 | DT9: =DS9/$DS$19 -> 0.06946227 | DU9: 170.05 | DV9: =(DU9-DP9)/DP9 -> 0.033487298 | DW9: =DV9*DV9 -> 0.0011213991 | DX9: =DU9*$L9 -> 129762.49 | DY9: =DX9/$DX$19 -> 0.070407978 | DZ9: 171.3 | EA9: =(DZ9-DU9)/DU9 -> 0.0073507792 | EB9: =EA9*DY9 -> 0.0005175535 | EC9: =DZ9*$L9 -> 130716.35 | ED9: =EC9/$EC$19 -> 0.070510111 | EE9: 170.56 | EF9: =(EE9-DZ9)/DZ9 -> -0.0043199066 | EG9: =EF9*ED9 -> -0.00030459709 | EH9: =EE9*$L9 -> 130151.66 | EI9: =EH9/$EH$19 -> 0.070405958 | EJ9: 173.75 | EK9: =(EJ9-EE9)/EE9 -> 0.018703096 | EL9: =EK9*EI9 -> 0.0013168094 | EM9: =EJ9*$L9 -> 132585.9 | EN9: =EM9/$EM$19 -> 0.0704758 | EO9: 176.12 | EP9: =(EO9-EJ9)/EJ9 -> 0.013640288 | EQ9: =EP9*EN9 -> 0.0009613102 | ER9: =EO9*$L9 -> 134394.41 | ES9: =ER9/$ER$19 -> 0.07084472 | ET9: 175.76 | EU9: =(ET9-EO9)/EO9 -> -0.0020440609 | EV9: =EU9*EU9 -> 4.1781848e-06 | EW9: =ET9*$L9 -> 134119.7 | EX9: =EW9/$EW$19 -> 0.0711523 | EY9: 176.62 | EZ9: =(EY9-ET9)/ET9 -> 0.004893036 | FA9: =EZ9*EX9 -> 0.00034815076 | FB9: =EY9*$L9 -> 134775.96 | FC9: =FB9/$FB$19 -> 0.071150375 | FD9: 175.12 | FE9: =(FD9-EY9)/EY9 -> -0.0084928094 | FF9: =FE9*FC9 -> -0.00060426657 | FG9: =FD9*$L9 -> 133631.33 | FH9: =FG9/$FG$19 -> 0.071825741 | FI9: 174.83 | FJ9: =(FI9-FD9)/FD9 -> -0.0016560073 | FK9: =FJ9*FH9 -> -0.00011894395 | FL9: =FI9*$L9 -> 133410.03 | FM9: =FL9/$FL$19 -> 0.071288692 | FN9: 174.71 | FO9: =(FN9-FI9)/FI9 -> -0.00068638106 | FP9: =FO9*FM9 -> -4.8931207e-05 | FQ9: =FN9*$L9 -> 133318.46 | FR9: =FQ9/$FQ$19 -> 0.071019042 | FS9: 174.56 | FT9: =(FS9-FN9)/FN9 -> -0.00085856562 | FU9: =FT9*FR9 -> -6.0974508e-05 | FV9: =FS9*$L9 -> 133204 | FW9: =FV9/$FQ$19 -> 0.070958068 | FX9: 172.43 | FY9: =(FX9-FS9)/FS9 -> -0.012202108 | FZ9: =FY9*FW9 -> -0.00086583802 | GA9: =FX9*$L9 -> 131578.63 | GB9: =GA9/$GA$19 -> 0.071220477 | GC9: 174.88 | GD9: =(GC9-FX9)/FX9 -> 0.014208664 | GE9: =GD9*GB9 -> 0.0010119479 | GF9: =GC9*$L9 -> 133448.19 | GG9: =GF9/$GF$19 -> 0.071699026 | GH9: 174.35 | GI9: =(GH9-GC9)/GC9 -> -0.0030306496 | GJ9: =GI9*GG9 -> -0.00021729462 | GK9: =GH9*$L9 -> 133043.75 | GL9: =GK9/$GK$19 -> 0.071348078 | GM9: 163.09 | GN9: =(GM9-GH9)/GH9 -> -0.064582736 | GO9: =GN9*GN9 -> 0.0041709298 | GP9: =GM9*$L9 -> 124451.42 | GQ9: =GP9/$GP$19 -> 0.067702055 | GR9: 161.08 | GS9: =(GR9-GM9)/GM9 -> -0.012324483 | GT9: =GS9*GQ9 -> -0.00083439285 | GU9: =GR9*$L9 -> 122917.63 | GV9: =GU9/$GU$19 -> 0.067252073 | GW9: 161.08 | GX9: =(GW9-GR9)/GR9 -> 0 | GY9: =GX9*GV9 -> 0 | GZ9: =GW9*$L9 -> 122917.63 | HA9: =GZ9/$GZ$19 -> 0.06743973 | HB9: 154.39 | HC9: =(HB9-GW9)/GW9 -> -0.041532158 | HD9: =HC9*HA9 -> -0.0028009175 | HE9: =HB9*$L9 -> 117812.59 | HF9: =HE9/$GF$19 -> 0.063298334 | HG9: 157.26 | HH9: =(HG9-HB9)/HB9 -> 0.018589287 | HI9: =HH9*HF9 -> 0.0011766709 | HJ9: =HG9*$L9 -> 120002.64 | HK9: =HJ9/$HJ$19 -> 0.066571335 | HL9: 164.51 | HM9: =(HL9-HG9)/HG9 -> 0.046101997 | HN9: =HM9*HM9 -> 0.0021253941 | HO9: =HL9*$L9 -> 125535 | HP9: =HO9/$HO$19 -> 0.068179468
B10: 4 | C10: Punjab National Bank (PNB) | D10: PNB | E10: 109 | F10: 125687 | G10: =(F10/$F$19) -> 0.066595208 | H10: 7.06 | I10: 104.62 | J10: =(I10-E10)/E10 -> -0.040183486 | K10: =G10*J10 -> -0.0026760276 | L10: =F10/E10 -> 1153.0917 | M10: =L10*I10 -> 120636.46 | N10: =(M10/$M$19) -> 0.067404701 | O10: 102.78 | P10: =(O10-I10)/I10 -> -0.017587459 | Q10: =N10*P10 -> -0.0011854774 | R10: =O10*L10 -> 118514.77 | S10: =R10/$R$19 -> 0.066803247 | T10: 102.75 | U10: =(T10-O10)/O10 -> -0.00029188558 | V10: =U10*S10 -> -1.9498905e-05 | W10: =T10*$L10 -> 118480.18 | X10: =W10/$W$19 -> 0.066887408 | Y10: 104.62 | Z10: =(Y10-T10)/T10 -> 0.018199513 | AA10: =Z10*X10 -> 0.0012173183 | AB10: =Y10*$L10 -> 120636.46 | AC10: =AB10/$AB$19 -> 0.067327589 | AD10: 102.05 | AE10: =(AD10-Y10)/Y10 -> -0.024565093 | AF10: =AE10*AC10 -> -0.0016539085 | AG10: =AD10*$L10 -> 117673.01 | AH10: =AG10/$AG$19 -> 0.066799424 | AI10: 99.49 | AJ10: =(AI10-AD10)/AD10 -> -0.025085742 | AK10: =AJ10*AH10 -> -0.0016757131 | AL10: =AI10*$L10 -> 114721.1 | AM10: =AL10/$AL$19 -> 0.066486988 | AN10: 101.3 | AO10: =(AN10-AI10)/AI10 -> 0.018192783 | AP10: =AO10*AM10 -> 0.0012095834 | AQ10: =AN10*$L10 -> 116808.19 | AR10: =AQ10/$AQ$19 -> 0.066989979 | AS10: 102.22 | AT10: =(AS10-AN10)/AN10 -> 0.0090819348 | AU10: =AT10*AR10 -> 0.00060839862 | AV10: =AS10*$L10 -> 117869.04 | AW10: =AV10/$AV$19 -> 0.067549667 | AX10: 101.12 | AY10: =(AX10-AS10)/AS10 -> -0.010761104 | AZ10: =AY10*AW10 -> -0.00072690896 | BA10: =AX10*$L10 -> 116600.64 | BB10: =BA10/$BA$19 -> 0.06667266 | BC10: 102.66 | BD10: =(BC10-AX10)/AX10 -> 0.01522943 | BE10: =BD10*BB10 -> 0.0010153866 | BF10: =BC10*$L10 -> 118376.4 | BG10: =BF10/$BF$19 -> 0.067722186 | BH10: 106.26 | BI10: =(BH10-BC10)/BC10 -> 0.035067212 | BJ10: =BI10*BG10 -> 0.0023748283 | BK10: =BH10*$L10 -> 122527.53 | BL10: =BK10/$BK$19 -> 0.068337193 | BM10: 105.95 | BN10: =(BM10-BH10)/BH10 -> -0.0029173725 | BO10: =BN10*BL10 -> -0.00019936505 | BP10: =BM10*$L10 -> 122170.07 | BQ10: =BP10/$BP$19 -> 0.068356586 | BR10: 106.67 | BS10: =(BR10-BM10)/BM10 -> 0.0067956583 | BT10: =BS10*BQ10 -> 0.000464528 | BU10: =BR10*$L10 -> 123000.3 | BV10: =BU10/$BU$19 -> 0.068703822 | BW10: 106.05 | BX10: =(BW10-BR10)/BR10 -> -0.0058123184 | BY10: =BX10*BV10 -> -0.00039932849 | BZ10: =BW10*$L10 -> 122285.38 | CA10: =BZ10/$BZ$19 -> 0.068854001 | CB10: 103.78 | CC10: =(CB10-BW10)/BW10 -> -0.021404998 | CD10: =CC10*CA10 -> -0.0014738197 | CE10: =CB10*$L10 -> 119667.86 | CF10: =CE10/$CE$19 -> 0.068484736 | CG10: 104.09 | CH10: =(CG10-CB10)/CB10 -> 0.0029870881 | CI10: =CH10*CF10 -> 0.00020456994 | CJ10: =CG10*$L10 -> 120025.32 | CK10: =CJ10/$CJ$19 -> 0.067839146 | CL10: 105.9 | CM10: =(CL10-CG10)/CG10 -> 0.017388798 | CN10: =CM10*CK10 -> 0.0011796412 | CO10: =CL10*$L10 -> 122112.42 | CP10: =CO10/$CO$19 -> 0.069104477 | CQ10: 106.27 | CR10: =(CQ10-CL10)/CL10 -> 0.0034938621 | CS10: =CR10*CP10 -> 0.00024144151 | CT10: =CQ10*$L10 -> 122539.06 | CU10: =CT10/$CT$19 -> 0.068312717 | CV10: 106.85 | CW10: =(CV10-CQ10)/CQ10 -> 0.0054577962 | CX10: =CW10*CW10 -> 2.9787539e-05 | CY10: =CV10*$L10 -> 123207.85 | CZ10: =CY10/$CY$19 -> 0.06878116 | DA10: 105.71 | DB10: =(DA10-CV10)/CV10 -> -0.010669162 | DC10: =DB10*CZ10 -> -0.00073383736 | DD10: =DA10*$L10 -> 121893.33 | DE10: =DD10/$DD$19 -> 0.068279457 | DF10: 109.65 | DG10: =(DF10-DA10)/DA10 -> 0.037271781 | DH10: =DG10*DE10 -> 0.002544897 | DI10: =DF10*$L10 -> 126436.51 | DJ10: =DI10/$DI$19 -> 0.068691952 | DK10: 107.17 | DL10: =(DK10-DF10)/DF10 -> -0.022617419 | DM10: =DL10*DJ10 -> -0.0015536347 | DN10: =DK10*$L10 -> 123576.84 | DO10: =DN10/$DN$19 -> 0.067840462 | DP10: 106.17 | DQ10: =(DP10-DK10)/DK10 -> -0.0093309695 | DR10: =DQ10*DO10 -> -0.00063301728 | DS10: =DP10*$L10 -> 122423.75 | DT10: =DS10/$DS$19 -> 0.067728369 | DU10: 106.88 | DV10: =(DU10-DP10)/DP10 -> 0.0066873882 | DW10: =DV10*DV10 -> 4.472116e-05 | DX10: =DU10*$L10 -> 123242.45 | DY10: =DX10/$DX$19 -> 0.066870259 | DZ10: 107.96 | EA10: =(DZ10-DU10)/DU10 -> 0.01010479 | EB10: =EA10*DY10 -> 0.00067570995 | EC10: =DZ10*$L10 -> 124487.78 | ED10: =EC10/$EC$19 -> 0.067150343 | EE10: 107.97 | EF10: =(EE10-DZ10)/DZ10 -> 9.2626899e-05 | EG10: =EF10*ED10 -> 6.219928e-06 | EH10: =EE10*$L10 -> 124499.32 | EI10: =EH10/$EH$19 -> 0.067348301 | EJ10: 108.87 | EK10: =(EJ10-EE10)/EE10 -> 0.0083356488 | EL10: =EK10*EI10 -> 0.00056139179 | EM10: =EJ10*$L10 -> 125537.1 | EN10: =EM10/$EM$19 -> 0.06672902 | EO10: 109.58 | EP10: =(EO10-EJ10)/EJ10 -> 0.0065215395 | EQ10: =EP10*EN10 -> 0.00043517594 | ER10: =EO10*$L10 -> 126355.79 | ES10: =ER10/$ER$19 -> 0.066607239 | ET10: 108.77 | EU10: =(ET10-EO10)/EO10 -> -0.0073918598 | EV10: =EU10*EU10 -> 5.4639592e-05 | EW10: =ET10*$L10 -> 125421.79 | EX10: =EW10/$EW$19 -> 0.06653794 | EY10: 109.8 | EZ10: =(EY10-ET10)/ET10 -> 0.0094695228 | FA10: =EZ10*EX10 -> 0.00063008254 | FB10: =EY10*$L10 -> 126609.47 | FC10: =FB10/$FB$19 -> 0.066839159 | FD10: 107.43 | FE10: =(FD10-EY10)/EY10 -> -0.021584699 | FF10: =FE10*FC10 -> -0.0014427032 | FG10: =FD10*$L10 -> 123876.65 | FH10: =FG10/$FG$19 -> 0.066582679 | FI10: 107.71 | FJ10: =(FI10-FD10)/FD10 -> 0.0026063483 | FK10: =FJ10*FH10 -> 0.00017353765 | FL10: =FI10*$L10 -> 124199.51 | FM10: =FL10/$FL$19 -> 0.066366977 | FN10: 107.87 | FO10: =(FN10-FI10)/FI10 -> 0.0014854702 | FP10: =FO10*FM10 -> 9.8586169e-05 | FQ10: =FN10*$L10 -> 124384.01 | FR10: =FQ10/$FQ$19 -> 0.066259636 | FS10: 109.96 | FT10: =(FS10-FN10)/FN10 -> 0.019375174 | FU10: =FT10*FR10 -> 0.001283792 | FV10: =FS10*$L10 -> 126793.97 | FW10: =FV10/$FQ$19 -> 0.067543428 | FX10: 106.69 | FY10: =(FX10-FS10)/FS10 -> -0.029738087 | FZ10: =FY10*FW10 -> -0.0020086123 | GA10: =FX10*$L10 -> 123023.36 | GB10: =GA10/$GA$19 -> 0.066589705 | GC10: 107.54 | GD10: =(GC10-FX10)/FX10 -> 0.0079670072 | GE10: =GD10*GB10 -> 0.00053052066 | GF10: =GC10*$L10 -> 124003.49 | GG10: =GF10/$GF$19 -> 0.066624577 | GH10: 106.91 | GI10: =(GH10-GC10)/GC10 -> -0.0058582853 | GJ10: =GI10*GG10 -> -0.00039030578 | GK10: =GH10*$L10 -> 123277.04 | GL10: =GK10/$GK$19 -> 0.06611043 | GM10: 105.35 | GN10: =(GM10-GH10)/GH10 -> -0.014591713 | GO10: =GN10*GN10 -> 0.00021291808 | GP10: =GM10*$L10 -> 121478.22 | GQ10: =GP10/$GP$19 -> 0.066084618 | GR10: 104.29 | GS10: =(GR10-GM10)/GM10 -> -0.010061699 | GT10: =GS10*GQ10 -> -0.00066492354 | GU10: =GR10*$L10 -> 120255.94 | GV10: =GU10/$GU$19 -> 0.065795781 | GW10: 103.79 | GX10: =(GW10-GR10)/GR10 -> -0.0047943235 | GY10: =GX10*GV10 -> -0.00031544626 | GZ10: =GW10*$L10 -> 119679.39 | HA10: =GZ10/$GZ$19 -> 0.065663048 | HB10: 100.95 | HC10: =(HB10-GW10)/GW10 -> -0.027362944 | HD10: =HC10*HA10 -> -0.0017967343 | HE10: =HB10*$L10 -> 116404.61 | HF10: =HE10/$GF$19 -> 0.062541855 | HG10: 103.44 | HH10: =(HG10-HB10)/HB10 -> 0.024665676 | HI10: =HH10*HF10 -> 0.0015426371 | HJ10: =HG10*$L10 -> 119275.81 | HK10: =HJ10/$HJ$19 -> 0.066168125 | HL10: 105.41 | HM10: =(HL10-HG10)/HG10 -> 0.019044857 | HN10: =HM10*HM10 -> 0.00036270658 | HO10: =HL10*$L10 -> 121547.4 | HP10: =HO10/$HO$19 -> 0.066013756
B11: 5 | C11: Canara Bank | D11: CANBK | E11: 135 | F11: 122136 | G11: =(F11/$F$19) -> 0.064713712 | H11: 6.05 | I11: 129.43 | J11: =(I11-E11)/E11 -> -0.041259259 | K11: =G11*J11 -> -0.0026700398 | L11: =F11/E11 -> 904.71111 | M11: =L11*I11 -> 117096.76 | N11: =(M11/$M$19) -> 0.065426921 | O11: 130.01 | P11: =(O11-I11)/I11 -> 0.0044811867 | Q11: =N11*P11 -> 0.00029319025 | R11: =O11*L11 -> 117621.49 | S11: =R11/$R$19 -> 0.066299733 | T11: 129.26 | U11: =(T11-O11)/O11 -> -0.005768787 | V11: =U11*S11 -> -0.00038246904 | W11: =T11*$L11 -> 116942.96 | X11: =W11/$W$19 -> 0.066019579 | Y11: 130.84 | Z11: =(Y11-T11)/T11 -> 0.012223426 | AA11: =Z11*X11 -> 0.00080698542 | AB11: =Y11*$L11 -> 118372.4 | AC11: =AB11/$AB$19 -> 0.066064012 | AD11: 128.07 | AE11: =(AD11-Y11)/Y11 -> -0.021170896 | AF11: =AE11*AC11 -> -0.0013986343 | AG11: =AD11*$L11 -> 115866.35 | AH11: =AG11/$AG$19 -> 0.065773837 | AI11: 124.9 | AJ11: =(AI11-AD11)/AD11 -> -0.024752089 | AK11: =AJ11*AH11 -> -0.0016280399 | AL11: =AI11*$L11 -> 112998.42 | AM11: =AL11/$AL$19 -> 0.065488603 | AN11: 126.15 | AO11: =(AN11-AI11)/AI11 -> 0.010008006 | AP11: =AO11*AM11 -> 0.00065541036 | AQ11: =AN11*$L11 -> 114129.31 | AR11: =AQ11/$AQ$19 -> 0.065453626 | AS11: 127.66 | AT11: =(AS11-AN11)/AN11 -> 0.011969877 | AU11: =AT11*AR11 -> 0.00078347187 | AV11: =AS11*$L11 -> 115495.42 | AW11: =AV11/$AV$19 -> 0.066189369 | AX11: 127.97 | AY11: =(AX11-AS11)/AS11 -> 0.0024283252 | AZ11: =AY11*AW11 -> 0.00016072931 | BA11: =AX11*$L11 -> 115775.88 | BB11: =BA11/$BA$19 -> 0.066201061 | BC11: 128.23 | BD11: =(BC11-AX11)/AX11 -> 0.0020317262 | BE11: =BD11*BB11 -> 0.00013450243 | BF11: =BC11*$L11 -> 116011.11 | BG11: =BF11/$BF$19 -> 0.066369021 | BH11: 133.7 | BI11: =(BH11-BC11)/BC11 -> 0.042657724 | BJ11: =BI11*BG11 -> 0.0028311514 | BK11: =BH11*$L11 -> 120959.88 | BL11: =BK11/$BK$19 -> 0.067462867 | BM11: 133.15 | BN11: =(BM11-BH11)/BH11 -> -0.0041136874 | BO11: =BN11*BL11 -> -0.00027752114 | BP11: =BM11*$L11 -> 120462.28 | BQ11: =BP11/$BP$19 -> 0.067401046 | BR11: 134.16 | BS11: =(BR11-BM11)/BM11 -> 0.00758543 | BT11: =BS11*BQ11 -> 0.00051126591 | BU11: =BR11*$L11 -> 121376.04 | BV11: =BU11/$BU$19 -> 0.067796569 | BW11: 130.8 | BX11: =(BW11-BR11)/BR11 -> -0.025044723 | BY11: =BX11*BV11 -> -0.0016979463 | BZ11: =BW11*$L11 -> 118336.21 | CA11: =BZ11/$BZ$19 -> 0.066630383 | CB11: 127.96 | CC11: =(CB11-BW11)/BW11 -> -0.021712538 | CD11: =CC11*CA11 -> -0.0014467147 | CE11: =CB11*$L11 -> 115766.83 | CF11: =CE11/$CE$19 -> 0.066252216 | CG11: 129.08 | CH11: =(CG11-CB11)/CB11 -> 0.0087527352 | CI11: =CH11*CF11 -> 0.00057988811 | CJ11: =CG11*$L11 -> 116780.11 | CK11: =CJ11/$CJ$19 -> 0.066004931 | CL11: 131.85 | CM11: =(CL11-CG11)/CG11 -> 0.02145956 | CN11: =CM11*CK11 -> 0.0014164368 | CO11: =CL11*$L11 -> 119286.16 | CP11: =CO11/$CO$19 -> 0.067505074 | CQ11: 133.12 | CR11: =(CQ11-CL11)/CL11 -> 0.0096321578 | CS11: =CR11*CP11 -> 0.00065021952 | CT11: =CQ11*$L11 -> 120435.14 | CU11: =CT11/$CT$19 -> 0.067139831 | CV11: 135.81 | CW11: =(CV11-CQ11)/CQ11 -> 0.020207332 | CX11: =CW11*CW11 -> 0.00040833626 | CY11: =CV11*$L11 -> 122868.82 | CZ11: =CY11/$CY$19 -> 0.068591892 | DA11: 131.91 | DB11: =(DA11-CV11)/CV11 -> -0.028716589 | DC11: =DB11*CZ11 -> -0.0019697252 | DD11: =DA11*$L11 -> 119340.44 | DE11: =DD11/$DD$19 -> 0.066849439 | DF11: 137.51 | DG11: =(DF11-DA11)/DA11 -> 0.042453188 | DH11: =DG11*DE11 -> 0.0028379718 | DI11: =DF11*$L11 -> 124406.82 | DJ11: =DI11/$DI$19 -> 0.06758924 | DK11: 133.46 | DL11: =(DK11-DF11)/DF11 -> -0.029452403 | DM11: =DL11*DJ11 -> -0.0019906656 | DN11: =DK11*$L11 -> 120742.74 | DO11: =DN11/$DN$19 -> 0.066284616 | DP11: 131.52 | DQ11: =(DP11-DK11)/DK11 -> -0.014536191 | DR11: =DQ11*DO11 -> -0.00096352582 | DS11: =DP11*$L11 -> 118987.61 | DT11: =DS11/$DS$19 -> 0.065827394 | DU11: 131.67 | DV11: =(DU11-DP11)/DP11 -> 0.0011405109 | DW11: =DV11*DV11 -> 1.3007652e-06 | DX11: =DU11*$L11 -> 119123.31 | DY11: =DX11/$DX$19 -> 0.064635254 | DZ11: 132.2 | EA11: =(DZ11-DU11)/DU11 -> 0.0040252146 | EB11: =EA11*DY11 -> 0.00026017076 | EC11: =DZ11*$L11 -> 119602.81 | ED11: =EC11/$EC$19 -> 0.064515323 | EE11: 132.83 | EF11: =(EE11-DZ11)/DZ11 -> 0.0047655068 | EG11: =EF11*ED11 -> 0.00030744821 | EH11: =EE11*$L11 -> 120172.78 | EI11: =EH11/$EH$19 -> 0.065007847 | EJ11: 135.24 | EK11: =(EJ11-EE11)/EE11 -> 0.018143492 | EL11: =EK11*EI11 -> 0.0011794693 | EM11: =EJ11*$L11 -> 122353.13 | EN11: =EM11/$EM$19 -> 0.065036588 | EO11: 134.97 | EP11: =(EO11-EJ11)/EJ11 -> -0.0019964508 | EQ11: =EP11*EN11 -> -0.00012984235 | ER11: =EO11*$L11 -> 122108.86 | ES11: =ER11/$ER$19 -> 0.064368508 | ET11: 133.74 | EU11: =(ET11-EO11)/EO11 -> -0.0091131363 | EV11: =EU11*EU11 -> 8.3049252e-05 | EW11: =ET11*$L11 -> 120996.06 | EX11: =EW11/$EW$19 -> 0.064190034 | EY11: 134.82 | EZ11: =(EY11-ET11)/ET11 -> 0.0080753701 | FA11: =EZ11*EX11 -> 0.00051835828 | FB11: =EY11*$L11 -> 121973.15 | FC11: =FB11/$FB$19 -> 0.064391571 | FD11: 130.37 | FE11: =(FD11-EY11)/EY11 -> -0.033006972 | FF11: =FE11*FC11 -> -0.0021253708 | FG11: =FD11*$L11 -> 117947.19 | FH11: =FG11/$FG$19 -> 0.063395644 | FI11: 130.15 | FJ11: =(FI11-FD11)/FD11 -> -0.0016875048 | FK11: =FJ11*FH11 -> -0.00010698045 | FL11: =FI11*$L11 -> 117748.15 | FM11: =FL11/$FL$19 -> 0.062919642 | FN11: 128.95 | FO11: =(FN11-FI11)/FI11 -> -0.0092201306 | FP11: =FO11*FM11 -> -0.00058012732 | FQ11: =FN11*$L11 -> 116662.5 | FR11: =FQ11/$FQ$19 -> 0.062146372 | FS11: 125.86 | FT11: =(FS11-FN11)/FN11 -> -0.023962776 | FU11: =FT11*FR11 -> -0.0014891996 | FV11: =FS11*$L11 -> 113866.94 | FW11: =FV11/$FQ$19 -> 0.060657172 | FX11: 125.52 | FY11: =(FX11-FS11)/FS11 -> -0.0027014143 | FZ11: =FY11*FW11 -> -0.00016386015 | GA11: =FX11*$L11 -> 113559.34 | GB11: =GA11/$GA$19 -> 0.061467049 | GC11: 126.28 | GD11: =(GC11-FX11)/FX11 -> 0.006054812 | GE11: =GD11*GB11 -> 0.00037217143 | GF11: =GC11*$L11 -> 114246.92 | GG11: =GF11/$GF$19 -> 0.06138257 | GH11: 126.64 | GI11: =(GH11-GC11)/GC11 -> 0.0028508077 | GJ11: =GI11*GG11 -> 0.0001749899 | GK11: =GH11*$L11 -> 114572.62 | GL11: =GK11/$GK$19 -> 0.061442462 | GM11: 127.19 | GN11: =(GM11-GH11)/GH11 -> 0.0043430196 | GO11: =GN11*GN11 -> 1.8861819e-05 | GP11: =GM11*$L11 -> 115070.21 | GQ11: =GP11/$GP$19 -> 0.062598636 | GR11: 126.46 | GS11: =(GR11-GM11)/GM11 -> -0.0057394449 | GT11: =GS11*GQ11 -> -0.00035928142 | GU11: =GR11*$L11 -> 114409.77 | GV11: =GU11/$GU$19 -> 0.062597158 | GW11: 125.03 | GX11: =(GW11-GR11)/GR11 -> -0.011307923 | GY11: =GX11*GV11 -> -0.00070784387 | GZ11: =GW11*$L11 -> 113116.03 | HA11: =GZ11/$GZ$19 -> 0.062062008 | HB11: 121.15 | HC11: =(HB11-GW11)/GW11 -> -0.031032552 | HD11: =HC11*HA11 -> -0.0019259425 | HE11: =HB11*$L11 -> 109605.75 | HF11: =HE11/$GF$19 -> 0.058888964 | HG11: 124.8 | HH11: =(HG11-HB11)/HB11 -> 0.030127941 | HI11: =HH11*HF11 -> 0.0017742032 | HJ11: =HG11*$L11 -> 112907.95 | HK11: =HJ11/$HJ$19 -> 0.06263556 | HL11: 129.3 | HM11: =(HL11-HG11)/HG11 -> 0.036057692 | HN11: =HM11*HM11 -> 0.0013001572 | HO11: =HL11*$L11 -> 116979.15 | HP11: =HO11/$HO$19 -> 0.063532686
B12: 6 | C12: Indian Bank | D12: INDIANB | E12: 852 | F12: 114741 | G12: =(F12/$F$19) -> 0.060795474 | H12: 9.36 | I12: 839.65 | J12: =(I12-E12)/E12 -> -0.014495305 | K12: =G12*J12 -> -0.00088124895 | L12: =F12/E12 -> 134.67254 | M12: =L12*I12 -> 113077.79 | N12: =(M12/$M$19) -> 0.063181355 | O12: 821.4 | P12: =(O12-I12)/I12 -> -0.021735247 | Q12: =N12*P12 -> -0.0013732624 | R12: =O12*L12 -> 110620.02 | S12: =R12/$R$19 -> 0.062353212 | T12: 813.95 | U12: =(T12-O12)/O12 -> -0.0090698807 | V12: =U12*S12 -> -0.0005655362 | W12: =T12*$L12 -> 109616.71 | X12: =W12/$W$19 -> 0.061883581 | Y12: 831.75 | Z12: =(Y12-T12)/T12 -> 0.021868665 | AA12: =Z12*X12 -> 0.0013533113 | AB12: =Y12*$L12 -> 112013.88 | AC12: =AB12/$AB$19 -> 0.062515302 | AD12: 820.6 | AE12: =(AD12-Y12)/Y12 -> -0.01340547 | AF12: =AE12*AC12 -> -0.00083804703 | AG12: =AD12*$L12 -> 110512.28 | AH12: =AG12/$AG$19 -> 0.062734493 | AI12: 810 | AJ12: =(AI12-AD12)/AD12 -> -0.012917378 | AK12: =AJ12*AH12 -> -0.00081036513 | AL12: =AI12*$L12 -> 109084.75 | AM12: =AL12/$AL$19 -> 0.063220426 | AN12: 817.1 | AO12: =(AN12-AI12)/AI12 -> 0.0087654321 | AP12: =AO12*AM12 -> 0.00055415435 | AQ12: =AN12*$L12 -> 110040.93 | AR12: =AQ12/$AQ$19 -> 0.063108925 | AS12: 810.2 | AT12: =(AS12-AN12)/AN12 -> -0.0084444988 | AU12: =AT12*AR12 -> -0.00053292324 | AV12: =AS12*$L12 -> 109111.69 | AW12: =AV12/$AV$19 -> 0.06253091 | AX12: 818.95 | AY12: =(AX12-AS12)/AS12 -> 0.010799803 | AZ12: =AY12*AW12 -> 0.00067532148 | BA12: =AX12*$L12 -> 110290.07 | BB12: =BA12/$BA$19 -> 0.063064257 | BC12: 825.95 | BD12: =(BC12-AX12)/AX12 -> 0.0085475304 | BE12: =BD12*BB12 -> 0.00053904365 | BF12: =BC12*$L12 -> 111232.78 | BG12: =BF12/$BF$19 -> 0.06363538 | BH12: 840.15 | BI12: =(BH12-BC12)/BC12 -> 0.017192324 | BJ12: =BI12*BG12 -> 0.0010940401 | BK12: =BH12*$L12 -> 113145.13 | BL12: =BK12/$BK$19 -> 0.063104355 | BM12: 835.5 | BN12: =(BM12-BH12)/BH12 -> -0.0055347259 | BO12: =BN12*BL12 -> -0.00034926531 | BP12: =BM12*$L12 -> 112518.9 | BQ12: =BP12/$BP$19 -> 0.062956566 | BR12: 833.35 | BS12: =(BR12-BM12)/BM12 -> -0.0025733094 | BT12: =BS12*BQ12 -> -0.00016200672 | BU12: =BR12*$L12 -> 112229.36 | BV12: =BU12/$BU$19 -> 0.062687539 | BW12: 833 | BX12: =(BW12-BR12)/BR12 -> -0.0004199916 | BY12: =BX12*BV12 -> -2.632824e-05 | BZ12: =BW12*$L12 -> 112182.22 | CA12: =BZ12/$BZ$19 -> 0.063165317 | CB12: 809.75 | CC12: =(CB12-BW12)/BW12 -> -0.027911164 | CD12: =CC12*CA12 -> -0.0017630176 | CE12: =CB12*$L12 -> 109051.09 | CF12: =CE12/$CE$19 -> 0.06240886 | CG12: 878.3 | CH12: =(CG12-CB12)/CB12 -> 0.084655758 | CI12: =CH12*CF12 -> 0.0052832693 | CJ12: =CG12*$L12 -> 118282.89 | CK12: =CJ12/$CJ$19 -> 0.066854312 | CL12: 847.9 | CM12: =(CL12-CG12)/CG12 -> -0.034612319 | CN12: =CM12*CK12 -> -0.0023139828 | CO12: =CL12*$L12 -> 114188.84 | CP12: =CO12/$CO$19 -> 0.064620458 | CQ12: 848.25 | CR12: =(CQ12-CL12)/CL12 -> 0.00041278453 | CS12: =CR12*CP12 -> 2.6674325e-05 | CT12: =CQ12*$L12 -> 114235.98 | CU12: =CT12/$CT$19 -> 0.063683939 | CV12: 842.05 | CW12: =(CV12-CQ12)/CQ12 -> -0.0073091659 | CX12: =CW12*CW12 -> 5.3423907e-05 | CY12: =CV12*$L12 -> 113401.01 | CZ12: =CY12/$CY$19 -> 0.063306459 | DA12: 843 | DB12: =(DA12-CV12)/CV12 -> 0.001128199 | DC12: =DB12*CZ12 -> 7.1422286e-05 | DD12: =DA12*$L12 -> 113528.95 | DE12: =DD12/$DD$19 -> 0.063594086 | DF12: 874.95 | DG12: =(DF12-DA12)/DA12 -> 0.037900356 | DH12: =DG12*DE12 -> 0.0024102385 | DI12: =DF12*$L12 -> 117831.73 | DJ12: =DI12/$DI$19 -> 0.064017046 | DK12: 833.45 | DL12: =(DK12-DF12)/DF12 -> -0.047431282 | DM12: =DL12*DJ12 -> -0.0030364106 | DN12: =DK12*$L12 -> 112242.82 | DO12: =DN12/$DN$19 -> 0.061618382 | DP12: 825.65 | DQ12: =(DP12-DK12)/DK12 -> -0.0093586898 | DR12: =DQ12*DO12 -> -0.00057666732 | DS12: =DP12*$L12 -> 111192.38 | DT12: =DS12/$DS$19 -> 0.061514849 | DU12: 845.5 | DV12: =(DU12-DP12)/DP12 -> 0.024041664 | DW12: =DV12*DV12 -> 0.00057800161 | DX12: =DU12*$L12 -> 113865.63 | DY12: =DX12/$DX$19 -> 0.061782481 | DZ12: 849.6 | EA12: =(DZ12-DU12)/DU12 -> 0.0048492017 | EB12: =EA12*DY12 -> 0.00029959571 | EC12: =DZ12*$L12 -> 114417.79 | ED12: =EC12/$EC$19 -> 0.061718453 | EE12: 853.3 | EF12: =(EE12-DZ12)/DZ12 -> 0.0043549906 | EG12: =EF12*ED12 -> 0.00026878328 | EH12: =EE12*$L12 -> 114916.07 | EI12: =EH12/$EH$19 -> 0.062164217 | EJ12: 876.35 | EK12: =(EJ12-EE12)/EE12 -> 0.027012774 | EL12: =EK12*EI12 -> 0.0016792279 | EM12: =EJ12*$L12 -> 118020.28 | EN12: =EM12/$EM$19 -> 0.062733467 | EO12: 875.7 | EP12: =(EO12-EJ12)/EJ12 -> -0.00074171279 | EQ12: =EP12*EN12 -> -4.6530215e-05 | ER12: =EO12*$L12 -> 117932.74 | ES12: =ER12/$ER$19 -> 0.062167107 | ET12: 870.65 | EU12: =(ET12-EO12)/EO12 -> -0.0057668151 | EV12: =EU12*EU12 -> 3.3256157e-05 | EW12: =ET12*$L12 -> 117252.64 | EX12: =EW12/$EW$19 -> 0.062204099 | EY12: 861.1 | EZ12: =(EY12-ET12)/ET12 -> -0.010968816 | FA12: =EZ12*EX12 -> -0.00068230534 | FB12: =EY12*$L12 -> 115966.52 | FC12: =FB12/$FB$19 -> 0.061220574 | FD12: 846.4 | FE12: =(FD12-EY12)/EY12 -> -0.017071188 | FF12: =FE12*FC12 -> -0.0010451079 | FG12: =FD12*$L12 -> 113986.83 | FH12: =FG12/$FG$19 -> 0.061266987 | FI12: 843.65 | FJ12: =(FI12-FD12)/FD12 -> -0.0032490548 | FK12: =FJ12*FH12 -> -0.0001990598 | FL12: =FI12*$L12 -> 113616.48 | FM12: =FL12/$FL$19 -> 0.060711854 | FN12: 832.6 | FO12: =(FN12-FI12)/FI12 -> -0.013097849 | FP12: =FO12*FM12 -> -0.00079519467 | FQ12: =FN12*$L12 -> 112128.35 | FR12: =FQ12/$FQ$19 -> 0.059731023 | FS12: 814.7 | FT12: =(FS12-FN12)/FN12 -> -0.021498919 | FU12: =FT12*FR12 -> -0.0012841524 | FV12: =FS12*$L12 -> 109717.71 | FW12: =FV12/$FQ$19 -> 0.05844687 | FX12: 816.65 | FY12: =(FX12-FS12)/FS12 -> 0.0023935191 | FZ12: =FY12*FW12 -> 0.0001398937 | GA12: =FX12*$L12 -> 109980.33 | GB12: =GA12/$GA$19 -> 0.059529812 | GC12: 820.95 | GD12: =(GC12-FX12)/FX12 -> 0.0052654136 | GE12: =GD12*GB12 -> 0.00031344908 | GF12: =GC12*$L12 -> 110559.42 | GG12: =GF12/$GF$19 -> 0.05940135 | GH12: 815.1 | GI12: =(GH12-GC12)/GC12 -> -0.0071258907 | GJ12: =GI12*GG12 -> -0.00042328753 | GK12: =GH12*$L12 -> 109771.58 | GL12: =GK12/$GK$19 -> 0.058867788 | GM12: 798.95 | GN12: =(GM12-GH12)/GH12 -> -0.01981352 | GO12: =GN12*GN12 -> 0.00039257557 | GP12: =GM12*$L12 -> 107596.62 | GQ12: =GP12/$GP$19 -> 0.058532977 | GR12: 786.9 | GS12: =(GR12-GM12)/GM12 -> -0.015082296 | GT12: =GS12*GQ12 -> -0.00088281166 | GU12: =GR12*$L12 -> 105973.82 | GV12: =GU12/$GU$19 -> 0.057981587 | GW12: 785.95 | GX12: =(GW12-GR12)/GR12 -> -0.001207269 | GY12: =GX12*GV12 -> -6.9999374e-05 | GZ12: =GW12*$L12 -> 105845.88 | HA12: =GZ12/$GZ$19 -> 0.058073181 | HB12: 772.4 | HC12: =(HB12-GW12)/GW12 -> -0.017240282 | HD12: =HC12*HA12 -> -0.0010011981 | HE12: =HB12*$L12 -> 104021.07 | HF12: =HE12/$GF$19 -> 0.055888425 | HG12: 793.15 | HH12: =(HG12-HB12)/HB12 -> 0.026864319 | HI12: =HH12*HF12 -> 0.0015014045 | HJ12: =HG12*$L12 -> 106815.52 | HK12: =HJ12/$HJ$19 -> 0.059255794 | HL12: 870.7 | HM12: =(HL12-HG12)/HG12 -> 0.097774696 | HN12: =HM12*HM12 -> 0.0095598911 | HO12: =HL12*$L12 -> 117259.38 | HP12: =HO12/$HO$19 -> 0.063684882
B13: 7 | C13: Bank of India (BOI) | D13: BANKINDIA | E13: 140 | F13: 63678 | G13: =(F13/$F$19) -> 0.033739763 | H13: 6.25 | I13: 143.86 | J13: =(I13-E13)/E13 -> 0.027571429 | K13: =G13*J13 -> 0.00093025347 | L13: =F13/E13 -> 454.84286 | M13: =L13*I13 -> 65433.693 | N13: =(M13/$M$19) -> 0.036560577 | O13: 140.14 | P13: =(O13-I13)/I13 -> -0.025858474 | Q13: =N13*P13 -> -0.00094540072 | R13: =O13*L13 -> 63741.678 | S13: =R13/$R$19 -> 0.035929286 | T13: 140.59 | U13: =(T13-O13)/O13 -> 0.0032110746 | V13: =U13*S13 -> 0.00011537162 | W13: =T13*$L13 -> 63946.357 | X13: =W13/$W$19 -> 0.036100605 | Y13: 143.95 | Z13: =(Y13-T13)/T13 -> 0.023899282 | AA13: =Z13*X13 -> 0.00086277854 | AB13: =Y13*$L13 -> 65474.629 | AC13: =AB13/$AB$19 -> 0.036541598 | AD13: 142.26 | AE13: =(AD13-Y13)/Y13 -> -0.011740188 | AF13: =AE13*AC13 -> -0.00042900521 | AG13: =AD13*$L13 -> 64705.945 | AH13: =AG13/$AG$19 -> 0.036731615 | AI13: 138.22 | AJ13: =(AI13-AD13)/AD13 -> -0.028398707 | AK13: =AJ13*AH13 -> -0.0010431304 | AL13: =AI13*$L13 -> 62868.38 | AM13: =AL13/$AL$19 -> 0.036435575 | AN13: 138.64 | AO13: =(AN13-AI13)/AI13 -> 0.0030386341 | AP13: =AO13*AM13 -> 0.00011071438 | AQ13: =AN13*$L13 -> 63059.414 | AR13: =AQ13/$AQ$19 -> 0.036164833 | AS13: 139.2 | AT13: =(AS13-AN13)/AN13 -> 0.0040392383 | AU13: =AT13*AR13 -> 0.00014607838 | AV13: =AS13*$L13 -> 63314.126 | AW13: =AV13/$AV$19 -> 0.036284746 | AX13: 139.23 | AY13: =(AX13-AS13)/AS13 -> 0.00021551724 | AZ13: =AY13*AW13 -> 7.8199884e-06 | BA13: =AX13*$L13 -> 63327.771 | BB13: =BA13/$BA$19 -> 0.036211045 | BC13: 139.92 | BD13: =(BC13-AX13)/AX13 -> 0.0049558285 | BE13: =BD13*BB13 -> 0.00017945573 | BF13: =BC13*$L13 -> 63641.613 | BG13: =BF13/$BF$19 -> 0.036408855 | BH13: 146.01 | BI13: =(BH13-BC13)/BC13 -> 0.043524871 | BJ13: =BI13*BG13 -> 0.0015846907 | BK13: =BH13*$L13 -> 66411.606 | BL13: =BK13/$BK$19 -> 0.037039698 | BM13: 145.05 | BN13: =(BM13-BH13)/BH13 -> -0.0065748921 | BO13: =BN13*BL13 -> -0.00024353202 | BP13: =BM13*$L13 -> 65974.956 | BQ13: =BP13/$BP$19 -> 0.036914301 | BR13: 147 | BS13: =(BR13-BM13)/BM13 -> 0.01344364 | BT13: =BS13*BQ13 -> 0.00049626258 | BU13: =BR13*$L13 -> 66861.9 | BV13: =BU13/$BU$19 -> 0.037346805 | BW13: 139.91 | BX13: =(BW13-BR13)/BR13 -> -0.048231293 | BY13: =BX13*BV13 -> -0.0018012847 | BZ13: =BW13*$L13 -> 63637.064 | CA13: =BZ13/$BZ$19 -> 0.035831483 | CB13: 136.74 | CC13: =(CB13-BW13)/BW13 -> -0.022657423 | CD13: =CC13*CA13 -> -0.00081184905 | CE13: =CB13*$L13 -> 62195.212 | CF13: =CE13/$CE$19 -> 0.035593706 | CG13: 137.29 | CH13: =(CG13-CB13)/CB13 -> 0.004022232 | CI13: =CH13*CF13 -> 0.00014316614 | CJ13: =CG13*$L13 -> 62445.376 | CK13: =CJ13/$CJ$19 -> 0.035294561 | CL13: 139.69 | CM13: =(CL13-CG13)/CG13 -> 0.017481244 | CN13: =CM13*CK13 -> 0.00061699284 | CO13: =CL13*$L13 -> 63536.999 | CP13: =CO13/$CO$19 -> 0.035956139 | CQ13: 141.46 | CR13: =(CQ13-CL13)/CL13 -> 0.012670914 | CS13: =CR13*CP13 -> 0.00045559716 | CT13: =CQ13*$L13 -> 64342.071 | CU13: =CT13/$CT$19 -> 0.035869229 | CV13: 141.46 | CW13: =(CV13-CQ13)/CQ13 -> 0 | CX13: =CW13*CW13 -> 0 | CY13: =CV13*$L13 -> 64342.071 | CZ13: =CY13/$CY$19 -> 0.035919157 | DA13: 140.08 | DB13: =(DA13-CV13)/CV13 -> -0.0097554079 | DC13: =DB13*CZ13 -> -0.00035040603 | DD13: =DA13*$L13 -> 63714.387 | DE13: =DD13/$DD$19 -> 0.035690089 | DF13: 147.72 | DG13: =(DF13-DA13)/DA13 -> 0.054540263 | DH13: =DG13*DE13 -> 0.0019465468 | DI13: =DF13*$L13 -> 67189.387 | DJ13: =DI13/$DI$19 -> 0.036503461 | DK13: 144.86 | DL13: =(DK13-DF13)/DF13 -> -0.019360953 | DM13: =DL13*DJ13 -> -0.00070674179 | DN13: =DK13*$L13 -> 65888.536 | DO13: =DN13/$DN$19 -> 0.036171087 | DP13: 141.73 | DQ13: =(DP13-DK13)/DK13 -> -0.021607069 | DR13: =DQ13*DO13 -> -0.00078155117 | DS13: =DP13*$L13 -> 64464.878 | DT13: =DS13/$DS$19 -> 0.03566384 | DU13: 145.68 | DV13: =(DU13-DP13)/DP13 -> 0.027869893 | DW13: =DV13*DV13 -> 0.00077673096 | DX13: =DU13*$L13 -> 66261.507 | DY13: =DX13/$DX$19 -> 0.035952907 | DZ13: 146.23 | EA13: =(DZ13-DU13)/DU13 -> 0.0037753981 | EB13: =EA13*DY13 -> 0.00013573654 | EC13: =DZ13*$L13 -> 66511.671 | ED13: =EC13/$EC$19 -> 0.035877267 | EE13: 145.67 | EF13: =(EE13-DZ13)/DZ13 -> -0.0038295835 | EG13: =EF13*ED13 -> -0.00013739499 | EH13: =EE13*$L13 -> 66256.959 | EI13: =EH13/$EH$19 -> 0.035841913 | EJ13: 147.14 | EK13: =(EJ13-EE13)/EE13 -> 0.010091302 | EL13: =EK13*EI13 -> 0.00036169158 | EM13: =EJ13*$L13 -> 66925.578 | EN13: =EM13/$EM$19 -> 0.035574172 | EO13: 147.67 | EP13: =(EO13-EJ13)/EJ13 -> 0.0036020117 | EQ13: =EP13*EN13 -> 0.00012813858 | ER13: =EO13*$L13 -> 67166.645 | ES13: =ER13/$ER$19 -> 0.03540625 | ET13: 146.57 | EU13: =(ET13-EO13)/EO13 -> -0.0074490418 | EV13: =EU13*EU13 -> 5.5488223e-05 | EW13: =ET13*$L13 -> 66666.318 | EX13: =EW13/$EW$19 -> 0.035367375 | EY13: 146.09 | EZ13: =(EY13-ET13)/ET13 -> -0.0032748857 | FA13: =EZ13*EX13 -> -0.00011582411 | FB13: =EY13*$L13 -> 66447.993 | FC13: =FB13/$FB$19 -> 0.035078954 | FD13: 144.51 | FE13: =(FD13-EY13)/EY13 -> -0.010815251 | FF13: =FE13*FC13 -> -0.00037938769 | FG13: =FD13*$L13 -> 65729.341 | FH13: =FG13/$FG$19 -> 0.035328981 | FI13: 144.15 | FJ13: =(FI13-FD13)/FD13 -> -0.0024911771 | FK13: =FJ13*FH13 -> -8.8010747e-05 | FL13: =FI13*$L13 -> 65565.598 | FM13: =FL13/$FL$19 -> 0.035035488 | FN13: 144.72 | FO13: =(FN13-FI13)/FI13 -> 0.0039542144 | FP13: =FO13*FM13 -> 0.00013853783 | FQ13: =FN13*$L13 -> 65824.858 | FR13: =FQ13/$FQ$19 -> 0.035065048 | FS13: 142.55 | FT13: =(FS13-FN13)/FN13 -> -0.014994472 | FU13: =FT13*FR13 -> -0.00052578189 | FV13: =FS13*$L13 -> 64837.849 | FW13: =FV13/$FQ$19 -> 0.034539266 | FX13: 140.39 | FY13: =(FX13-FS13)/FS13 -> -0.015152578 | FZ13: =FY13*FW13 -> -0.00052335893 | GA13: =FX13*$L13 -> 63855.389 | GB13: =GA13/$GA$19 -> 0.034563448 | GC13: 141.63 | GD13: =(GC13-FX13)/FX13 -> 0.0088325379 | GE13: =GD13*GB13 -> 0.00030528297 | GF13: =GC13*$L13 -> 64419.394 | GG13: =GF13/$GF$19 -> 0.034611244 | GH13: 144.96 | GI13: =(GH13-GC13)/GC13 -> 0.023511968 | GJ13: =GI13*GG13 -> 0.00081377844 | GK13: =GH13*$L13 -> 65934.021 | GL13: =GK13/$GK$19 -> 0.035358786 | GM13: 144.05 | GN13: =(GM13-GH13)/GH13 -> -0.0062775938 | GO13: =GN13*GN13 -> 3.9408184e-05 | GP13: =GM13*$L13 -> 65520.114 | GQ13: =GP13/$GP$19 -> 0.035643195 | GR13: 139.8 | GS13: =(GR13-GM13)/GM13 -> -0.029503645 | GT13: =GS13*GQ13 -> -0.0010516041 | GU13: =GR13*$L13 -> 63587.031 | GV13: =GU13/$GU$19 -> 0.034790451 | GW13: 142.41 | GX13: =(GW13-GR13)/GR13 -> 0.018669528 | GY13: =GX13*GV13 -> 0.0006495213 | GZ13: =GW13*$L13 -> 64774.171 | HA13: =GZ13/$GZ$19 -> 0.035538863 | HB13: 135.12 | HC13: =(HB13-GW13)/GW13 -> -0.051190225 | HD13: =HC13*HA13 -> -0.0018192424 | HE13: =HB13*$L13 -> 61458.367 | HF13: =HE13/$GF$19 -> 0.033020343 | HG13: 138.53 | HH13: =(HG13-HB13)/HB13 -> 0.025236827 | HI13: =HH13*HF13 -> 0.00083332868 | HJ13: =HG13*$L13 -> 63009.381 | HK13: =HJ13/$HJ$19 -> 0.034954385 | HL13: 144.9 | HM13: =(HL13-HG13)/HG13 -> 0.04598282 | HN13: =HM13*HM13 -> 0.0021144197 | HO13: =HL13*$L13 -> 65906.73 | HP13: =HO13/$HO$19 -> 0.035794684
B14: 8 | C14: Indian Overseas Bank (IOB) | D14: IOB | E14: 35 | F14: 67398 | G14: =(F14/$F$19) -> 0.035710804 | H14: 12.9 | I14: 34.29 | J14: =(I14-E14)/E14 -> -0.020285714 | K14: =G14*J14 -> -0.00072441916 | L14: =F14/E14 -> 1925.6571 | M14: =L14*I14 -> 66030.783 | N14: =(M14/$M$19) -> 0.036894197 | O14: 33.65 | P14: =(O14-I14)/I14 -> -0.018664334 | Q14: =N14*P14 -> -0.0006886056 | R14: =O14*L14 -> 64798.363 | S14: =R14/$R$19 -> 0.036524908 | T14: 33.68 | U14: =(T14-O14)/O14 -> 0.00089153046 | V14: =U14*S14 -> 3.2563068e-05 | W14: =T14*$L14 -> 64856.133 | X14: =W14/$W$19 -> 0.036614215 | Y14: 33.82 | Z14: =(Y14-T14)/T14 -> 0.0041567696 | AA14: =Z14*X14 -> 0.00015219685 | AB14: =Y14*$L14 -> 65125.725 | AC14: =AB14/$AB$19 -> 0.036346873 | AD14: 33.79 | AE14: =(AD14-Y14)/Y14 -> -0.00088704908 | AF14: =AE14*AC14 -> -3.2241461e-05 | AG14: =AD14*$L14 -> 65067.955 | AH14: =AG14/$AG$19 -> 0.036937118 | AI14: 33.43 | AJ14: =(AI14-AD14)/AD14 -> -0.01065404 | AK14: =AJ14*AH14 -> -0.00039352952 | AL14: =AI14*$L14 -> 64374.718 | AM14: =AL14/$AL$19 -> 0.037308579 | AN14: 33.54 | AO14: =(AN14-AI14)/AI14 -> 0.0032904577 | AP14: =AO14*AM14 -> 0.0001227623 | AQ14: =AN14*$L14 -> 64586.541 | AR14: =AQ14/$AQ$19 -> 0.037040646 | AS14: 33.49 | AT14: =(AS14-AN14)/AN14 -> -0.0014907573 | AU14: =AT14*AR14 -> -5.5218614e-05 | AV14: =AS14*$L14 -> 64490.258 | AW14: =AV14/$AV$19 -> 0.036958777 | AX14: 33.77 | AY14: =(AX14-AS14)/AS14 -> 0.0083607047 | AZ14: =AY14*AW14 -> 0.00030900142 | BA14: =AX14*$L14 -> 65029.442 | BB14: =BA14/$BA$19 -> 0.037184067 | BC14: 33.43 | BD14: =(BC14-AX14)/AX14 -> -0.010068108 | BE14: =BD14*BB14 -> -0.00037437319 | BF14: =BC14*$L14 -> 64374.718 | BG14: =BF14/$BF$19 -> 0.036828259 | BH14: 33.79 | BI14: =(BH14-BC14)/BC14 -> 0.010768771 | BJ14: =BI14*BG14 -> 0.00039659507 | BK14: =BH14*$L14 -> 65067.955 | BL14: =BK14/$BK$19 -> 0.036290305 | BM14: 33.71 | BN14: =(BM14-BH14)/BH14 -> -0.0023675644 | BO14: =BN14*BL14 -> -8.5919633e-05 | BP14: =BM14*$L14 -> 64913.902 | BQ14: =BP14/$BP$19 -> 0.03632062 | BR14: 33.88 | BS14: =(BR14-BM14)/BM14 -> 0.0050430139 | BT14: =BS14*BQ14 -> 0.0001831654 | BU14: =BR14*$L14 -> 65241.264 | BV14: =BU14/$BU$19 -> 0.036441573 | BW14: 33.42 | BX14: =(BW14-BR14)/BR14 -> -0.013577332 | BY14: =BX14*BV14 -> -0.00049477932 | BZ14: =BW14*$L14 -> 64355.462 | CA14: =BZ14/$BZ$19 -> 0.036235984 | CB14: 32.95 | CC14: =(CB14-BW14)/BW14 -> -0.014063435 | CD14: =CC14*CA14 -> -0.0005096024 | CE14: =CB14*$L14 -> 63450.403 | CF14: =CE14/$CE$19 -> 0.036312039 | CG14: 32.79 | CH14: =(CG14-CB14)/CB14 -> -0.0048558422 | CI14: =CH14*CF14 -> -0.00017632553 | CJ14: =CG14*$L14 -> 63142.298 | CK14: =CJ14/$CJ$19 -> 0.035688466 | CL14: 33.01 | CM14: =(CL14-CG14)/CG14 -> 0.0067093626 | CN14: =CM14*CK14 -> 0.00023944686 | CO14: =CL14*$L14 -> 63565.942 | CP14: =CO14/$CO$19 -> 0.035972519 | CQ14: 32.92 | CR14: =(CQ14-CL14)/CL14 -> -0.0027264465 | CS14: =CR14*CP14 -> -9.8077149e-05 | CT14: =CQ14*$L14 -> 63392.633 | CU14: =CT14/$CT$19 -> 0.03533994 | CV14: 32.93 | CW14: =(CV14-CQ14)/CQ14 -> 0.00030376671 | CX14: =CW14*CW14 -> 9.2274212e-08 | CY14: =CV14*$L14 -> 63411.89 | CZ14: =CY14/$CY$19 -> 0.035399881 | DA14: 32.71 | DB14: =(DA14-CV14)/CV14 -> -0.0066808381 | DC14: =DB14*CZ14 -> -0.00023650088 | DD14: =DA14*$L14 -> 62988.245 | DE14: =DD14/$DD$19 -> 0.035283335 | DF14: 33.43 | DG14: =(DF14-DA14)/DA14 -> 0.022011617 | DH14: =DG14*DE14 -> 0.00077664327 | DI14: =DF14*$L14 -> 64374.718 | DJ14: =DI14/$DI$19 -> 0.034974273 | DK14: 33.43 | DL14: =(DK14-DF14)/DF14 -> 0 | DM14: =DL14*DJ14 -> 0 | DN14: =DK14*$L14 -> 64374.718 | DO14: =DN14/$DN$19 -> 0.035340041 | DP14: 32.42 | DQ14: =(DP14-DK14)/DK14 -> -0.030212384 | DR14: =DQ14*DO14 -> -0.0010677069 | DS14: =DP14*$L14 -> 62429.805 | DT14: =DS14/$DS$19 -> 0.034537979 | DU14: 33.37 | DV14: =(DU14-DP14)/DP14 -> 0.029302899 | DW14: =DV14*DV14 -> 0.00085865992 | DX14: =DU14*$L14 -> 64259.179 | DY14: =DX14/$DX$19 -> 0.034866461 | DZ14: 33.84 | EA14: =(DZ14-DU14)/DU14 -> 0.014084507 | EB14: =EA14*DY14 -> 0.00049107692 | EC14: =DZ14*$L14 -> 65164.238 | ED14: =EC14/$EC$19 -> 0.035150444 | EE14: 34.03 | EF14: =(EE14-DZ14)/DZ14 -> 0.0056146572 | EG14: =EF14*ED14 -> 0.00019735769 | EH14: =EE14*$L14 -> 65530.113 | EI14: =EH14/$EH$19 -> 0.035448723 | EJ14: 35.58 | EK14: =(EJ14-EE14)/EE14 -> 0.045548046 | EL14: =EK14*EI14 -> 0.0016146201 | EM14: =EJ14*$L14 -> 68514.881 | EN14: =EM14/$EM$19 -> 0.036418963 | EO14: 35.23 | EP14: =(EO14-EJ14)/EJ14 -> -0.0098369871 | EQ14: =EP14*EN14 -> -0.00035825287 | ER14: =EO14*$L14 -> 67840.901 | ES14: =ER14/$ER$19 -> 0.035761677 | ET14: 35.09 | EU14: =(ET14-EO14)/EO14 -> -0.0039738859 | EV14: =EU14*EU14 -> 1.5791769e-05 | EW14: =ET14*$L14 -> 67571.309 | EX14: =EW14/$EW$19 -> 0.035847485 | EY14: 35.38 | EZ14: =(EY14-ET14)/ET14 -> 0.0082644628 | FA14: =EZ14*EX14 -> 0.00029626021 | FB14: =EY14*$L14 -> 68129.75 | FC14: =FB14/$FB$19 -> 0.035966781 | FD14: 34.95 | FE14: =(FD14-EY14)/EY14 -> -0.012153759 | FF14: =FE14*FC14 -> -0.00043713159 | FG14: =FD14*$L14 -> 67301.717 | FH14: =FG14/$FG$19 -> 0.03617412 | FI14: 34.9 | FJ14: =(FI14-FD14)/FD14 -> -0.0014306152 | FK14: =FJ14*FH14 -> -5.1751245e-05 | FL14: =FI14*$L14 -> 67205.434 | FM14: =FL14/$FL$19 -> 0.035911748 | FN14: 34.47 | FO14: =(FN14-FI14)/FI14 -> -0.012320917 | FP14: =FO14*FM14 -> -0.00044246566 | FQ14: =FN14*$L14 -> 66377.402 | FR14: =FQ14/$FQ$19 -> 0.035359389 | FS14: 34.01 | FT14: =(FS14-FN14)/FN14 -> -0.013344938 | FU14: =FT14*FR14 -> -0.00047186885 | FV14: =FS14*$L14 -> 65491.599 | FW14: =FV14/$FQ$19 -> 0.034887521 | FX14: 34.1 | FY14: =(FX14-FS14)/FS14 -> 0.0026462805 | FZ14: =FY14*FW14 -> 9.2322165e-05 | GA14: =FX14*$L14 -> 65664.909 | GB14: =GA14/$GA$19 -> 0.0355429 | GC14: 34.18 | GD14: =(GC14-FX14)/FX14 -> 0.0023460411 | GE14: =GD14*GB14 -> 8.3385102e-05 | GF14: =GC14*$L14 -> 65818.961 | GG14: =GF14/$GF$19 -> 0.035363203 | GH14: 34.45 | GI14: =(GH14-GC14)/GC14 -> 0.0078993563 | GJ14: =GI14*GG14 -> 0.00027934654 | GK14: =GH14*$L14 -> 66338.889 | GL14: =GK14/$GK$19 -> 0.035575907 | GM14: 34.37 | GN14: =(GM14-GH14)/GH14 -> -0.0023222061 | GO14: =GN14*GN14 -> 5.3926412e-06 | GP14: =GM14*$L14 -> 66184.836 | GQ14: =GP14/$GP$19 -> 0.036004806 | GR14: 34.2 | GS14: =(GR14-GM14)/GM14 -> -0.004946174 | GT14: =GS14*GQ14 -> -0.00017808604 | GU14: =GR14*$L14 -> 65857.474 | GV14: =GU14/$GU$19 -> 0.036032682 | GW14: 34.03 | GX14: =(GW14-GR14)/GR14 -> -0.0049707602 | GY14: =GX14*GV14 -> -0.00017910982 | GZ14: =GW14*$L14 -> 65530.113 | HA14: =GZ14/$GZ$19 -> 0.035953616 | HB14: 33.47 | HC14: =(HB14-GW14)/GW14 -> -0.016456068 | HD14: =HC14*HA14 -> -0.00059165516 | HE14: =HB14*$L14 -> 64451.745 | HF14: =HE14/$GF$19 -> 0.034628625 | HG14: 33.76 | HH14: =(HG14-HB14)/HB14 -> 0.0086644756 | HI14: =HH14*HF14 -> 0.00030003888 | HJ14: =HG14*$L14 -> 65010.185 | HK14: =HJ14/$HJ$19 -> 0.036064329 | HL14: 33.8 | HM14: =(HL14-HG14)/HG14 -> 0.0011848341 | HN14: =HM14*HM14 -> 1.4038319e-06 | HO14: =HL14*$L14 -> 65087.211 | HP14: =HO14/$HO$19 -> 0.035349594
B15: 9 | C15: Bank of Maharashtra | D15: MAHABANK | E15: 78.4 | F15: 60279 | G15: =(F15/$F$19) -> 0.031938804 | H15: 8.59 | I15: 81.42 | J15: =(I15-E15)/E15 -> 0.038520408 | K15: =G15*J15 -> 0.0012302958 | L15: =F15/E15 -> 768.8648 | M15: =L15*I15 -> 62600.972 | N15: =(M15/$M$19) -> 0.034977816 | O15: 78.37 | P15: =(O15-I15)/I15 -> -0.037460084 | Q15: =N15*P15 -> -0.0013102719 | R15: =O15*L15 -> 60255.934 | S15: =R15/$R$19 -> 0.033964476 | T15: 79.97 | U15: =(T15-O15)/O15 -> 0.020415976 | V15: =U15*S15 -> 0.00069341791 | W15: =T15*$L15 -> 61486.118 | X15: =W15/$W$19 -> 0.034711689 | Y15: 78.5 | Z15: =(Y15-T15)/T15 -> -0.018381893 | AA15: =Z15*X15 -> -0.00063806656 | AB15: =Y15*$L15 -> 60355.886 | AC15: =AB15/$AB$19 -> 0.033684811 | AD15: 78.02 | AE15: =(AD15-Y15)/Y15 -> -0.0061146497 | AF15: =AE15*AC15 -> -0.00020597082 | AG15: =AD15*$L15 -> 59986.831 | AH15: =AG15/$AG$19 -> 0.034052717 | AI15: 77.8 | AJ15: =(AI15-AD15)/AD15 -> -0.0028197898 | AK15: =AJ15*AH15 -> -9.6021504e-05 | AL15: =AI15*$L15 -> 59817.681 | AM15: =AL15/$AL$19 -> 0.034667533 | AN15: 78.34 | AO15: =(AN15-AI15)/AI15 -> 0.006940874 | AP15: =AO15*AM15 -> 0.00024062298 | AQ15: =AN15*$L15 -> 60232.868 | AR15: =AQ15/$AQ$19 -> 0.034543797 | AS15: 78.75 | AT15: =(AS15-AN15)/AN15 -> 0.0052335971 | AU15: =AT15*AR15 -> 0.00018078832 | AV15: =AS15*$L15 -> 60548.103 | AW15: =AV15/$AV$19 -> 0.034699564 | AX15: 79.76 | AY15: =(AX15-AS15)/AS15 -> 0.012825397 | AZ15: =AY15*AW15 -> 0.00044503567 | BA15: =AX15*$L15 -> 61324.656 | BB15: =BA15/$BA$19 -> 0.035065657 | BC15: 80.04 | BD15: =(BC15-AX15)/AX15 -> 0.0035105316 | BE15: =BD15*BB15 -> 0.0001230991 | BF15: =BC15*$L15 -> 61539.938 | BG15: =BF15/$BF$19 -> 0.035206504 | BH15: 80.87 | BI15: =(BH15-BC15)/BC15 -> 0.010369815 | BJ15: =BI15*BG15 -> 0.00036508494 | BK15: =BH15*$L15 -> 62178.096 | BL15: =BK15/$BK$19 -> 0.034678546 | BM15: 80.15 | BN15: =(BM15-BH15)/BH15 -> -0.0089031779 | BO15: =BN15*BL15 -> -0.00030874927 | BP15: =BM15*$L15 -> 61624.513 | BQ15: =BP15/$BP$19 -> 0.034480142 | BR15: 80.08 | BS15: =(BR15-BM15)/BM15 -> -0.00087336245 | BT15: =BS15*BQ15 -> -3.0113661e-05 | BU15: =BR15*$L15 -> 61570.693 | BV15: =BU15/$BU$19 -> 0.034391315 | BW15: 79.27 | BX15: =(BW15-BR15)/BR15 -> -0.010114885 | BY15: =BX15*BV15 -> -0.0003478642 | BZ15: =BW15*$L15 -> 60947.912 | CA15: =BZ15/$BZ$19 -> 0.034317329 | CB15: 77.64 | CC15: =(CB15-BW15)/BW15 -> -0.020562634 | CD15: =CC15*CA15 -> -0.00070565468 | CE15: =CB15*$L15 -> 59694.663 | CF15: =CE15/$CE$19 -> 0.034162666 | CG15: 80.5 | CH15: =(CG15-CB15)/CB15 -> 0.036836682 | CI15: =CH15*CF15 -> 0.0012584393 | CJ15: =CG15*$L15 -> 61893.616 | CK15: =CJ15/$CJ$19 -> 0.034982703 | CL15: 79.74 | CM15: =(CL15-CG15)/CG15 -> -0.0094409938 | CN15: =CM15*CK15 -> -0.00033027148 | CO15: =CL15*$L15 -> 61309.279 | CP15: =CO15/$CO$19 -> 0.034695453 | CQ15: 79.9 | CR15: =(CQ15-CL15)/CL15 -> 0.0020065212 | CS15: =CR15*CP15 -> 6.9617163e-05 | CT15: =CQ15*$L15 -> 61432.297 | CU15: =CT15/$CT$19 -> 0.034247097 | CV15: 79.19 | CW15: =(CV15-CQ15)/CQ15 -> -0.0088861076 | CX15: =CW15*CW15 -> 7.8962909e-05 | CY15: =CV15*$L15 -> 60886.403 | CZ15: =CY15/$CY$19 -> 0.03399002 | DA15: 79.61 | DB15: =(DA15-CV15)/CV15 -> 0.0053037 | DC15: =DB15*CZ15 -> 0.00018027287 | DD15: =DA15*$L15 -> 61209.326 | DE15: =DD15/$DD$19 -> 0.034286861 | DF15: 83.97 | DG15: =(DF15-DA15)/DA15 -> 0.054766989 | DH15: =DG15*DE15 -> 0.0018777881 | DI15: =DF15*$L15 -> 64561.577 | DJ15: =DI15/$DI$19 -> 0.035075792 | DK15: 84.18 | DL15: =(DK15-DF15)/DF15 -> 0.0025008932 | DM15: =DL15*DJ15 -> 8.7720809e-05 | DN15: =DK15*$L15 -> 64723.039 | DO15: =DN15/$DN$19 -> 0.035531259 | DP15: 83.72 | DQ15: =(DP15-DK15)/DK15 -> -0.0054644809 | DR15: =DQ15*DO15 -> -0.00019415989 | DS15: =DP15*$L15 -> 64369.361 | DT15: =DS15/$DS$19 -> 0.035610997 | DU15: 87.3 | DV15: =(DU15-DP15)/DP15 -> 0.042761586 | DW15: =DV15*DV15 -> 0.0018285533 | DX15: =DU15*$L15 -> 67121.897 | DY15: =DX15/$DX$19 -> 0.036419746 | DZ15: 89.12 | EA15: =(DZ15-DU15)/DU15 -> 0.020847652 | EB15: =EA15*DY15 -> 0.00075926619 | EC15: =DZ15*$L15 -> 68521.231 | ED15: =EC15/$EC$19 -> 0.03696125 | EE15: 88.19 | EF15: =(EE15-DZ15)/DZ15 -> -0.010435368 | EG15: =EF15*ED15 -> -0.00038570425 | EH15: =EE15*$L15 -> 67806.186 | EI15: =EH15/$EH$19 -> 0.036679973 | EJ15: 90.14 | EK15: =(EJ15-EE15)/EE15 -> 0.02211135 | EL15: =EK15*EI15 -> 0.00081104373 | EM15: =EJ15*$L15 -> 69305.473 | EN15: =EM15/$EM$19 -> 0.0368392 | EO15: 89.5 | EP15: =(EO15-EJ15)/EJ15 -> -0.0071000666 | EQ15: =EP15*EN15 -> -0.00026156077 | ER15: =EO15*$L15 -> 68813.399 | ES15: =ER15/$ER$19 -> 0.03627432 | ET15: 90.19 | EU15: =(ET15-EO15)/EO15 -> 0.0077094972 | EV15: =EU15*EU15 -> 5.9436347e-05 | EW15: =ET15*$L15 -> 69343.916 | EX15: =EW15/$EW$19 -> 0.036787877 | EY15: 89.47 | EZ15: =(EY15-ET15)/ET15 -> -0.0079831467 | FA15: =EZ15*EX15 -> -0.00029368302 | FB15: =EY15*$L15 -> 68790.333 | FC15: =FB15/$FB$19 -> 0.036315513 | FD15: 87.89 | FE15: =(FD15-EY15)/EY15 -> -0.017659551 | FF15: =FE15*FC15 -> -0.00064131565 | FG15: =FD15*$L15 -> 67575.527 | FH15: =FG15/$FG$19 -> 0.03632129 | FI15: 88.53 | FJ15: =(FI15-FD15)/FD15 -> 0.0072818296 | FK15: =FJ15*FH15 -> 0.00026448545 | FL15: =FI15*$L15 -> 68067.6 | FM15: =FL15/$FL$19 -> 0.036372453 | FN15: 88.71 | FO15: =(FN15-FI15)/FI15 -> 0.0020332091 | FP15: =FO15*FM15 -> 7.3952801e-05 | FQ15: =FN15*$L15 -> 68205.996 | FR15: =FQ15/$FQ$19 -> 0.036333486 | FS15: 93.85 | FT15: =(FS15-FN15)/FN15 -> 0.057941607 | FU15: =FT15*FR15 -> 0.0021052206 | FV15: =FS15*$L15 -> 72157.961 | FW15: =FV15/$FQ$19 -> 0.038438706 | FX15: 91.44 | FY15: =(FX15-FS15)/FS15 -> -0.025679275 | FZ15: =FY15*FW15 -> -0.00098707812 | GA15: =FX15*$L15 -> 70304.997 | GB15: =GA15/$GA$19 -> 0.038054472 | GC15: 91.2 | GD15: =(GC15-FX15)/FX15 -> -0.0026246719 | GE15: =GD15*GB15 -> -9.9880505e-05 | GF15: =GC15*$L15 -> 70120.469 | GG15: =GF15/$GF$19 -> 0.037674317 | GH15: 91.04 | GI15: =(GH15-GC15)/GC15 -> -0.001754386 | GJ15: =GI15*GG15 -> -6.6095292e-05 | GK15: =GH15*$L15 -> 69997.451 | GL15: =GK15/$GK$19 -> 0.037537903 | GM15: 88.53 | GN15: =(GM15-GH15)/GH15 -> -0.027570299 | GO15: =GN15*GN15 -> 0.00076012137 | GP15: =GM15*$L15 -> 68067.6 | GQ15: =GP15/$GP$19 -> 0.037029037 | GR15: 86.51 | GS15: =(GR15-GM15)/GM15 -> -0.022817124 | GT15: =GS15*GQ15 -> -0.00084489614 | GU15: =GR15*$L15 -> 66514.493 | GV15: =GU15/$GU$19 -> 0.036392157 | GW15: 83.19 | GX15: =(GW15-GR15)/GR15 -> -0.038377066 | GY15: =GX15*GV15 -> -0.0013966242 | GZ15: =GW15*$L15 -> 63961.862 | HA15: =GZ15/$GZ$19 -> 0.035093183 | HB15: 80.6 | HC15: =(HB15-GW15)/GW15 -> -0.03113355 | HD15: =HC15*HA15 -> -0.0010925754 | HE15: =HB15*$L15 -> 61970.503 | HF15: =HE15/$GF$19 -> 0.033295504 | HG15: 82.01 | HH15: =(HG15-HB15)/HB15 -> 0.017493797 | HI15: =HH15*HF15 -> 0.00058246476 | HJ15: =HG15*$L15 -> 63054.602 | HK15: =HJ15/$HJ$19 -> 0.034979471 | HL15: 84.25 | HM15: =(HL15-HG15)/HG15 -> 0.027313742 | HN15: =HM15*HM15 -> 0.00074604051 | HO15: =HL15*$L15 -> 64776.859 | HP15: =HO15/$HO$19 -> 0.035181038
B16: 10 | C16: Central Bank of India | D16: CENTRALBK | E16: 36.4 | F16: 32965 | G16: =(F16/$F$19) -> 0.017466492 | H16: 7.38 | I16: 35.64 | J16: =(I16-E16)/E16 -> -0.020879121 | K16: =G16*J16 -> -0.000364685 | L16: =F16/E16 -> 905.63187 | M16: =L16*I16 -> 32276.72 | N16: =(M16/$M$19) -> 0.018034371 | O16: 34.53 | P16: =(O16-I16)/I16 -> -0.031144781 | Q16: =N16*P16 -> -0.00056167654 | R16: =O16*L16 -> 31271.468 | S16: =R16/$R$19 -> 0.017626796 | T16: 34.38 | U16: =(T16-O16)/O16 -> -0.0043440487 | V16: =U16*S16 -> -7.6571658e-05 | W16: =T16*$L16 -> 31135.624 | X16: =W16/$W$19 -> 0.017577465 | Y16: 34.61 | Z16: =(Y16-T16)/T16 -> 0.006689936 | AA16: =Z16*X16 -> 0.00011759212 | AB16: =Y16*$L16 -> 31343.919 | AC16: =AB16/$AB$19 -> 0.01749314 | AD16: 34.15 | AE16: =(AD16-Y16)/Y16 -> -0.013290956 | AF16: =AE16*AC16 -> -0.00023250057 | AG16: =AD16*$L16 -> 30927.328 | AH16: =AG16/$AG$19 -> 0.017556512 | AI16: 33.77 | AJ16: =(AI16-AD16)/AD16 -> -0.011127379 | AK16: =AJ16*AH16 -> -0.00019535797 | AL16: =AI16*$L16 -> 30583.188 | AM16: =AL16/$AL$19 -> 0.017724587 | AN16: 34.04 | AO16: =(AN16-AI16)/AI16 -> 0.0079952621 | AP16: =AO16*AM16 -> 0.00014171272 | AQ16: =AN16*$L16 -> 30827.709 | AR16: =AQ16/$AQ$19 -> 0.017679818 | AS16: 33.85 | AT16: =(AS16-AN16)/AN16 -> -0.0055816686 | AU16: =AT16*AR16 -> -9.8682884e-05 | AV16: =AS16*$L16 -> 30655.639 | AW16: =AV16/$AV$19 -> 0.017568466 | AX16: 33.92 | AY16: =(AX16-AS16)/AS16 -> 0.0020679468 | AZ16: =AY16*AW16 -> 3.6330654e-05 | BA16: =AX16*$L16 -> 30719.033 | BB16: =BA16/$BA$19 -> 0.017565253 | BC16: 31.27 | BD16: =(BC16-AX16)/AX16 -> -0.078125 | BE16: =BD16*BB16 -> -0.0013722854 | BF16: =BC16*$L16 -> 28319.109 | BG16: =BF16/$BF$19 -> 0.016201134 | BH16: 31.27 | BI16: =(BH16-BC16)/BC16 -> 0 | BJ16: =BI16*BG16 -> 0 | BK16: =BH16*$L16 -> 28319.109 | BL16: =BK16/$BK$19 -> 0.015794397 | BM16: 31.04 | BN16: =(BM16-BH16)/BH16 -> -0.0073552926 | BO16: =BN16*BL16 -> -0.00011617241 | BP16: =BM16*$L16 -> 28110.813 | BQ16: =BP16/$BP$19 -> 0.01572856 | BR16: 30.84 | BS16: =(BR16-BM16)/BM16 -> -0.006443299 | BT16: =BS16*BQ16 -> -0.00010134381 | BU16: =BR16*$L16 -> 27929.687 | BV16: =BU16/$BU$19 -> 0.015600582 | BW16: 30.77 | BX16: =(BW16-BR16)/BR16 -> -0.0022697795 | BY16: =BX16*BV16 -> -3.5409882e-05 | BZ16: =BW16*$L16 -> 27866.293 | CA16: =BZ16/$BZ$19 -> 0.015690394 | CB16: 30.31 | CC16: =(CB16-BW16)/BW16 -> -0.014949626 | CD16: =CC16*CA16 -> -0.00023456552 | CE16: =CB16*$L16 -> 27449.702 | CF16: =CE16/$CE$19 -> 0.015709194 | CG16: 37 | CH16: =(CG16-CB16)/CB16 -> 0.22071923 | CI16: =CH16*CF16 -> 0.0034673212 | CJ16: =CG16*$L16 -> 33508.379 | CK16: =CJ16/$CJ$19 -> 0.018939169 | CL16: 30.29 | CM16: =(CL16-CG16)/CG16 -> -0.18135135 | CN16: =CM16*CK16 -> -0.0034346439 | CO16: =CL16*$L16 -> 27431.589 | CP16: =CO16/$CO$19 -> 0.015523775 | CQ16: 30.4 | CR16: =(CQ16-CL16)/CL16 -> 0.0036315616 | CS16: =CR16*CP16 -> 5.6375544e-05 | CT16: =CQ16*$L16 -> 27531.209 | CU16: =CT16/$CT$19 -> 0.015348018 | CV16: 30.39 | CW16: =(CV16-CQ16)/CQ16 -> -0.00032894737 | CX16: =CW16*CW16 -> 1.0820637e-07 | CY16: =CV16*$L16 -> 27522.152 | CZ16: =CY16/$CY$19 -> 0.015364326 | DA16: 30.43 | DB16: =(DA16-CV16)/CV16 -> 0.0013162224 | DC16: =DB16*CZ16 -> 2.022287e-05 | DD16: =DA16*$L16 -> 27558.378 | DE16: =DD16/$DD$19 -> 0.015437031 | DF16: 31.08 | DG16: =(DF16-DA16)/DA16 -> 0.0213605 | DH16: =DG16*DE16 -> 0.00032974269 | DI16: =DF16*$L16 -> 28147.038 | DJ16: =DI16/$DI$19 -> 0.015292063 | DK16: 30.76 | DL16: =(DK16-DF16)/DF16 -> -0.01029601 | DM16: =DL16*DJ16 -> -0.00015744723 | DN16: =DK16*$L16 -> 27857.236 | DO16: =DN16/$DN$19 -> 0.015292896 | DP16: 30.17 | DQ16: =(DP16-DK16)/DK16 -> -0.019180754 | DR16: =DQ16*DO16 -> -0.00029332928 | DS16: =DP16*$L16 -> 27322.913 | DT16: =DS16/$DS$19 -> 0.015115828 | DU16: 31.04 | DV16: =(DU16-DP16)/DP16 -> 0.028836593 | DW16: =DV16*DV16 -> 0.00083154908 | DX16: =DU16*$L16 -> 28110.813 | DY16: =DX16/$DX$19 -> 0.015252678 | DZ16: 31.87 | EA16: =(DZ16-DU16)/DU16 -> 0.026739691 | EB16: =EA16*DY16 -> 0.0004078519 | EC16: =DZ16*$L16 -> 28862.488 | ED16: =EC16/$EC$19 -> 0.015568804 | EE16: 32 | EF16: =(EE16-DZ16)/DZ16 -> 0.0040790712 | EG16: =EF16*ED16 -> 6.3506261e-05 | EH16: =EE16*$L16 -> 28980.22 | EI16: =EH16/$EH$19 -> 0.015676942 | EJ16: 33.87 | EK16: =(EJ16-EE16)/EE16 -> 0.0584375 | EL16: =EK16*EI16 -> 0.00091612131 | EM16: =EJ16*$L16 -> 30673.751 | EN16: =EM16/$EM$19 -> 0.016304578 | EO16: 33.1 | EP16: =(EO16-EJ16)/EJ16 -> -0.022733983 | EQ16: =EP16*EN16 -> -0.00037066799 | ER16: =EO16*$L16 -> 29976.415 | ES16: =ER16/$ER$19 -> 0.015801778 | ET16: 32.84 | EU16: =(ET16-EO16)/EO16 -> -0.0078549849 | EV16: =EU16*EU16 -> 6.1700788e-05 | EW16: =ET16*$L16 -> 29740.951 | EX16: =EW16/$EW$19 -> 0.015777973 | EY16: 33.03 | EZ16: =(EY16-ET16)/ET16 -> 0.0057856273 | FA16: =EZ16*EX16 -> 9.128547e-05 | FB16: =EY16*$L16 -> 29913.021 | FC16: =FB16/$FB$19 -> 0.01579156 | FD16: 32.5 | FE16: =(FD16-EY16)/EY16 -> -0.016046019 | FF16: =FE16*FC16 -> -0.00025339167 | FG16: =FD16*$L16 -> 29433.036 | FH16: =FG16/$FG$19 -> 0.015820015 | FI16: 32.51 | FJ16: =(FI16-FD16)/FD16 -> 0.00030769231 | FK16: =FJ16*FH16 -> 4.8676969e-06 | FL16: =FI16*$L16 -> 29442.092 | FM16: =FL16/$FL$19 -> 0.015732611 | FN16: 32.2 | FO16: =(FN16-FI16)/FI16 -> -0.0095355275 | FP16: =FO16*FM16 -> -0.00015001875 | FQ16: =FN16*$L16 -> 29161.346 | FR16: =FQ16/$FQ$19 -> 0.015534314 | FS16: 33.62 | FT16: =(FS16-FN16)/FN16 -> 0.044099379 | FU16: =FT16*FR16 -> 0.00068505359 | FV16: =FS16*$L16 -> 30447.343 | FW16: =FV16/$FQ$19 -> 0.016219367 | FX16: 32.53 | FY16: =(FX16-FS16)/FS16 -> -0.032421178 | FZ16: =FY16*FW16 -> -0.000525851 | GA16: =FX16*$L16 -> 29460.205 | GB16: =GA16/$GA$19 -> 0.015946129 | GC16: 32.68 | GD16: =(GC16-FX16)/FX16 -> 0.0046111282 | GE16: =GD16*GB16 -> 7.3529644e-05 | GF16: =GC16*$L16 -> 29596.049 | GG16: =GF16/$GF$19 -> 0.015901362 | GH16: 32.55 | GI16: =(GH16-GC16)/GC16 -> -0.0039779682 | GJ16: =GI16*GG16 -> -6.325511e-05 | GK16: =GH16*$L16 -> 29478.317 | GL16: =GK16/$GK$19 -> 0.015808493 | GM16: 32.8 | GN16: =(GM16-GH16)/GH16 -> 0.0076804916 | GO16: =GN16*GN16 -> 5.898995e-05 | GP16: =GM16*$L16 -> 29704.725 | GQ16: =GP16/$GP$19 -> 0.016159485 | GR16: 32.61 | GS16: =(GR16-GM16)/GM16 -> -0.0057926829 | GT16: =GS16*GQ16 -> -9.3606774e-05 | GU16: =GR16*$L16 -> 29532.655 | GV16: =GU16/$GU$19 -> 0.016158238 | GW16: 32.13 | GX16: =(GW16-GR16)/GR16 -> -0.014719411 | GY16: =GX16*GV16 -> -0.00023783975 | GZ16: =GW16*$L16 -> 29097.952 | HA16: =GZ16/$GZ$19 -> 0.015964822 | HB16: 31.25 | HC16: =(HB16-GW16)/GW16 -> -0.027388733 | HD16: =HC16*HA16 -> -0.00043725626 | HE16: =HB16*$L16 -> 28300.996 | HF16: =HE16/$GF$19 -> 0.015205555 | HG16: 31.65 | HH16: =(HG16-HB16)/HB16 -> 0.0128 | HI16: =HH16*HF16 -> 0.00019463111 | HJ16: =HG16*$L16 -> 28663.249 | HK16: =HJ16/$HJ$19 -> 0.015900906 | HL16: 32.6 | HM16: =(HL16-HG16)/HG16 -> 0.030015798 | HN16: =HM16*HM16 -> 0.00090094812 | HO16: =HL16*$L16 -> 29523.599 | HP16: =HO16/$HO$19 -> 0.016034597
B17: 11 | C17: UCO Bank | D17: UCOBANK | E17: 26.8 | F17: 33593 | G17: =(F17/$F$19) -> 0.017799238 | H17: 12.1 | I17: 26.36 | J17: =(I17-E17)/E17 -> -0.01641791 | K17: =G17*J17 -> -0.00029222629 | L17: =F17/E17 -> 1253.4701 | M17: =L17*I17 -> 33041.473 | N17: =(M17/$M$19) -> 0.018461671 | O17: 25.48 | P17: =(O17-I17)/I17 -> -0.033383915 | Q17: =N17*P17 -> -0.00061632286 | R17: =O17*L17 -> 31938.419 | S17: =R17/$R$19 -> 0.018002736 | T17: 25.36 | U17: =(T17-O17)/O17 -> -0.0047095761 | V17: =U17*S17 -> -8.4785257e-05 | W17: =T17*$L17 -> 31788.003 | X17: =W17/$W$19 -> 0.017945763 | Y17: 25.45 | Z17: =(Y17-T17)/T17 -> 0.0035488959 | AA17: =Z17*X17 -> 6.3687644e-05 | AB17: =Y17*$L17 -> 31900.815 | AC17: =AB17/$AB$19 -> 0.017803946 | AD17: 25.19 | AE17: =(AD17-Y17)/Y17 -> -0.01021611 | AF17: =AE17*AC17 -> -0.00018188707 | AG17: =AD17*$L17 -> 31574.913 | AH17: =AG17/$AG$19 -> 0.017924127 | AI17: 24.68 | AJ17: =(AI17-AD17)/AD17 -> -0.020246129 | AK17: =AJ17*AH17 -> -0.00036289419 | AL17: =AI17*$L17 -> 30935.643 | AM17: =AL17/$AL$19 -> 0.017928853 | AN17: 27.77 | AO17: =(AN17-AI17)/AI17 -> 0.12520259 | AP17: =AO17*AM17 -> 0.0022447389 | AQ17: =AN17*$L17 -> 34808.866 | AR17: =AQ17/$AQ$19 -> 0.019963028 | AS17: 24.53 | AT17: =(AS17-AN17)/AN17 -> -0.11667267 | AU17: =AT17*AR17 -> -0.0023291397 | AV17: =AS17*$L17 -> 30747.623 | AW17: =AV17/$AV$19 -> 0.017621181 | AX17: 25.82 | AY17: =(AX17-AS17)/AS17 -> 0.052588667 | AZ17: =AY17*AW17 -> 0.00092667443 | BA17: =AX17*$L17 -> 32364.599 | BB17: =BA17/$BA$19 -> 0.018506193 | BC17: 24.74 | BD17: =(BC17-AX17)/AX17 -> -0.04182804 | BE17: =BD17*BB17 -> -0.0007740778 | BF17: =BC17*$L17 -> 31010.851 | BG17: =BF17/$BF$19 -> 0.017741059 | BH17: 25.54 | BI17: =(BH17-BC17)/BC17 -> 0.032336297 | BJ17: =BI17*BG17 -> 0.00057368016 | BK17: =BH17*$L17 -> 32013.628 | BL17: =BK17/$BK$19 -> 0.017854938 | BM17: 25.43 | BN17: =(BM17-BH17)/BH17 -> -0.0043069695 | BO17: =BN17*BL17 -> -7.6900674e-05 | BP17: =BM17*$L17 -> 31875.746 | BQ17: =BP17/$BP$19 -> 0.017835114 | BR17: 25.54 | BS17: =(BR17-BM17)/BM17 -> 0.0043255997 | BT17: =BS17*BQ17 -> 7.7147565e-05 | BU17: =BR17*$L17 -> 32013.628 | BV17: =BU17/$BU$19 -> 0.017881734 | BW17: 25.2 | BX17: =(BW17-BR17)/BR17 -> -0.013312451 | BY17: =BX17*BV17 -> -0.00023804971 | BZ17: =BW17*$L17 -> 31587.448 | CA17: =BZ17/$BZ$19 -> 0.017785627 | CB17: 24.89 | CC17: =(CB17-BW17)/BW17 -> -0.012301587 | CD17: =CC17*CA17 -> -0.00021879144 | CE17: =CB17*$L17 -> 31198.872 | CF17: =CE17/$CE$19 -> 0.017854807 | CG17: 24.83 | CH17: =(CG17-CB17)/CB17 -> -0.0024106067 | CI17: =CH17*CF17 -> -4.3040916e-05 | CJ17: =CG17*$L17 -> 31123.664 | CK17: =CJ17/$CJ$19 -> 0.017591311 | CL17: 25.1 | CM17: =(CL17-CG17)/CG17 -> 0.010873943 | CN17: =CM17*CK17 -> 0.00019128692 | CO17: =CL17*$L17 -> 31462.101 | CP17: =CO17/$CO$19 -> 0.017804676 | CQ17: 25.07 | CR17: =(CQ17-CL17)/CL17 -> -0.0011952191 | CS17: =CR17*CP17 -> -2.1280489e-05 | CT17: =CQ17*$L17 -> 31424.497 | CU17: =CT17/$CT$19 -> 0.017518437 | CV17: 25.26 | CW17: =(CV17-CQ17)/CQ17 -> 0.0075787794 | CX17: =CW17*CW17 -> 5.7437897e-05 | CY17: =CV17*$L17 -> 31662.656 | CZ17: =CY17/$CY$19 -> 0.017675774 | DA17: 25.03 | DB17: =(DA17-CV17)/CV17 -> -0.0091053048 | DC17: =DB17*CZ17 -> -0.00016094331 | DD17: =DA17*$L17 -> 31374.358 | DE17: =DD17/$DD$19 -> 0.01757458 | DF17: 26.04 | DG17: =(DF17-DA17)/DA17 -> 0.040351578 | DH17: =DG17*DE17 -> 0.00070916206 | DI17: =DF17*$L17 -> 32640.363 | DJ17: =DI17/$DI$19 -> 0.01773325 | DK17: 25.75 | DL17: =(DK17-DF17)/DF17 -> -0.011136713 | DM17: =DL17*DJ17 -> -0.00019749011 | DN17: =DK17*$L17 -> 32276.856 | DO17: =DN17/$DN$19 -> 0.017719152 | DP17: 25.12 | DQ17: =(DP17-DK17)/DK17 -> -0.024466019 | DR17: =DQ17*DO17 -> -0.00043351711 | DS17: =DP17*$L17 -> 31487.17 | DT17: =DS17/$DS$19 -> 0.017419616 | DU17: 25.99 | DV17: =(DU17-DP17)/DP17 -> 0.034633758 | DW17: =DV17*DV17 -> 0.0011994972 | DX17: =DU17*$L17 -> 32577.689 | DY17: =DX17/$DX$19 -> 0.017676365 | DZ17: 26.18 | EA17: =(DZ17-DU17)/DU17 -> 0.007310504 | EB17: =EA17*DY17 -> 0.00012922314 | EC17: =DZ17*$L17 -> 32815.849 | ED17: =EC17/$EC$19 -> 0.017701299 | EE17: 26.33 | EF17: =(EE17-DZ17)/DZ17 -> 0.0057295646 | EG17: =EF17*ED17 -> 0.00010142073 | EH17: =EE17*$L17 -> 33003.869 | EI17: =EH17/$EH$19 -> 0.017853548 | EJ17: 28.2 | EK17: =(EJ17-EE17)/EE17 -> 0.071021648 | EL17: =EK17*EI17 -> 0.0012679884 | EM17: =EJ17*$L17 -> 35347.858 | EN17: =EM17/$EM$19 -> 0.018789091 | EO17: 27.99 | EP17: =(EO17-EJ17)/EJ17 -> -0.0074468085 | EQ17: =EP17*EN17 -> -0.00013991876 | ER17: =EO17*$L17 -> 35084.629 | ES17: =ER17/$ER$19 -> 0.018494524 | ET17: 27.58 | EU17: =(ET17-EO17)/EO17 -> -0.014648089 | EV17: =EU17*EU17 -> 0.0002145665 | EW17: =ET17*$L17 -> 34570.707 | EX17: =EW17/$EW$19 -> 0.018340223 | EY17: 27.57 | EZ17: =(EY17-ET17)/ET17 -> -0.00036258158 | FA17: =EZ17*EX17 -> -6.6498271e-06 | FB17: =EY17*$L17 -> 34558.172 | FC17: =FB17/$FB$19 -> 0.01824381 | FD17: 26.85 | FE17: =(FD17-EY17)/EY17 -> -0.026115343 | FF17: =FE17*FC17 -> -0.00047644334 | FG17: =FD17*$L17 -> 33655.674 | FH17: =FG17/$FG$19 -> 0.018089648 | FI17: 27.11 | FJ17: =(FI17-FD17)/FD17 -> 0.0096834264 | FK17: =FJ17*FH17 -> 0.00017516978 | FL17: =FI17*$L17 -> 33981.576 | FM17: =FL17/$FL$19 -> 0.01815832 | FN17: 27.16 | FO17: =(FN17-FI17)/FI17 -> 0.0018443379 | FP17: =FO17*FM17 -> 3.3490077e-05 | FQ17: =FN17*$L17 -> 34044.249 | FR17: =FQ17/$FQ$19 -> 0.018135447 | FS17: 26.79 | FT17: =(FS17-FN17)/FN17 -> -0.013622975 | FU17: =FT17*FR17 -> -0.00024705874 | FV17: =FS17*$L17 -> 33580.465 | FW17: =FV17/$FQ$19 -> 0.017888388 | FX17: 26.98 | FY17: =(FX17-FS17)/FS17 -> 0.0070921986 | FZ17: =FY17*FW17 -> 0.000126868 | GA17: =FX17*$L17 -> 33818.625 | GB17: =GA17/$GA$19 -> 0.018305241 | GC17: 26.87 | GD17: =(GC17-FX17)/FX17 -> -0.0040770941 | GE17: =GD17*GB17 -> -7.4632191e-05 | GF17: =GC17*$L17 -> 33680.743 | GG17: =GF17/$GF$19 -> 0.018095985 | GH17: 27.14 | GI17: =(GH17-GC17)/GC17 -> 0.010048381 | GJ17: =GI17*GG17 -> 0.00018183536 | GK17: =GH17*$L17 -> 34019.18 | GL17: =GK17/$GK$19 -> 0.018243646 | GM17: 26.95 | GN17: =(GM17-GH17)/GH17 -> -0.0070007369 | GO17: =GN17*GN17 -> 4.9010317e-05 | GP17: =GM17*$L17 -> 33781.021 | GQ17: =GP17/$GP$19 -> 0.018377005 | GR17: 26.56 | GS17: =(GR17-GM17)/GM17 -> -0.014471243 | GT17: =GS17*GQ17 -> -0.00026593811 | GU17: =GR17*$L17 -> 33292.167 | GV17: =GU17/$GU$19 -> 0.018215185 | GW17: 26.39 | GX17: =(GW17-GR17)/GR17 -> -0.0064006024 | GY17: =GX17*GV17 -> -0.00011658816 | GZ17: =GW17*$L17 -> 33079.077 | HA17: =GZ17/$GZ$19 -> 0.018149098 | HB17: 26.11 | HC17: =(HB17-GW17)/GW17 -> -0.01061008 | HD17: =HC17*HA17 -> -0.00019256338 | HE17: =HB17*$L17 -> 32728.106 | HF17: =HE17/$GF$19 -> 0.017584152 | HG17: 26.04 | HH17: =(HG17-HB17)/HB17 -> -0.0026809651 | HI17: =HH17*HF17 -> -4.71425e-05 | HJ17: =HG17*$L17 -> 32640.363 | HK17: =HJ17/$HJ$19 -> 0.018107205 | HL17: 26.7 | HM17: =(HL17-HG17)/HG17 -> 0.025345622 | HN17: =HM17*HM17 -> 0.00064240056 | HO17: =HL17*$L17 -> 33467.653 | HP17: =HO17/$HO$19 -> 0.018176657
B18: 12 | C18: Punjab & Sind Bank | D18: PSB | E18: 24.9 | F18: 17689 | G18: =(F18/$F$19) -> 0.0093725097 | H18: 13.4 | I18: 24.87 | J18: =(I18-E18)/E18 -> -0.0012048193 | K18: =G18*J18 -> -1.129218e-05 | L18: =F18/E18 -> 710.40161 | M18: =L18*I18 -> 17667.688 | N18: =(M18/$M$19) -> 0.0098716859 | O18: 23.79 | P18: =(O18-I18)/I18 -> -0.043425814 | Q18: =N18*P18 -> -0.000428686 | R18: =O18*L18 -> 16900.454 | S18: =R18/$R$19 -> 0.0095262829 | T18: 24.03 | U18: =(T18-O18)/O18 -> 0.010088272 | V18: =U18*S18 -> 9.6103737e-05 | W18: =T18*$L18 -> 17070.951 | X18: =W18/$W$19 -> 0.0096373223 | Y18: 24.08 | Z18: =(Y18-T18)/T18 -> 0.0020807324 | AA18: =Z18*X18 -> 2.0052689e-05 | AB18: =Y18*$L18 -> 17106.471 | AC18: =AB18/$AB$19 -> 0.0095471755 | AD18: 23.67 | AE18: =(AD18-Y18)/Y18 -> -0.017026578 | AF18: =AE18*AC18 -> -0.00016255573 | AG18: =AD18*$L18 -> 16815.206 | AH18: =AG18/$AG$19 -> 0.0095454858 | AI18: 23.41 | AJ18: =(AI18-AD18)/AD18 -> -0.010984368 | AK18: =AJ18*AH18 -> -0.00010485113 | AL18: =AI18*$L18 -> 16630.502 | AM18: =AL18/$AL$19 -> 0.0096382617 | AN18: 23.51 | AO18: =(AN18-AI18)/AI18 -> 0.0042716788 | AP18: =AO18*AM18 -> 4.1171558e-05 | AQ18: =AN18*$L18 -> 16701.542 | AR18: =AQ18/$AQ$19 -> 0.0095784028 | AS18: 23.54 | AT18: =(AS18-AN18)/AN18 -> 0.0012760527 | AU18: =AT18*AR18 -> 1.2222547e-05 | AV18: =AS18*$L18 -> 16722.854 | AW18: =AV18/$AV$19 -> 0.0095837145 | AX18: 23.69 | AY18: =(AX18-AS18)/AS18 -> 0.0063721325 | AZ18: =AY18*AW18 -> 6.1068699e-05 | BA18: =AX18*$L18 -> 16829.414 | BB18: =BA18/$BA$19 -> 0.009623119 | BC18: 23.64 | BD18: =(BC18-AX18)/AX18 -> -0.0021105952 | BE18: =BD18*BB18 -> -2.0310509e-05 | BF18: =BC18*$L18 -> 16793.894 | BG18: =BF18/$BF$19 -> 0.0096076518 | BH18: 24.05 | BI18: =(BH18-BC18)/BC18 -> 0.017343486 | BJ18: =BI18*BG18 -> 0.00016663017 | BK18: =BH18*$L18 -> 17085.159 | BL18: =BK18/$BK$19 -> 0.0095288936 | BM18: 24.15 | BN18: =(BM18-BH18)/BH18 -> 0.0041580042 | BO18: =BN18*BL18 -> 3.9621179e-05 | BP18: =BM18*$L18 -> 17156.199 | BQ18: =BP18/$BP$19 -> 0.0095992347 | BR18: 24.28 | BS18: =(BR18-BM18)/BM18 -> 0.0053830228 | BT18: =BS18*BQ18 -> 5.1672899e-05 | BU18: =BR18*$L18 -> 17248.551 | BV18: =BU18/$BU$19 -> 0.0096344596 | BW18: 23.98 | BX18: =(BW18-BR18)/BR18 -> -0.012355848 | BY18: =BX18*BV18 -> -0.00011904192 | BZ18: =BW18*$L18 -> 17035.431 | CA18: =BZ18/$BZ$19 -> 0.0095919688 | CB18: 23.72 | CC18: =(CB18-BW18)/BW18 -> -0.010842369 | CD18: =CC18*CA18 -> -0.00010399966 | CE18: =CB18*$L18 -> 16850.726 | CF18: =CE18/$CE$19 -> 0.0096435043 | CG18: 23.79 | CH18: =(CG18-CB18)/CB18 -> 0.0029510961 | CI18: =CH18*CF18 -> 2.8458908e-05 | CJ18: =CG18*$L18 -> 16900.454 | CK18: =CJ18/$CJ$19 -> 0.0095522544 | CL18: 23.41 | CM18: =(CL18-CG18)/CG18 -> -0.015973098 | CN18: =CM18*CK18 -> -0.0001525791 | CO18: =CL18*$L18 -> 16630.502 | CP18: =CO18/$CO$19 -> 0.0094113453 | CQ18: 23.29 | CR18: =(CQ18-CL18)/CL18 -> -0.0051260145 | CS18: =CR18*CP18 -> -4.8242693e-05 | CT18: =CQ18*$L18 -> 16545.253 | CU18: =CT18/$CT$19 -> 0.0092235995 | CV18: 23.68 | CW18: =(CV18-CQ18)/CQ18 -> 0.016745384 | CX18: =CW18*CW18 -> 0.00028040789 | CY18: =CV18*$L18 -> 16822.31 | CZ18: =CY18/$CY$19 -> 0.0093911059 | DA18: 23.19 | DB18: =(DA18-CV18)/CV18 -> -0.020692568 | DC18: =DB18*CZ18 -> -0.00019432609 | DD18: =DA18*$L18 -> 16474.213 | DE18: =DD18/$DD$19 -> 0.0092281534 | DF18: 24.21 | DG18: =(DF18-DA18)/DA18 -> 0.043984476 | DH18: =DG18*DE18 -> 0.00040589549 | DI18: =DF18*$L18 -> 17198.823 | DJ18: =DI18/$DI$19 -> 0.0093439839 | DK18: 23.82 | DL18: =(DK18-DF18)/DF18 -> -0.016109046 | DM18: =DL18*DJ18 -> -0.00015052267 | DN18: =DK18*$L18 -> 16921.766 | DO18: =DN18/$DN$19 -> 0.0092896081 | DP18: 23.38 | DQ18: =(DP18-DK18)/DK18 -> -0.018471872 | DR18: =DQ18*DO18 -> -0.00017159646 | DS18: =DP18*$L18 -> 16609.19 | DT18: =DS18/$DS$19 -> 0.0091886854 | DU18: 24.02 | DV18: =(DU18-DP18)/DP18 -> 0.027373824 | DW18: =DV18*DV18 -> 0.00074932623 | DX18: =DU18*$L18 -> 17063.847 | DY18: =DX18/$DX$19 -> 0.009258692 | DZ18: 24.01 | EA18: =(DZ18-DU18)/DU18 -> -0.00041631973 | EB18: =EA18*DY18 -> -3.8545762e-06 | EC18: =DZ18*$L18 -> 17056.743 | ED18: =EC18/$EC$19 -> 0.0092006305 | EE18: 24 | EF18: =(EE18-DZ18)/DZ18 -> -0.00041649313 | EG18: =EF18*ED18 -> -3.8319994e-06 | EH18: =EE18*$L18 -> 17049.639 | EI18: =EH18/$EH$19 -> 0.0092230563 | EJ18: 25.48 | EK18: =(EJ18-EE18)/EE18 -> 0.061666667 | EL18: =EK18*EI18 -> 0.00056875514 | EM18: =EJ18*$L18 -> 18101.033 | EN18: =EM18/$EM$19 -> 0.0096215718 | EO18: 25.15 | EP18: =(EO18-EJ18)/EJ18 -> -0.012951334 | EQ18: =EP18*EN18 -> -0.00012461219 | ER18: =EO18*$L18 -> 17866.6 | ES18: =ER18/$ER$19 -> 0.0094182063 | ET18: 25.09 | EU18: =(ET18-EO18)/EO18 -> -0.0023856859 | EV18: =EU18*EU18 -> 5.6914971e-06 | EW18: =ET18*$L18 -> 17823.976 | EX18: =EW18/$EW$19 -> 0.0094558583 | EY18: 25.07 | EZ18: =(EY18-ET18)/ET18 -> -0.00079713033 | FA18: =EZ18*EX18 -> -7.5375515e-06 | FB18: =EY18*$L18 -> 17809.768 | FC18: =FB18/$FB$19 -> 0.0094020605 | FD18: 24.84 | FE18: =(FD18-EY18)/EY18 -> -0.0091743119 | FF18: =FE18*FC18 -> -8.6257436e-05 | FG18: =FD18*$L18 -> 17646.376 | FH18: =FG18/$FG$19 -> 0.009484782 | FI18: 25.01 | FJ18: =(FI18-FD18)/FD18 -> 0.0068438003 | FK18: =FJ18*FH18 -> 6.4911954e-05 | FL18: =FI18*$L18 -> 17767.144 | FM18: =FL18/$FL$19 -> 0.0094940119 | FN18: 24.63 | FO18: =(FN18-FI18)/FI18 -> -0.015193922 | FP18: =FO18*FM18 -> -0.00014425128 | FQ18: =FN18*$L18 -> 17497.192 | FR18: =FQ18/$FQ$19 -> 0.0093207928 | FS18: 24.35 | FT18: =(FS18-FN18)/FN18 -> -0.01136825 | FU18: =FT18*FR18 -> -0.0001059611 | FV18: =FS18*$L18 -> 17298.279 | FW18: =FV18/$FQ$19 -> 0.0092148317 | FX18: 24.24 | FY18: =(FX18-FS18)/FS18 -> -0.0045174538 | FZ18: =FY18*FW18 -> -4.1627577e-05 | GA18: =FX18*$L18 -> 17220.135 | GB18: =GA18/$GA$19 -> 0.0093208616 | GC18: 24.58 | GD18: =(GC18-FX18)/FX18 -> 0.014026403 | GE18: =GD18*GB18 -> 0.00013073816 | GF18: =GC18*$L18 -> 17461.671 | GG18: =GF18/$GF$19 -> 0.0093818046 | GH18: 24.91 | GI18: =(GH18-GC18)/GC18 -> 0.013425549 | GJ18: =GI18*GG18 -> 0.00012595588 | GK18: =GH18*$L18 -> 17696.104 | GL18: =GK18/$GK$19 -> 0.0094899833 | GM18: 24.75 | GN18: =(GM18-GH18)/GH18 -> -0.0064231232 | GO18: =GN18*GN18 -> 4.1256512e-05 | GP18: =GM18*$L18 -> 17582.44 | GQ18: =GP18/$GP$19 -> 0.0095649151 | GR18: 24.81 | GS18: =(GR18-GM18)/GM18 -> 0.0024242424 | GT18: =GS18*GQ18 -> 2.3187673e-05 | GU18: =GR18*$L18 -> 17625.064 | GV18: =GU18/$GU$19 -> 0.0096432231 | GW18: 24.77 | GX18: =(GW18-GR18)/GR18 -> -0.0016122531 | GY18: =GX18*GV18 -> -1.5547317e-05 | GZ18: =GW18*$L18 -> 17596.648 | HA18: =GZ18/$GZ$19 -> 0.0096545404 | HB18: 24.1 | HC18: =(HB18-GW18)/GW18 -> -0.027048849 | HD18: =HC18*HA18 -> -0.00026114421 | HE18: =HB18*$L18 -> 17120.679 | HF18: =HE18/$GF$19 -> 0.009198596 | HG18: 24.46 | HH18: =(HG18-HB18)/HB18 -> 0.014937759 | HI18: =HH18*HF18 -> 0.00013740641 | HJ18: =HG18*$L18 -> 17376.423 | HK18: =HJ18/$HJ$19 -> 0.0096395518 | HL18: 24.99 | HM18: =(HL18-HG18)/HG18 -> 0.021668029 | HN18: =HM18*HM18 -> 0.0004695035 | HO18: =HL18*$L18 -> 17752.936 | HP18: =HO18/$HO$19 -> 0.0096418186
C19: Total Sector Market Cap | F19: =SUM(F7:F18) -> 1887328 | G19: =(F19/$F$19) -> 1 | K19: =SUM(K7:K18) -> -0.051710356 | M19: =SUM(M7:M18) -> 1789733.6 | N19: =SUM(N7:N18) -> 1 | Q19: =SUM(Q7:Q18) -> -0.0087424418 | R19: =SUM(R7:R18) -> 1774087 | S19: =R19/$R$19 -> 1 | V19: =SUM(V7:V18) -> -0.00154977 | W19: =SUM(W7:W18) -> 1771337.5 | X19: =SUM(X7:X18) -> 1 | AA19: =SUM(AA7:AA18) -> 0.011542627 | AB19: =SUM(AB7:AB18) -> 1791783.4 | AC19: =AB19/$AB$19 -> 1 | AF19: =SUM(AF7:AF18) -> -0.016852584 | AG19: =SUM(AG7:AG18) -> 1761587.2 | AH19: =SUM(AH7:AH18) -> 1 | AK19: =SUM(AK7:AK18) -> -0.020504421 | AL19: =SUM(AL7:AL18) -> 1725466.9 | AM19: =SUM(AM7:AM18) -> 1 | AP19: =SUM(AP7:AP18) -> 0.01054773 | AQ19: =SUM(AQ7:AQ18) -> 1743666.7 | AR19: =SUM(AR7:AR18) -> 1 | AU19: =SUM(AU7:AU18) -> 0.00072110838 | AV19: =SUM(AV7:AV18) -> 1744924 | AW19: =SUM(AW7:AW18) -> 1 | AZ19: =SUM(AZ7:AZ18) -> 0.0022512691 | BA19: =SUM(BA7:BA18) -> 1748852.3 | BB19: =SUM(BB7:BB18) -> 1 | BE19: =SUM(BE7:BE18) -> -0.0005041117 | BF19: =SUM(BF7:BF18) -> 1747970.7 | BG19: =SUM(BG7:BG18) -> 1 | BJ19: =SUM(BJ7:BJ18) -> 0.025752027 | BK19: =SUM(BK7:BK18) -> 1792984.5 | BL19: =SUM(BL7:BL18) -> 1 | BO19: =SUM(BO7:BO18) -> -0.0032002468 | BP19: =SUM(BP7:BP18) -> 1787246.5 | BQ19: =SUM(BQ7:BQ18) -> 1 | BT19: =SUM(BT7:BT18) -> 0.0017072059 | BU19: =SUM(BU7:BU18) -> 1790297.7 | BV19: =SUM(BV7:BV18) -> 1 | BY19: =SUM(BY7:BY18) -> -0.0079807505 | BZ19: =SUM(BZ7:BZ18) -> 1776009.8 | CA19: =SUM(CA7:CA18) -> 1 | CD19: =SUM(CD7:CD18) -> -0.016128486 | CE19: =SUM(CE7:CE18) -> 1747365.4 | CF19: =CE19/$CE$19 -> 1 | CI19: =SUM(CI7:CI18) -> 0.01253199 | CJ19: =SUM(CJ7:CJ18) -> 1769263.4 | CK19: =CJ19/$CJ$19 -> 1 | CN19: =SUM(CN7:CN18) -> -0.0012399942 | CO19: =SUM(CO7:CO18) -> 1767069.5 | CP19: =CO19/$CO$19 -> 1 | CS19: =SUM(CS7:CS18) -> 0.015124587 | CT19: =SUM(CT7:CT18) -> 1793795.7 | CU19: =SUM(CU7:CU18) -> 1 | CX19: =SUM(CX7:CX18) -> 0.0017025588 | CY19: =SUM(CY7:CY18) -> 1791302.3 | CZ19: =SUM(CZ7:CZ18) -> 1 | DC19: =SUM(DC7:DC18) -> -0.0033997632 | DD19: =SUM(DD7:DD18) -> 1785212.3 | DE19: =SUM(DE7:DE18) -> 1 | DH19: =SUM(DH7:DH18) -> 0.031042961 | DI19: =SUM(DI7:DI18) -> 1840630.6 | DJ19: =SUM(DJ7:DJ18) -> 1 | DM19: =SUM(DM7:DM18) -> -0.010349936 | DN19: =SUM(DN7:DN18) -> 1821580.2 | DO19: =SUM(DO7:DO18) -> 1 | DR19: =SUM(DR7:DR18) -> -0.0076913841 | DS19: =SUM(DS7:DS18) -> 1807569.7 | DT19: =SUM(DT7:DT18) -> 1 | DW19: =SUM(DW7:DW18) -> 0.0089738674 | DX19: =SUM(DX7:DX18) -> 1843008.3 | DY19: =SUM(DY7:DY18) -> 1 | EB19: =SUM(EB7:EB18) -> 0.0058916476 | EC19: =SUM(EC7:EC18) -> 1853866.7 | ED19: =SUM(ED7:ED18) -> 1 | EG19: =SUM(EG7:EG18) -> -0.0028469721 | EH19: =SUM(EH7:EH18) -> 1848588.8 | EI19: =SUM(EI7:EI18) -> 1 | EL19: =SUM(EL7:EL18) -> 0.017693541 | EM19: =SUM(EM7:EM18) -> 1881296.9 | EN19: =SUM(EN7:EN18) -> 1 | EQ19: =SUM(EQ7:EQ18) -> 0.0083618145 | ER19: =SUM(ER7:ER18) -> 1897027.9 | ES19: =SUM(ES7:ES18) -> 1 | EV19: =SUM(EV7:EV18) -> 0.0006884029 | EW19: =SUM(EW7:EW18) -> 1884966.5 | EX19: =SUM(EX7:EX18) -> 1 | FA19: =SUM(FA7:FA18) -> 0.0049202289 | FB19: =SUM(FB7:FB18) -> 1894241 | FC19: =SUM(FC7:FC18) -> 1 | FF19: =SUM(FF7:FF18) -> -0.017815801 | FG19: =SUM(FG7:FG18) -> 1860493.6 | FH19: =SUM(FH7:FH18) -> 1 | FK19: =SUM(FK7:FK18) -> 0.0058649658 | FL19: =SUM(FL7:FL18) -> 1871405.3 | FM19: =SUM(FM7:FM18) -> 1 | FP19: =SUM(FP7:FP18) -> 0.0031078734 | FQ19: =SUM(FQ7:FQ18) -> 1877221.4 | FR19: =SUM(FR7:FR18) -> 1 | FU19: =SUM(FU7:FU18) -> -0.0062414141 | FV19: =SUM(FV7:FV18) -> 1865504.9 | FW19: =SUM(FW7:FW18) -> 0.99375859 | FZ19: =SUM(FZ7:FZ18) -> -0.0096002 | GA19: =SUM(GA7:GA18) -> 1847483.2 | GB19: =SUM(GB7:GB18) -> 1 | GE19: =SUM(GE7:GE18) -> 0.0074394215 | GF19: =SUM(GF7:GF18) -> 1861227.4 | GG19: =SUM(GG7:GG18) -> 1 | GJ19: =SUM(GJ7:GJ18) -> 0.001873253 | GK19: =SUM(GK7:GK18) -> 1864713.9 | GL19: =SUM(GL7:GL18) -> 1 | GO19: =SUM(GO7:GO18) -> 0.0059417312 | GP19: =SUM(GP7:GP18) -> 1838222.3 | GQ19: =SUM(GQ7:GQ18) -> 1 | GT19: =SUM(GT7:GT18) -> -0.0057159671 | GU19: =SUM(GU7:GU18) -> 1827715 | GV19: =SUM(GV7:GV18) -> 1 | GY19: =SUM(GY7:GY18) -> -0.0027825955 | GZ19: =SUM(GZ7:GZ18) -> 1822629.2 | HA19: =SUM(HA7:HA18) -> 1 | HD19: =SUM(HD7:HD18) -> -0.024763672 | HE19: =SUM(HE7:HE18) -> 1777494.3 | HF19: =SUM(HF7:HF18) -> 0.97877927 | HI19: =SUM(HI7:HI18) -> 0.013619667 | HJ19: =SUM(HJ7:HJ18) -> 1802617.3 | HK19: =SUM(HK7:HK18) -> 1 | HN19: =SUM(HN7:HN18) -> 0.019048095 | HO19: =SUM(HO7:HO18) -> 1841243.5 | HP19: =SUM(HP7:HP18) -> 1
C20: Average of the Industry (Sector PE) | H20: =AVERAGE(H7:H18) -> 9.065
C21: New Index | K21: =1000+(1000*K19) -> 948.28964 | Q21: =1000+(1000*Q19) -> 991.25756 | V21: =1000+(1000*V19) -> 998.45023 | AA21: =1000+(1000*AA19) -> 1011.5426 | AF21: =1000+(1000*AF19) -> 983.14742 | AK21: =1000+(1000*AK19) -> 979.49558 | AP21: =1000+(1000*AP19) -> 1010.5477 | AU21: =1000+(1000*AU19) -> 1000.7211 | AZ21: =1000+(1000*AZ19) -> 1002.2513 | BE21: =1000+(1000*BE19) -> 999.49589 | BJ21: =1000+(1000*BJ19) -> 1025.752 | BO21: =1000+(1000*BO19) -> 996.79975 | BT21: =1000+(1000*BT19) -> 1001.7072 | BY21: =1000+(1000*BY19) -> 992.01925 | CD21: =1000+(1000*CD19) -> 983.87151 | CI21: =1000+(1000*CI19) -> 1012.532 | CN21: =1000+(1000*CN19) -> 998.76001 | CS21: =1000+(1000*CS19) -> 1015.1246 | CX21: =1000+(1000*CX19) -> 1001.7026 | DC21: =1000+(1000*DC19) -> 996.60024 | DH21: =1000+(1000*DH19) -> 1031.043 | DM21: =1000+(1000*DM19) -> 989.65006 | DR21: =1000+(1000*DR19) -> 992.30862 | DW21: =1000+(1000*DW19) -> 1008.9739 | EB21: =1000+(1000*EB19) -> 1005.8916 | EG21: =1000+(1000*EG19) -> 997.15303 | EL21: =1000+(1000*EL19) -> 1017.6935 | EQ21: =1000+(1000*EQ19) -> 1008.3618 | EV21: =1000+(1000*EV19) -> 1000.6884 | FA21: =1000+(1000*FA19) -> 1004.9202 | FF21: =1000+(1000*FF19) -> 982.1842 | FK21: =1000+(1000*FK19) -> 1005.865 | FP21: =1000+(1000*FP19) -> 1003.1079 | FU21: =1000+(1000*FU19) -> 993.75859 | FZ21: =1000+(1000*FZ19) -> 990.3998 | GE21: =1000+(1000*GE19) -> 1007.4394 | GJ21: =1000+(1000*GJ19) -> 1001.8733 | GO21: =1000+(1000*GO19) -> 1005.9417 | GT21: =1000+(1000*GT19) -> 994.28403 | GY21: =1000+(1000*GY19) -> 997.2174 | HD21: =1000+(1000*HD19) -> 975.23633 | HI21: =1000+(1000*HI19) -> 1013.6197 | HN21: =1000+(1000*HN19) -> 1019.0481
B23: NOTES: | C23: 1. Market closed on 28/05/26 (Thursday) on the occasion of Bakri Eid
C24: 2. Assumption : Index Base = 1,000
C25: 3. Market closed on 26/06/26 (Friday) due to Muharram

Sheet RATIOS
B2: Ratio | D2: Description | E2: Analysis | F2: Weightage
B3: Gross NPA Ratio | D3: To check loan quality , Higher NPA = more risk + lower profits, “This ratio helps us understand whether the bank is giving safe loans or risky ones.” | E3: Lower is Better | F3: 0.3
B4: Net Interest Margin | D4: To check core earning ability , NIM shows how efficiently the bank earns from the difference between int earned on loans given and paid on deposits made, “This tells us how well the bank is making money from its main business.” | E4: Higher is Better | F4: 0.2
B5: Return on Assets | D5: To check efficiency , “This shows how efficiently the bank is using its resources to earn profit.” | E5: Higher is Better | F5: 0.25
B6: Capital Adequacy Ratio | D6: To check safety , Higher CAR = safer bank , “This tells us how strong and stable the bank is during risky situations.” | E6: Higher is Better | F6: 0.15
B7: P/B Ratio (Price to Book Ratio) | D7: To check valuation , Banks are valued based on their assets (book value) , “This shows whether the bank’s stock is fairly priced compared to its actual worth.” | E7: Lower is Better | F7: 0.1
B9: Gross NPA measures asset quality, NIM reflects core earning ability, ROA indicates efficiency in using assets, CAR ensures financial stability, and P/B ratio helps in valuation analysis. Together, these ratios give a comprehensive view of risk, profitability, efficiency, and market valuation of banks.”
B12: “Why only these 5?” | D12: “Because banking is an asset-driven industry, so I focused on asset quality, profitability, safety, and valuation rather than general ratios.”
B15: Why NOT Others in Top 5? | D15: P/E Ratio → Less relevant than P/B in banking
D16: ROE → Can be misleading due to leverage
D17: Cost-to-Income → Secondary efficiency metric
D18: Credit Growth → Important but not core
D19: Net NPA → Useful, but Gross NPA already covers risk

Sheet Co's Over-Under Valued
C4: Companies Overvalued | J4: Companies Undervalued
M6: Revenue | P6: Profit
C7: Company Name | D7: Price | E7: PE Ratio | F7: Growth Rate % | G7: PEG Ratio | H7: Select/Reject | J7: Company Name | K7: Price | L7: PE Ratio | M7: Mar25 | N7: Mar26 | O7: Change in Revenue | P7: Mar25 | Q7: Mar26 | R7: Change in Profit | S7: Select/Reject
C8: State Bank of India (SBI) | D8: 1068 | E8: 12.17 | F8: =((86.91-75.17)/75.17)*100 -> 15.617933 | G8: =E8/F8 -> 0.77923245 | H8: Growth Pick | J8: Bank of Baroda (BOB) | K8: 263 | L8: 7 | M8: 127945 | N8: 134298 | O8: =N8-M8 -> 6353 | P8: 20865 | Q8: 20070 | R8: =Q8-P8 -> -795 | S8: Value Pick
C9: Indian Bank | D9: 852 | E9: 9.36 | F9: =((83.61-62.51)/62.51)*100 -> 33.754599 | G9: =E9/F9 -> 0.27729555 | H9: Growth Pick | J9: Union Bank of India | K9: 166 | L9: 6.52 | M9: 108417 | N9: 106799 | O9: =N9-M9 -> -1618 | P9: 18027 | Q9: 19430 | R9: =Q9-P9 -> 1403 | S9: Value Pick
C10: Indian Overseas Bank (IOB) | D10: 35 | E10: 12.9 | F10: =((1.73-1.4)/1.4)*100 -> 23.571429 | G10: =E10/F10 -> 0.54727273 | H10: Growth Pick | J10: Punjab National Bank (PNB) | K10: 109 | L10: 7.06 | M10: 124010 | N10: 130772 | O10: =N10-M10 -> 6762 | P10: 18553 | Q10: 18467 | R10: =Q10-P10 -> -86 | S10: Value Pick
C11: UCO Bank | D11: 26.8 | E11: 12.1 | F11: =((1.95-1.38)/1.38)*100 -> 41.304348 | G11: =E11/F11 -> 0.29294737 | H11: Growth Pick | J11: Canara Bank | K11: 135 | L11: 6.05 | M11: 121601 | N11: 126371 | O11: =N11-M11 -> 4770 | P11: 17692 | Q11: 17879 | R11: =Q11-P11 -> 187 | S11: Value Pick
C12: Punjab & Sind Bank | D12: 24.9 | E12: 13.4 | F12: =((1.43-0.88)/0.88)*100 -> 62.5 | G12: =E12/F12 -> 0.2144 | H12: Growth Pick | J12: Bank of India (BOI) | K12: 140 | L12: 6.25 | M12: 71308 | N12: 75613 | O12: =N12-M12 -> 4305 | P12: 9552 | Q12: 10309 | R12: =Q12-P12 -> 757 | S12: Value Pick
J13: Bank of Maharashtra | K13: 78.4 | L13: 8.59 | M13: 24948 | N13: 29282 | O13: =N13-M13 -> 4334 | P13: 5542 | Q13: 7017 | R13: =Q13-P13 -> 1475 | S13: Value Pick
J14: Central Bank of India | K14: 36.4 | L14: 7.38 | M14: 33797 | N14: 36168 | O14: =N14-M14 -> 2371 | P14: 3843 | Q14: 4531 | R14: =Q14-P14 -> 688 | S14: Value Pick
H16: Above 1.5 & Below 0 - Reject | S16: Profit Inc & Revenue Inc - Accept
H17: Between 0 to 1.5 - Accept | S17: Profit Inc & Revenue Dec - Accept
S18: Profit Dec & Revenue Inc - Accept
S19: Profit Dec & Revenue Dec - Reject
B22: METHOD I
C24: Value + Growth Pick | D24: Ratios
C25: Company Name | D25: Gross NPA Ratio (%) | E25: Rank | F25: Net Interest Margin (%) | G25: Rank | H25: Return on Assets (%) | I25: Rank | J25: Capital Adequacy Ratio (%) | K25: Rank | L25: P/B Ratio (Times) | M25: Rank | N25: Total Rank | O25: Final Rank
B26: Overvalued | C26: State Bank of India (SBI) | D26: 0.0149 | E26: =RANK(D26,$D$26:$D$37,1) -> 3 | F26: 0.0293 | G26: =RANK(F26,$F$26:$F$37,0) -> 5 | H26: 0.0104 | I26: =RANK(H26,$H$26:$H$37,0) -> 5 | J26: 0.154 | K26: =RANK(J26,$J$26:$J$37,0) -> 12 | L26: 1.7 | M26: =RANK(L26,$L$26:$L$37,1) -> 10 | N26: =SUM(E26+G26+I26+K26+M26) -> 35 | O26: =RANK(N26,$N$26:$N$37,1) -> 8
C27: Indian Bank | D27: 0.0198 | E27: =RANK(D27,$D$26:$D$37,1) -> 6 | F27: 0.0336 | G27: =RANK(F27,$F$26:$F$37,0) -> 2 | H27: 0.0131 | I27: =RANK(H27,$H$26:$H$37,0) -> 3 | J27: 0.1793 | K27: =RANK(J27,$J$26:$J$37,0) -> 5 | L27: 1.6 | M27: =RANK(L27,$L$26:$L$37,1) -> 9 | N27: =SUM(E27+G27+I27+K27+M27) -> 25 | O27: =RANK(N27,$N$26:$N$37,1) -> 3
C28: Indian Overseas Bank (IOB) | D28: 0.0142 | E28: =RANK(D28,$D$26:$D$37,1) -> 1 | F28: 0.0325 | G28: =RANK(F28,$F$26:$F$37,0) -> 3 | H28: 0.0132 | I28: =RANK(H28,$H$26:$H$37,0) -> 2 | J28: 0.1978 | K28: =RANK(J28,$J$26:$J$37,0) -> 1 | L28: 2 | M28: =RANK(L28,$L$26:$L$37,1) -> 11 | N28: =SUM(E28+G28+I28+K28+M28) -> 18 | O28: =RANK(N28,$N$26:$N$37,1) -> 1
C29: UCO Bank | D29: 0.0217 | E29: =RANK(D29,$D$26:$D$37,1) -> 8 | F29: 0.03 | G29: =RANK(F29,$F$26:$F$37,0) -> 4 | H29: 0.0079 | I29: =RANK(H29,$H$26:$H$37,0) -> 10 | J29: 0.1861 | K29: =RANK(J29,$J$26:$J$37,0) -> 2 | L29: 1.22 | M29: =RANK(L29,$L$26:$L$37,1) -> 6 | N29: =SUM(E29+G29+I29+K29+M29) -> 30 | O29: =RANK(N29,$N$26:$N$37,1) -> 4
C30: Punjab & Sind Bank | D30: 0.026 | E30: =RANK(D30,$D$26:$D$37,1) -> 9 | F30: 0.029 | G30: =RANK(F30,$F$26:$F$37,0) -> 6 | H30: 0.0079 | I30: =RANK(H30,$H$26:$H$37,0) -> 10 | J30: 0.1683 | K30: =RANK(J30,$J$26:$J$37,0) -> 8 | L30: 1.49 | M30: =RANK(L30,$L$26:$L$37,1) -> 7 | N30: =SUM(E30+G30+I30+K30+M30) -> 40 | O30: =RANK(N30,$N$26:$N$37,1) -> 10
B31: Undervalued | C31: Bank of Baroda (BOB) | D31: 0.0189 | E31: =RANK(D31,$D$26:$D$37,1) -> 5 | F31: 0.0289 | G31: =RANK(F31,$F$26:$F$37,0) -> 8 | H31: 0.0106 | I31: =RANK(H31,$H$26:$H$37,0) -> 4 | J31: 0.1582 | K31: =RANK(J31,$J$26:$J$37,0) -> 11 | L31: 1.05 | M31: =RANK(L31,$L$26:$L$37,1) -> 4 | N31: =SUM(E31+G31+I31+K31+M31) -> 32 | O31: =RANK(N31,$N$26:$N$37,1) -> 6
C32: Union Bank of India | D32: 0.0306 | E32: =RANK(D32,$D$26:$D$37,1) -> 12 | F32: 0.027 | G32: =RANK(F32,$F$26:$F$37,0) -> 10 | H32: 0.0101 | I32: =RANK(H32,$H$26:$H$37,0) -> 7 | J32: 0.162 | K32: =RANK(J32,$J$26:$J$37,0) -> 10 | L32: 1.08 | M32: =RANK(L32,$L$26:$L$37,1) -> 5 | N32: =SUM(E32+G32+I32+K32+M32) -> 44 | O32: =RANK(N32,$N$26:$N$37,1) -> 12
C33: Punjab National Bank (PNB) | D33: 0.0295 | E33: =RANK(D33,$D$26:$D$37,1) -> 11 | F33: 0.0257 | G33: =RANK(F33,$F$26:$F$37,0) -> 11 | H33: 0.0089 | I33: =RANK(H33,$H$26:$H$37,0) -> 8 | J33: 0.1774 | K33: =RANK(J33,$J$26:$J$37,0) -> 6 | L33: 0.84 | M33: =RANK(L33,$L$26:$L$37,1) -> 1 | N33: =SUM(E33+G33+I33+K33+M33) -> 37 | O33: =RANK(N33,$N$26:$N$37,1) -> 9
C34: Canara Bank | D34: 0.0184 | E34: =RANK(D34,$D$26:$D$37,1) -> 4 | F34: 0.0251 | G34: =RANK(F34,$F$26:$F$37,0) -> 12 | H34: 0.0102 | I34: =RANK(H34,$H$26:$H$37,0) -> 6 | J34: 0.1704 | K34: =RANK(J34,$J$26:$J$37,0) -> 7 | L34: 0.87 | M34: =RANK(L34,$L$26:$L$37,1) -> 3 | N34: =SUM(E34+G34+I34+K34+M34) -> 32 | O34: =RANK(N34,$N$26:$N$37,1) -> 6
C35: Bank of India (BOI) | D35: 0.0198 | E35: =RANK(D35,$D$26:$D$37,1) -> 6 | F35: 0.028 | G35: =RANK(F35,$F$26:$F$37,0) -> 9 | H35: 0.0085 | I35: =RANK(H35,$H$26:$H$37,0) -> 9 | J35: 0.1801 | K35: =RANK(J35,$J$26:$J$37,0) -> 4 | L35: 0.85 | M35: =RANK(L35,$L$26:$L$37,1) -> 2 | N35: =SUM(E35+G35+I35+K35+M35) -> 30 | O35: =RANK(N35,$N$26:$N$37,1) -> 4
C36: Bank of Maharashtra | D36: 0.0145 | E36: =RANK(D36,$D$26:$D$37,1) -> 2 | F36: 0.039 | G36: =RANK(F36,$F$26:$F$37,0) -> 1 | H36: 0.0186 | I36: =RANK(H36,$H$26:$H$37,0) -> 1 | J36: 0.1836 | K36: =RANK(J36,$J$26:$J$37,0) -> 3 | L36: 2.5 | M36: =RANK(L36,$L$26:$L$37,1) -> 12 | N36: =SUM(E36+G36+I36+K36+M36) -> 19 | O36: =RANK(N36,$N$26:$N$37,1) -> 2
C37: Central Bank of India | D37: 0.026 | E37: =RANK(D37,$D$26:$D$37,1) -> 9 | F37: 0.029 | G37: =RANK(F37,$F$26:$F$37,0) -> 6 | H37: 0.0079 | I37: =RANK(H37,$H$26:$H$37,0) -> 10 | J37: 0.1683 | K37: =RANK(J37,$J$26:$J$37,0) -> 8 | L37: 1.49 | M37: =RANK(L37,$L$26:$L$37,1) -> 7 | N37: =SUM(E37+G37+I37+K37+M37) -> 40 | O37: =RANK(N37,$N$26:$N$37,1) -> 10
D39: Lower is Better | F39: Higher is Better | H39: Higher is Better | J39: Higher is Better | L39: Lower is Better
B45: METHOD II
C47: Value + Growth Pick | D47: Ratios
C48: Company Name | D48: Gross NPA Ratio | H48: Net Interest Margin (%) | L48: Return on Assets (%) | P48: Capital Adequacy Ratio (%) | T48: P/B Ratio (Times)
D49: Calculation | E49: Rank | F49: Ratio Weightage | G49: Weighted Rank | H49: Calculation | I49: Rank | J49: Ratio Weightage | K49: Weighted Rank | L49: Calculation | M49: Rank | N49: Ratio Weightage | O49: Weighted Rank | P49: Calculation | Q49: Rank | R49: Ratio Weightage | S49: Weighted Rank | T49: Calculation | U49: Rank | V49: Ratio Weightage | W49: Weighted Rank | X49: Total Rank | Y49: Final Rank
B50: Overvalued | C50: State Bank of India (SBI) | D50: 0.0149 | E50: =RANK(D50,$D$26:$D$37,1) -> 3 | F50: 0.3 | G50: =E50*F50 -> 0.9 | H50: 0.0293 | I50: =RANK(H50,$F$26:$F$37,0) -> 5 | J50: 0.2 | K50: =I50*J50 -> 1 | L50: 0.0104 | M50: =RANK(L50,$H$26:$H$37,0) -> 5 | N50: 0.25 | O50: =M50*N50 -> 1.25 | P50: 0.154 | Q50: =RANK(P50,$J$26:$J$37,0) -> 12 | R50: 0.15 | S50: =Q50*R50 -> 1.8 | T50: 1.7 | U50: =RANK(T50,$L$26:$L$37,1) -> 10 | V50: 0.1 | W50: =U50*V50 -> 1 | X50: =W50+S50+O50+K50+G50 -> 5.95 | Y50: =RANK(X50,$X$50:$X$61,1) -> 4
C51: Indian Bank | D51: 0.0198 | E51: =RANK(D51,$D$26:$D$37,1) -> 6 | F51: 0.3 | G51: =E51*F51 -> 1.8 | H51: 0.0336 | I51: =RANK(H51,$F$26:$F$37,0) -> 2 | J51: 0.2 | K51: =I51*J51 -> 0.4 | L51: 0.0131 | M51: =RANK(L51,$H$26:$H$37,0) -> 3 | N51: 0.25 | O51: =M51*N51 -> 0.75 | P51: 0.1793 | Q51: =RANK(P51,$J$26:$J$37,0) -> 5 | R51: 0.15 | S51: =Q51*R51 -> 0.75 | T51: 1.6 | U51: =RANK(T51,$L$26:$L$37,1) -> 9 | V51: 0.1 | W51: =U51*V51 -> 0.9 | X51: =W51+S51+O51+K51+G51 -> 4.6 | Y51: =RANK(X51,$X$50:$X$61,1) -> 3
C52: Indian Overseas Bank (IOB) | D52: 0.0142 | E52: =RANK(D52,$D$26:$D$37,1) -> 1 | F52: 0.3 | G52: =E52*F52 -> 0.3 | H52: 0.0325 | I52: =RANK(H52,$F$26:$F$37,0) -> 3 | J52: 0.2 | K52: =I52*J52 -> 0.6 | L52: 0.0132 | M52: =RANK(L52,$H$26:$H$37,0) -> 2 | N52: 0.25 | O52: =M52*N52 -> 0.5 | P52: 0.1978 | Q52: =RANK(P52,$J$26:$J$37,0) -> 1 | R52: 0.15 | S52: =Q52*R52 -> 0.15 | T52: 2 | U52: =RANK(T52,$L$26:$L$37,1) -> 11 | V52: 0.1 | W52: =U52*V52 -> 1.1 | X52: =W52+S52+O52+K52+G52 -> 2.65 | Y52: =RANK(X52,$X$50:$X$61,1) -> 1
C53: UCO Bank | D53: 0.0217 | E53: =RANK(D53,$D$26:$D$37,1) -> 8 | F53: 0.3 | G53: =E53*F53 -> 2.4 | H53: 0.03 | I53: =RANK(H53,$F$26:$F$37,0) -> 4 | J53: 0.2 | K53: =I53*J53 -> 0.8 | L53: 0.0079 | M53: =RANK(L53,$H$26:$H$37,0) -> 10 | N53: 0.25 | O53: =M53*N53 -> 2.5 | P53: 0.1861 | Q53: =RANK(P53,$J$26:$J$37,0) -> 2 | R53: 0.15 | S53: =Q53*R53 -> 0.3 | T53: 1.22 | U53: =RANK(T53,$L$26:$L$37,1) -> 6 | V53: 0.1 | W53: =U53*V53 -> 0.6 | X53: =W53+S53+O53+K53+G53 -> 6.6 | Y53: =RANK(X53,$X$50:$X$61,1) -> 7
C54: Punjab & Sind Bank | D54: 0.026 | E54: =RANK(D54,$D$26:$D$37,1) -> 9 | F54: 0.3 | G54: =E54*F54 -> 2.7 | H54: 0.029 | I54: =RANK(H54,$F$26:$F$37,0) -> 6 | J54: 0.2 | K54: =I54*J54 -> 1.2 | L54: 0.0079 | M54: =RANK(L54,$H$26:$H$37,0) -> 10 | N54: 0.25 | O54: =M54*N54 -> 2.5 | P54: 0.1683 | Q54: =RANK(P54,$J$26:$J$37,0) -> 8 | R54: 0.15 | S54: =Q54*R54 -> 1.2 | T54: 1.49 | U54: =RANK(T54,$L$26:$L$37,1) -> 7 | V54: 0.1 | W54: =U54*V54 -> 0.7 | X54: =W54+S54+O54+K54+G54 -> 8.3 | Y54: =RANK(X54,$X$50:$X$61,1) -> 9
B55: Undervalued | C55: Bank of Baroda (BOB) | D55: 0.0189 | E55: =RANK(D55,$D$26:$D$37,1) -> 5 | F55: 0.3 | G55: =E55*F55 -> 1.5 | H55: 0.0289 | I55: =RANK(H55,$F$26:$F$37,0) -> 8 | J55: 0.2 | K55: =I55*J55 -> 1.6 | L55: 0.0106 | M55: =RANK(L55,$H$26:$H$37,0) -> 4 | N55: 0.25 | O55: =M55*N55 -> 1 | P55: 0.1582 | Q55: =RANK(P55,$J$26:$J$37,0) -> 11 | R55: 0.15 | S55: =Q55*R55 -> 1.65 | T55: 1.05 | U55: =RANK(T55,$L$26:$L$37,1) -> 4 | V55: 0.1 | W55: =U55*V55 -> 0.4 | X55: =W55+S55+O55+K55+G55 -> 6.15 | Y55: =RANK(X55,$X$50:$X$61,1) -> 5
C56: Union Bank of India | D56: 0.0306 | E56: =RANK(D56,$D$26:$D$37,1) -> 12 | F56: 0.3 | G56: =E56*F56 -> 3.6 | H56: 0.027 | I56: =RANK(H56,$F$26:$F$37,0) -> 10 | J56: 0.2 | K56: =I56*J56 -> 2 | L56: 0.0101 | M56: =RANK(L56,$H$26:$H$37,0) -> 7 | N56: 0.25 | O56: =M56*N56 -> 1.75 | P56: 0.162 | Q56: =RANK(P56,$J$26:$J$37,0) -> 10 | R56: 0.15 | S56: =Q56*R56 -> 1.5 | T56: 1.08 | U56: =RANK(T56,$L$26:$L$37,1) -> 5 | V56: 0.1 | W56: =U56*V56 -> 0.5 | X56: =W56+S56+O56+K56+G56 -> 9.35 | Y56: =RANK(X56,$X$50:$X$61,1) -> 12
C57: Punjab National Bank (PNB) | D57: 0.0295 | E57: =RANK(D57,$D$26:$D$37,1) -> 11 | F57: 0.3 | G57: =E57*F57 -> 3.3 | H57: 0.0257 | I57: =RANK(H57,$F$26:$F$37,0) -> 11 | J57: 0.2 | K57: =I57*J57 -> 2.2 | L57: 0.0089 | M57: =RANK(L57,$H$26:$H$37,0) -> 8 | N57: 0.25 | O57: =M57*N57 -> 2 | P57: 0.1774 | Q57: =RANK(P57,$J$26:$J$37,0) -> 6 | R57: 0.15 | S57: =Q57*R57 -> 0.9 | T57: 0.84 | U57: =RANK(T57,$L$26:$L$37,1) -> 1 | V57: 0.1 | W57: =U57*V57 -> 0.1 | X57: =W57+S57+O57+K57+G57 -> 8.5 | Y57: =RANK(X57,$X$50:$X$61,1) -> 11
C58: Canara Bank | D58: 0.0184 | E58: =RANK(D58,$D$26:$D$37,1) -> 4 | F58: 0.3 | G58: =E58*F58 -> 1.2 | H58: 0.0251 | I58: =RANK(H58,$F$26:$F$37,0) -> 12 | J58: 0.2 | K58: =I58*J58 -> 2.4 | L58: 0.0102 | M58: =RANK(L58,$H$26:$H$37,0) -> 6 | N58: 0.25 | O58: =M58*N58 -> 1.5 | P58: 0.1704 | Q58: =RANK(P58,$J$26:$J$37,0) -> 7 | R58: 0.15 | S58: =Q58*R58 -> 1.05 | T58: 0.87 | U58: =RANK(T58,$L$26:$L$37,1) -> 3 | V58: 0.1 | W58: =U58*V58 -> 0.3 | X58: =W58+S58+O58+K58+G58 -> 6.45 | Y58: =RANK(X58,$X$50:$X$61,1) -> 6
C59: Bank of India (BOI) | D59: 0.0198 | E59: =RANK(D59,$D$26:$D$37,1) -> 6 | F59: 0.3 | G59: =E59*F59 -> 1.8 | H59: 0.028 | I59: =RANK(H59,$F$26:$F$37,0) -> 9 | J59: 0.2 | K59: =I59*J59 -> 1.8 | L59: 0.0085 | M59: =RANK(L59,$H$26:$H$37,0) -> 9 | N59: 0.25 | O59: =M59*N59 -> 2.25 | P59: 0.1801 | Q59: =RANK(P59,$J$26:$J$37,0) -> 4 | R59: 0.15 | S59: =Q59*R59 -> 0.6 | T59: 0.85 | U59: =RANK(T59,$L$26:$L$37,1) -> 2 | V59: 0.1 | W59: =U59*V59 -> 0.2 | X59: =W59+S59+O59+K59+G59 -> 6.65 | Y59: =RANK(X59,$X$50:$X$61,1) -> 8
C60: Bank of Maharashtra | D60: 0.0145 | E60: =RANK(D60,$D$26:$D$37,1) -> 2 | F60: 0.3 | G60: =E60*F60 -> 0.6 | H60: 0.039 | I60: =RANK(H60,$F$26:$F$37,0) -> 1 | J60: 0.2 | K60: =I60*J60 -> 0.2 | L60: 0.0186 | M60: =RANK(L60,$H$26:$H$37,0) -> 1 | N60: 0.25 | O60: =M60*N60 -> 0.25 | P60: 0.1836 | Q60: =RANK(P60,$J$26:$J$37,0) -> 3 | R60: 0.15 | S60: =Q60*R60 -> 0.45 | T60: 2.5 | U60: =RANK(T60,$L$26:$L$37,1) -> 12 | V60: 0.1 | W60: =U60*V60 -> 1.2 | X60: =W60+S60+O60+K60+G60 -> 2.7 | Y60: =RANK(X60,$X$50:$X$61,1) -> 2
C61: Central Bank of India | D61: 0.026 | E61: =RANK(D61,$D$26:$D$37,1) -> 9 | F61: 0.3 | G61: =E61*F61 -> 2.7 | H61: 0.029 | I61: =RANK(H61,$F$26:$F$37,0) -> 6 | J61: 0.2 | K61: =I61*J61 -> 1.2 | L61: 0.0079 | M61: =RANK(L61,$H$26:$H$37,0) -> 10 | N61: 0.25 | O61: =M61*N61 -> 2.5 | P61: 0.1683 | Q61: =RANK(P61,$J$26:$J$37,0) -> 8 | R61: 0.15 | S61: =Q61*R61 -> 1.2 | T61: 1.49 | U61: =RANK(T61,$L$26:$L$37,1) -> 7 | V61: 0.1 | W61: =U61*V61 -> 0.7 | X61: =W61+S61+O61+K61+G61 -> 8.3 | Y61: =RANK(X61,$X$50:$X$61,1) -> 9
Q76: w

Sheet SECTOR FUND & AUM
B3: SECTOR FUND
B4: Company Name (Ranked) | D4: Price | E4: No of Shares | F4: Assets allocattion | G4: Weightage
B6: 1 | C6: Indian Overseas Bank (IOB) | D6: 33.82 | E6: =F6/D6 -> 443524.54 | F6: =$F$19*G6 -> 15000000 | G6: 0.15
B7: 2 | C7: Bank of Maharashtra | D7: 78.5 | E7: =F7/D7 -> 165605.1 | F7: =$F$19*G7 -> 13000000 | G7: 0.13
B8: 3 | C8: Indian Bank | D8: 831.75 | E8: =F8/D8 -> 13225.128 | F8: =$F$19*G8 -> 11000000 | G8: 0.11
B9: 4 | C9: State Bank of India (SBI) | D9: 979.9 | E9: =F9/D9 -> 10205.123 | F9: =$F$19*G9 -> 10000000 | G9: 0.1
B10: 5 | C10: Bank of Baroda (BOB) | D10: 267.8 | E10: =F10/D10 -> 33607.17 | F10: =$F$19*G10 -> 9000000 | G10: 0.09
B11: 6 | C11: Canara Bank | D11: 130.84 | E11: =F11/D11 -> 61143.381 | F11: =$F$19*G11 -> 8000000 | G11: 0.08
B12: 7 | C12: UCO Bank | D12: 25.45 | E12: =F12/D12 -> 275049.12 | F12: =$F$19*G12 -> 7000000 | G12: 0.07
B13: 8 | C13: Bank of India (BOI) | D13: 143.95 | E13: =F13/D13 -> 48627.996 | F13: =$F$19*G13 -> 7000000 | G13: 0.07
B14: 9 | C14: Punjab & Sind Bank | D14: 24.08 | E14: =F14/D14 -> 249169.44 | F14: =$F$19*G14 -> 6000000 | G14: 0.06
B15: 10 | C15: Central Bank of India | D15: 32.61 | E15: =F15/D15 -> 153327.2 | F15: =$F$19*G15 -> 5000000 | G15: 0.05
B16: 11 | C16: Punjab National Bank (PNB) | D16: 104.62 | E16: =F16/D16 -> 47792.009 | F16: =$F$19*G16 -> 5000000 | G16: 0.05
B17: 12 | C17: Union Bank of India | D17: 164.9 | E17: =F17/D17 -> 24257.126 | F17: =$F$19*G17 -> 4000000 | G17: 0.04
C19: Total AUM | E19: =SUM(E6:E17) -> 1525533.3 | F19: 100000000
B23: CALCULATING AUM
D27: Week 1 | S27: Week 2 | AE27: Week 3 | AT27: Week 4 | BI27: Week 5 | BX27: Week 6 | CJ27: Week 7 | CY27: Week 8
D28: 18-05-2026 (Mon) | G28: 19-05-2026 (Tiues) | J28: 20-05-2026 (Wed) | M28: 21-05-2026 (Thurs) | P28: 22-05-2026 (Fri) | S28: 25-05-2026 (Mon) | V28: 26-05-2026 (Tues) | Y28: 27-05-2026 (Wed) | AB28: 29-05-2026 (Fri) | AE28: 01-06-2026 (Mon) | AH28: 02-06-2026 (Tues) | AK28: 03-06-2026 (Wed) | AN28: 04-06-2026 (Thurs) | AQ28: 05-06-2026 (Fri) | AT28: 08-06-2026 (Mon) | AW28: 09-06-2026 (Tues) | AZ28: 10-06-2026 (Wed) | BC28: 11-06-2026 (Thurs) | BF28: 12-06-2026 (Fri) | BI28: 15-06-2026 (Mon) | BL28: 16-06-2026 (Tues) | BO28: 17-06-2026 (Wed) | BR28: 18-06-2026 (Thurs) | BU28: 19-06-2026 (Fri) | BX28: 22-06-2026 (Mon) | CA28: 23-06-2026 (Tues) | CD28: 24-06-2026 (Wed) | CG28: 25-06-2026 (Thurs) | CJ28: 29-06-2026 (Mon) | CM28: 30-06-2026 (Tues) | CP28: 01-07-2026 (Wed) | CS28: 02-07-2026 (Thurs) | CV28: 03-07-2026 (Fri) | CY28: 06-07-2026 (Mon) | DB28: 07-07-2026 (Tues) | DE28: 08-07-2026 (Wed) | DH28: 09-07-2026 (Thurs) | DK28: 10-07-2026 (Fri)
B29: S.No | C29: Company Name (Ranked) | D29: Price | E29: No of Shares | F29: AUM | G29: Price | H29: No of Shares | I29: AUM | J29: Price | K29: No of Shares | L29: AUM | M29: Price | N29: No of Shares | O29: AUM | P29: Price | Q29: No of Shares | R29: AUM | S29: Price | T29: No of Shares | U29: AUM | V29: Price | W29: No of Shares | X29: AUM | Y29: Price | Z29: No of Shares | AA29: AUM | AB29: Price | AC29: No of Shares | AD29: AUM | AE29: Price | AF29: No of Shares | AG29: AUM | AH29: Price | AI29: No of Shares | AJ29: AUM | AK29: Price | AL29: No of Shares | AM29: AUM | AN29: Price | AO29: No of Shares | AP29: AUM | AQ29: Price | AR29: No of Shares | AS29: AUM | AT29: Price | AU29: No of Shares | AV29: AUM | AW29: Price | AX29: No of Shares | AY29: AUM | AZ29: Price | BA29: No of Shares | BB29: AUM | BC29: Price | BD29: No of Shares | BE29: AUM | BF29: Price | BG29: No of Shares | BH29: AUM | BI29: Price | BJ29: No of Shares | BK29: AUM | BL29: Price | BM29: No of Shares | BN29: AUM | BO29: Price | BP29: No of Shares | BQ29: AUM | BR29: Price | BS29: No of Shares | BT29: AUM | BU29: Price | BV29: No of Shares | BW29: AUM | BX29: Price | BY29: No of Shares | BZ29: AUM | CA29: Price | CB29: No of Shares | CC29: AUM | CD29: Price | CE29: No of Shares | CF29: AUM | CG29: Price | CH29: No of Shares | CI29: AUM | CJ29: Price | CK29: No of Shares | CL29: AUM | CM29: Price | CN29: No of Shares | CO29: AUM | CP29: Price | CQ29: No of Shares | CR29: AUM | CS29: Price | CT29: No of Shares | CU29: AUM | CV29: Price | CW29: No of Shares | CX29: AUM | CY29: Price | CZ29: No of Shares | DA29: AUM | DB29: Price | DC29: No of Shares | DD29: AUM | DE29: Price | DF29: No of Shares | DG29: AUM | DH29: Price | DI29: No of Shares | DJ29: AUM | DK29: Price | DL29: No of Shares | DM29: AUM
B31: 1 | C31: Indian Overseas Bank (IOB) | D31: 33.43 | E31: 443525 | F31: =D31*E31 -> 14827041 | G31: 33.54 | H31: 443525 | I31: =G31*H31 -> 14875828 | J31: 33.49 | K31: 443525 | L31: =J31*K31 -> 14853652 | M31: 33.77 | N31: 443525 | O31: =M31*N31 -> 14977839 | P31: 33.43 | Q31: 443525 | R31: =P31*Q31 -> 14827041 | S31: 33.79 | T31: 443525 | U31: =S31*T31 -> 14986710 | V31: 33.71 | W31: 443525 | X31: =V31*W31 -> 14951228 | Y31: 33.88 | Z31: 443525 | AA31: =Y31*Z31 -> 15026627 | AB31: 33.42 | AC31: 443525 | AD31: =AB31*AC31 -> 14822606 | AE31: 32.95 | AF31: 443525 | AG31: =AE31*AF31 -> 14614149 | AH31: 32.79 | AI31: 443525 | AJ31: =AH31*AI31 -> 14543185 | AK31: 33.01 | AL31: 443525 | AM31: =AK31*AL31 -> 14640760 | AN31: 32.92 | AO31: 443525 | AP31: =AN31*AO31 -> 14600843 | AQ31: 32.93 | AR31: 443525 | AS31: =AQ31*AR31 -> 14605278 | AT31: 32.71 | AU31: 443525 | AV31: =AT31*AU31 -> 14507703 | AW31: 33.43 | AX31: 443525 | AY31: =AW31*AX31 -> 14827041 | AZ31: 33.43 | BA31: 443525 | BB31: =AZ31*BA31 -> 14827041 | BC31: 32.42 | BD31: 443525 | BE31: =BC31*BD31 -> 14379080 | BF31: 33.37 | BG31: 443525 | BH31: =BF31*BG31 -> 14800429 | BI31: 33.84 | BJ31: 443525 | BK31: =BI31*BJ31 -> 15008886 | BL31: 34.03 | BM31: 443525 | BN31: =BL31*BM31 -> 15093156 | BO31: 35.58 | BP31: 443525 | BQ31: =BO31*BP31 -> 15780620 | BR31: 35.23 | BS31: 443525 | BT31: =BR31*BS31 -> 15625386 | BU31: 35.09 | BV31: 443525 | BW31: =BU31*BV31 -> 15563292 | BX31: 35.38 | BY31: 443525 | BZ31: =BX31*BY31 -> 15691915 | CA31: 34.95 | CB31: 443525 | CC31: =CA31*CB31 -> 15501199 | CD31: 34.9 | CE31: 443525 | CF31: =CD31*CE31 -> 15479022 | CG31: 34.47 | CH31: 443525 | CI31: =CG31*CH31 -> 15288307 | CJ31: 34.01 | CK31: 443525 | CL31: =CJ31*CK31 -> 15084285 | CM31: 34.1 | CN31: 443525 | CO31: =CM31*CN31 -> 15124202 | CP31: 34.18 | CQ31: 443525 | CR31: =CP31*CQ31 -> 15159684 | CS31: 34.45 | CT31: 443525 | CU31: =CS31*CT31 -> 15279436 | CV31: 34.37 | CW31: 443525 | CX31: =CV31*CW31 -> 15243954 | CY31: 34.2 | CZ31: 443525 | DA31: =CY31*CZ31 -> 15168555 | DB31: 34.03 | DC31: 443525 | DD31: =DB31*DC31 -> 15093156 | DE31: 33.47 | DF31: 443525 | DG31: =DE31*DF31 -> 14844782 | DH31: 33.76 | DI31: 443525 | DJ31: =DH31*DI31 -> 14973404 | DK31: 33.8 | DL31: 443525 | DM31: =DK31*DL31 -> 14991145
B32: 2 | C32: Bank of Maharashtra | D32: 77.8 | E32: 165605 | F32: =D32*E32 -> 12884069 | G32: 78.34 | H32: 165605 | I32: =G32*H32 -> 12973496 | J32: 78.75 | K32: 165605 | L32: =J32*K32 -> 13041394 | M32: 79.76 | N32: 165605 | O32: =M32*N32 -> 13208655 | P32: 80.04 | Q32: 165605 | R32: =P32*Q32 -> 13255024 | S32: 80.87 | T32: 165605 | U32: =S32*T32 -> 13392476 | V32: 80.15 | W32: 165605 | X32: =V32*W32 -> 13273241 | Y32: 80.08 | Z32: 165605 | AA32: =Y32*Z32 -> 13261648 | AB32: 79.27 | AC32: 165605 | AD32: =AB32*AC32 -> 13127508 | AE32: 77.64 | AF32: 165605 | AG32: =AE32*AF32 -> 12857572 | AH32: 80.5 | AI32: 165605 | AJ32: =AH32*AI32 -> 13331202 | AK32: 79.74 | AL32: 165605 | AM32: =AK32*AL32 -> 13205343 | AN32: 79.9 | AO32: 165605 | AP32: =AN32*AO32 -> 13231840 | AQ32: 79.19 | AR32: 165605 | AS32: =AQ32*AR32 -> 13114260 | AT32: 79.61 | AU32: 165605 | AV32: =AT32*AU32 -> 13183814 | AW32: 83.97 | AX32: 165605 | AY32: =AW32*AX32 -> 13905852 | AZ32: 84.18 | BA32: 165605 | BB32: =AZ32*BA32 -> 13940629 | BC32: 83.72 | BD32: 165605 | BE32: =BC32*BD32 -> 13864451 | BF32: 87.3 | BG32: 165605 | BH32: =BF32*BG32 -> 14457316 | BI32: 89.12 | BJ32: 165605 | BK32: =BI32*BJ32 -> 14758718 | BL32: 88.19 | BM32: 165605 | BN32: =BL32*BM32 -> 14604705 | BO32: 90.14 | BP32: 165605 | BQ32: =BO32*BP32 -> 14927635 | BR32: 89.5 | BS32: 165605 | BT32: =BR32*BS32 -> 14821648 | BU32: 90.19 | BV32: 165605 | BW32: =BU32*BV32 -> 14935915 | BX32: 89.47 | BY32: 165605 | BZ32: =BX32*BY32 -> 14816679 | CA32: 87.89 | CB32: 165605 | CC32: =CA32*CB32 -> 14555023 | CD32: 88.53 | CE32: 165605 | CF32: =CD32*CE32 -> 14661011 | CG32: 88.71 | CH32: 165605 | CI32: =CG32*CH32 -> 14690820 | CJ32: 93.85 | CK32: 165605 | CL32: =CJ32*CK32 -> 15542029 | CM32: 91.44 | CN32: 165605 | CO32: =CM32*CN32 -> 15142921 | CP32: 91.2 | CQ32: 165605 | CR32: =CP32*CQ32 -> 15103176 | CS32: 91.04 | CT32: 165605 | CU32: =CS32*CT32 -> 15076679 | CV32: 88.53 | CW32: 165605 | CX32: =CV32*CW32 -> 14661011 | CY32: 86.51 | CZ32: 165605 | DA32: =CY32*CZ32 -> 14326489 | DB32: 83.19 | DC32: 165605 | DD32: =DB32*DC32 -> 13776680 | DE32: 80.6 | DF32: 165605 | DG32: =DE32*DF32 -> 13347763 | DH32: 82.01 | DI32: 165605 | DJ32: =DH32*DI32 -> 13581266 | DK32: 84.25 | DL32: 165605 | DM32: =DK32*DL32 -> 13952221
B33: 3 | C33: Indian Bank | D33: 810 | E33: 13225 | F33: =D33*E33 -> 10712250 | G33: 817.1 | H33: 13225 | I33: =G33*H33 -> 10806148 | J33: 810.2 | K33: 13225 | L33: =J33*K33 -> 10714895 | M33: 818.95 | N33: 13225 | O33: =M33*N33 -> 10830614 | P33: 825.95 | Q33: 13225 | R33: =P33*Q33 -> 10923189 | S33: 840.15 | T33: 13225 | U33: =S33*T33 -> 11110984 | V33: 835.5 | W33: 13225 | X33: =V33*W33 -> 11049488 | Y33: 833.35 | Z33: 13225 | AA33: =Y33*Z33 -> 11021054 | AB33: 833 | AC33: 13225 | AD33: =AB33*AC33 -> 11016425 | AE33: 809.75 | AF33: 13225 | AG33: =AE33*AF33 -> 10708944 | AH33: 878.3 | AI33: 13225 | AJ33: =AH33*AI33 -> 11615518 | AK33: 847.9 | AL33: 13225 | AM33: =AK33*AL33 -> 11213478 | AN33: 848.25 | AO33: 13225 | AP33: =AN33*AO33 -> 11218106 | AQ33: 842.05 | AR33: 13225 | AS33: =AQ33*AR33 -> 11136111 | AT33: 843 | AU33: 13225 | AV33: =AT33*AU33 -> 11148675 | AW33: 874.95 | AX33: 13225 | AY33: =AW33*AX33 -> 11571214 | AZ33: 833.45 | BA33: 13225 | BB33: =AZ33*BA33 -> 11022376 | BC33: 825.65 | BD33: 13225 | BE33: =BC33*BD33 -> 10919221 | BF33: 845.5 | BG33: 13225 | BH33: =BF33*BG33 -> 11181738 | BI33: 849.6 | BJ33: 13225 | BK33: =BI33*BJ33 -> 11235960 | BL33: 853.3 | BM33: 13225 | BN33: =BL33*BM33 -> 11284892 | BO33: 876.35 | BP33: 13225 | BQ33: =BO33*BP33 -> 11589729 | BR33: 875.7 | BS33: 13225 | BT33: =BR33*BS33 -> 11581132 | BU33: 870.65 | BV33: 13225 | BW33: =BU33*BV33 -> 11514346 | BX33: 861.1 | BY33: 13225 | BZ33: =BX33*BY33 -> 11388048 | CA33: 846.4 | CB33: 13225 | CC33: =CA33*CB33 -> 11193640 | CD33: 843.65 | CE33: 13225 | CF33: =CD33*CE33 -> 11157271 | CG33: 832.6 | CH33: 13225 | CI33: =CG33*CH33 -> 11011135 | CJ33: 814.7 | CK33: 13225 | CL33: =CJ33*CK33 -> 10774408 | CM33: 816.65 | CN33: 13225 | CO33: =CM33*CN33 -> 10800196 | CP33: 820.95 | CQ33: 13225 | CR33: =CP33*CQ33 -> 10857064 | CS33: 815.1 | CT33: 13225 | CU33: =CS33*CT33 -> 10779698 | CV33: 798.95 | CW33: 13225 | CX33: =CV33*CW33 -> 10566114 | CY33: 786.9 | CZ33: 13225 | DA33: =CY33*CZ33 -> 10406752 | DB33: 785.95 | DC33: 13225 | DD33: =DB33*DC33 -> 10394189 | DE33: 772.4 | DF33: 13225 | DG33: =DE33*DF33 -> 10214990 | DH33: 793.15 | DI33: 13225 | DJ33: =DH33*DI33 -> 10489409 | DK33: 870.7 | DL33: 13225 | DM33: =DK33*DL33 -> 11515008
B34: 4 | C34: State Bank of India (SBI) | D34: 939.4 | E34: 10205 | F34: =D34*E34 -> 9586577 | G34: 948.8 | H34: 10205 | I34: =G34*H34 -> 9682504 | J34: 950.9 | K34: 10205 | L34: =J34*K34 -> 9703934.5 | M34: 950.9 | N34: 10205 | O34: =M34*N34 -> 9703934.5 | P34: 949.2 | Q34: 10205 | R34: =P34*Q34 -> 9686586 | S34: 969.6 | T34: 10205 | U34: =S34*T34 -> 9894768 | V34: 968.6 | W34: 10205 | X34: =V34*W34 -> 9884563 | Y34: 967.8 | Z34: 10205 | AA34: =Y34*Z34 -> 9876399 | AB34: 964.4 | AC34: 10205 | AD34: =AB34*AC34 -> 9841702 | AE34: 954.1 | AF34: 10205 | AG34: =AE34*AF34 -> 9736590.5 | AH34: 956.65 | AI34: 10205 | AJ34: =AH34*AI34 -> 9762613.2 | AK34: 954.1 | AL34: 10205 | AM34: =AK34*AL34 -> 9736590.5 | AN34: 979.25 | AO34: 10205 | AP34: =AN34*AO34 -> 9993246.2 | AQ34: 978 | AR34: 10205 | AS34: =AQ34*AR34 -> 9980490 | AT34: 981.95 | AU34: 10205 | AV34: =AT34*AU34 -> 10020800 | AW34: 1002.7 | AX34: 10205 | AY34: =AW34*AX34 -> 10232554 | AZ34: 1003.25 | BA34: 10205 | BB34: =AZ34*BA34 -> 10238166 | BC34: 1000.7 | BD34: 10205 | BE34: =BC34*BD34 -> 10212144 | BF34: 1017.15 | BG34: 10205 | BH34: =BF34*BG34 -> 10380016 | BI34: 1020.85 | BJ34: 10205 | BK34: =BI34*BJ34 -> 10417774 | BL34: 1015.3 | BM34: 10205 | BN34: =BL34*BM34 -> 10361136 | BO34: 1026.5 | BP34: 10205 | BQ34: =BO34*BP34 -> 10475432 | BR34: 1042.7 | BS34: 10205 | BT34: =BR34*BS34 -> 10640754 | BU34: 1035.1 | BV34: 10205 | BW34: =BU34*BV34 -> 10563196 | BX34: 1040.75 | BY34: 10205 | BZ34: =BX34*BY34 -> 10620854 | CA34: 1024.2 | CB34: 10205 | CC34: =CA34*CB34 -> 10451961 | CD34: 1034.6 | CE34: 10205 | CF34: =CD34*CE34 -> 10558093 | CG34: 1045 | CH34: 10205 | CI34: =CG34*CH34 -> 10664225 | CJ34: 1036.1 | CK34: 10205 | CL34: =CJ34*CK34 -> 10573400 | CM34: 1026.9 | CN34: 10205 | CO34: =CM34*CN34 -> 10479514 | CP34: 1047.4 | CQ34: 10205 | CR34: =CP34*CQ34 -> 10688717 | CS34: 1051.6 | CT34: 10205 | CU34: =CS34*CT34 -> 10731578 | CV34: 1040 | CW34: 10205 | CX34: =CV34*CW34 -> 10613200 | CY34: 1037.7 | CZ34: 10205 | DA34: =CY34*CZ34 -> 10589728 | DB34: 1038.1 | DC34: 10205 | DD34: =DB34*DC34 -> 10593810 | DE34: 1016.9 | DF34: 10205 | DG34: =DE34*DF34 -> 10377464 | DH34: 1022.1 | DI34: 10205 | DJ34: =DH34*DI34 -> 10430530 | DK34: 1036 | DL34: 10205 | DM34: =DK34*DL34 -> 10572380
B35: 5 | C35: Bank of Baroda (BOB) | D35: 260.05 | E35: 33607 | F35: =D35*E35 -> 8739500.3 | G35: 260.6 | H35: 33607 | I35: =G35*H35 -> 8757984.2 | J35: 263.55 | K35: 33607 | L35: =J35*K35 -> 8857124.8 | M35: 263.1 | N35: 33607 | O35: =M35*N35 -> 8842001.7 | P35: 265.4 | Q35: 33607 | R35: =P35*Q35 -> 8919297.8 | S35: 272.25 | T35: 33607 | U35: =S35*T35 -> 9149505.8 | V35: 270.5 | W35: 33607 | X35: =V35*W35 -> 9090693.5 | Y35: 270.95 | Z35: 33607 | AA35: =Y35*Z35 -> 9105816.7 | AB35: 268.5 | AC35: 33607 | AD35: =AB35*AC35 -> 9023479.5 | AE35: 264.35 | AF35: 33607 | AG35: =AE35*AF35 -> 8884010.5 | AH35: 265.8 | AI35: 33607 | AJ35: =AH35*AI35 -> 8932740.6 | AK35: 268.85 | AL35: 33607 | AM35: =AK35*AL35 -> 9035242 | AN35: 271.3 | AO35: 33607 | AP35: =AN35*AO35 -> 9117579.1 | AQ35: 263.7 | AR35: 33607 | AS35: =AQ35*AR35 -> 8862165.9 | AT35: 259.25 | AU35: 33607 | AV35: =AT35*AU35 -> 8712614.8 | AW35: 273.8 | AX35: 33607 | AY35: =AW35*AX35 -> 9201596.6 | AZ35: 269.3 | BA35: 33607 | BB35: =AZ35*BA35 -> 9050365.1 | BC35: 267.6 | BD35: 33607 | BE35: =BC35*BD35 -> 8993233.2 | BF35: 274.75 | BG35: 33607 | BH35: =BF35*BG35 -> 9233523.2 | BI35: 276.05 | BJ35: 33607 | BK35: =BI35*BJ35 -> 9277212.3 | BL35: 275.35 | BM35: 33607 | BN35: =BL35*BM35 -> 9253687.5 | BO35: 281.85 | BP35: 33607 | BQ35: =BO35*BP35 -> 9472133 | BR35: 283 | BS35: 33607 | BT35: =BR35*BS35 -> 9510781 | BU35: 281.05 | BV35: 33607 | BW35: =BU35*BV35 -> 9445247.3 | BX35: 286.05 | BY35: 33607 | BZ35: =BX35*BY35 -> 9613282.3 | CA35: 277.8 | CB35: 33607 | CC35: =CA35*CB35 -> 9336024.6 | CD35: 279.9 | CE35: 33607 | CF35: =CD35*CE35 -> 9406599.3 | CG35: 279.15 | CH35: 33607 | CI35: =CG35*CH35 -> 9381394 | CJ35: 272.8 | CK35: 33607 | CL35: =CJ35*CK35 -> 9167989.6 | CM35: 272.8 | CN35: 33607 | CO35: =CM35*CN35 -> 9167989.6 | CP35: 272.4 | CQ35: 33607 | CR35: =CP35*CQ35 -> 9154546.8 | CS35: 271.65 | CT35: 33607 | CU35: =CS35*CT35 -> 9129341.5 | CV35: 252.2 | CW35: 33607 | CX35: =CV35*CW35 -> 8475685.4 | CY35: 249.95 | CZ35: 33607 | DA35: =CY35*CZ35 -> 8400069.7 | DB35: 247.85 | DC35: 33607 | DD35: =DB35*DC35 -> 8329495 | DE35: 240.45 | DF35: 33607 | DG35: =DE35*DF35 -> 8080803.1 | DH35: 250.95 | DI35: 33607 | DJ35: =DH35*DI35 -> 8433676.7 | DK35: 244.6 | DL35: 33607 | DM35: =DK35*DL35 -> 8220272.2
B36: 6 | C36: Canara Bank | D36: 124.9 | E36: 61143 | F36: =D36*E36 -> 7636760.7 | G36: 126.15 | H36: 61143 | I36: =G36*H36 -> 7713189.5 | J36: 127.66 | K36: 61143 | L36: =J36*K36 -> 7805515.4 | M36: 127.97 | N36: 61143 | O36: =M36*N36 -> 7824469.7 | P36: 128.23 | Q36: 61143 | R36: =P36*Q36 -> 7840366.9 | S36: 133.7 | T36: 61143 | U36: =S36*T36 -> 8174819.1 | V36: 31.04 | W36: 61143 | X36: =V36*W36 -> 1897878.7 | Y36: 30.84 | Z36: 61143 | AA36: =Y36*Z36 -> 1885650.1 | AB36: 30.77 | AC36: 61143 | AD36: =AB36*AC36 -> 1881370.1 | AE36: 127.96 | AF36: 61143 | AG36: =AE36*AF36 -> 7823858.3 | AH36: 129.08 | AI36: 61143 | AJ36: =AH36*AI36 -> 7892338.4 | AK36: 131.85 | AL36: 61143 | AM36: =AK36*AL36 -> 8061704.5 | AN36: 133.12 | AO36: 61143 | AP36: =AN36*AO36 -> 8139356.2 | AQ36: 135.81 | AR36: 61143 | AS36: =AQ36*AR36 -> 8303830.8 | AT36: 131.91 | AU36: 61143 | AV36: =AT36*AU36 -> 8065373.1 | AW36: 137.51 | AX36: 61143 | AY36: =AW36*AX36 -> 8407773.9 | AZ36: 133.46 | BA36: 61143 | BB36: =AZ36*BA36 -> 8160144.8 | BC36: 131.52 | BD36: 61143 | BE36: =BC36*BD36 -> 8041527.4 | BF36: 131.67 | BG36: 61143 | BH36: =BF36*BG36 -> 8050698.8 | BI36: 132.2 | BJ36: 61143 | BK36: =BI36*BJ36 -> 8083104.6 | BL36: 132.83 | BM36: 61143 | BN36: =BL36*BM36 -> 8121624.7 | BO36: 135.24 | BP36: 61143 | BQ36: =BO36*BP36 -> 8268979.3 | BR36: 134.97 | BS36: 61143 | BT36: =BR36*BS36 -> 8252470.7 | BU36: 133.74 | BV36: 61143 | BW36: =BU36*BV36 -> 8177264.8 | BX36: 134.82 | BY36: 61143 | BZ36: =BX36*BY36 -> 8243299.3 | CA36: 130.37 | CB36: 61143 | CC36: =CA36*CB36 -> 7971212.9 | CD36: 130.35 | CE36: 61143 | CF36: =CD36*CE36 -> 7969990 | CG36: 128.95 | CH36: 61143 | CI36: =CG36*CH36 -> 7884389.8 | CJ36: 125.86 | CK36: 61143 | CL36: =CJ36*CK36 -> 7695458 | CM36: 125.52 | CN36: 61143 | CO36: =CM36*CN36 -> 7674669.4 | CP36: 126.28 | CQ36: 61143 | CR36: =CP36*CQ36 -> 7721138 | CS36: 126.64 | CT36: 61143 | CU36: =CS36*CT36 -> 7743149.5 | CV36: 127.19 | CW36: 61143 | CX36: =CV36*CW36 -> 7776778.2 | CY36: 126.46 | CZ36: 61143 | DA36: =CY36*CZ36 -> 7732143.8 | DB36: 125.03 | DC36: 61143 | DD36: =DB36*DC36 -> 7644709.3 | DE36: 121.15 | DF36: 61143 | DG36: =DE36*DF36 -> 7407474.5 | DH36: 124.8 | DI36: 61143 | DJ36: =DH36*DI36 -> 7630646.4 | DK36: 129.3 | DL36: 61143 | DM36: =DK36*DL36 -> 7905789.9
B37: 7 | C37: UCO Bank | D37: 24.68 | E37: 275049 | F37: =D37*E37 -> 6788209.3 | G37: 24.77 | H37: 275049 | I37: =G37*H37 -> 6812963.7 | J37: 24.53 | K37: 275049 | L37: =J37*K37 -> 6746952 | M37: 24.82 | N37: 275049 | O37: =M37*N37 -> 6826716.2 | P37: 24.75 | Q37: 275049 | R37: =P37*Q37 -> 6807462.8 | S37: 25.54 | T37: 275049 | U37: =S37*T37 -> 7024751.5 | V37: 25.43 | W37: 275049 | X37: =V37*W37 -> 6994496.1 | Y37: 25.54 | Z37: 275049 | AA37: =Y37*Z37 -> 7024751.5 | AB37: 25.2 | AC37: 275049 | AD37: =AB37*AC37 -> 6931234.8 | AE37: 24.89 | AF37: 275049 | AG37: =AE37*AF37 -> 6845969.6 | AH37: 25.83 | AI37: 275049 | AJ37: =AH37*AI37 -> 7104515.7 | AK37: 25.1 | AL37: 275049 | AM37: =AK37*AL37 -> 6903729.9 | AN37: 25.07 | AO37: 275049 | AP37: =AN37*AO37 -> 6895478.4 | AQ37: 25.26 | AR37: 275049 | AS37: =AQ37*AR37 -> 6947737.7 | AT37: 25.03 | AU37: 275049 | AV37: =AT37*AU37 -> 6884476.5 | AW37: 26.04 | AX37: 275049 | AY37: =AW37*AX37 -> 7162276 | AZ37: 25.75 | BA37: 275049 | BB37: =AZ37*BA37 -> 7082511.8 | BC37: 25.12 | BD37: 275049 | BE37: =BC37*BD37 -> 6909230.9 | BF37: 25.99 | BG37: 275049 | BH37: =BF37*BG37 -> 7148523.5 | BI37: 26.18 | BJ37: 275049 | BK37: =BI37*BJ37 -> 7200782.8 | BL37: 26.33 | BM37: 275049 | BN37: =BL37*BM37 -> 7242040.2 | BO37: 28.2 | BP37: 275049 | BQ37: =BO37*BP37 -> 7756381.8 | BR37: 27.99 | BS37: 275049 | BT37: =BR37*BS37 -> 7698621.5 | BU37: 27.58 | BV37: 275049 | BW37: =BU37*BV37 -> 7585851.4 | BX37: 27.57 | BY37: 275049 | BZ37: =BX37*BY37 -> 7583100.9 | CA37: 26.85 | CB37: 275049 | CC37: =CA37*CB37 -> 7385065.7 | CD37: 27.11 | CE37: 275049 | CF37: =CD37*CE37 -> 7456578.4 | CG37: 27.16 | CH37: 275049 | CI37: =CG37*CH37 -> 7470330.8 | CJ37: 26.79 | CK37: 275049 | CL37: =CJ37*CK37 -> 7368562.7 | CM37: 26.98 | CN37: 275049 | CO37: =CM37*CN37 -> 7420822 | CP37: 26.87 | CQ37: 275049 | CR37: =CP37*CQ37 -> 7390566.6 | CS37: 27.14 | CT37: 275049 | CU37: =CS37*CT37 -> 7464829.9 | CV37: 26.95 | CW37: 275049 | CX37: =CV37*CW37 -> 7412570.5 | CY37: 26.56 | CZ37: 275049 | DA37: =CY37*CZ37 -> 7305301.4 | DB37: 26.39 | DC37: 275049 | DD37: =DB37*DC37 -> 7258543.1 | DE37: 26.11 | DF37: 275049 | DG37: =DE37*DF37 -> 7181529.4 | DH37: 26.04 | DI37: 275049 | DJ37: =DH37*DI37 -> 7162276 | DK37: 26.7 | DL37: 275049 | DM37: =DK37*DL37 -> 7343808.3
B38: 8 | C38: Bank of India (BOI) | D38: 138.22 | E38: 48628 | F38: =D38*E38 -> 6721362.2 | G38: 138.64 | H38: 48628 | I38: =G38*H38 -> 6741785.9 | J38: 139.17 | K38: 48628 | L38: =J38*K38 -> 6767558.8 | M38: 139.23 | N38: 48628 | O38: =M38*N38 -> 6770476.4 | P38: 139.92 | Q38: 48628 | R38: =P38*Q38 -> 6804029.8 | S38: 146.01 | T38: 48628 | U38: =S38*T38 -> 7100174.3 | V38: 145.05 | W38: 48628 | X38: =V38*W38 -> 7053491.4 | Y38: 147 | Z38: 48628 | AA38: =Y38*Z38 -> 7148316 | AB38: 139.91 | AC38: 48628 | AD38: =AB38*AC38 -> 6803543.5 | AE38: 136.74 | AF38: 48628 | AG38: =AE38*AF38 -> 6649392.7 | AH38: 137.29 | AI38: 48628 | AJ38: =AH38*AI38 -> 6676138.1 | AK38: 139.69 | AL38: 48628 | AM38: =AK38*AL38 -> 6792845.3 | AN38: 141.46 | AO38: 48628 | AP38: =AN38*AO38 -> 6878916.9 | AQ38: 141.46 | AR38: 48628 | AS38: =AQ38*AR38 -> 6878916.9 | AT38: 140.08 | AU38: 48628 | AV38: =AT38*AU38 -> 6811810.2 | AW38: 147.72 | AX38: 48628 | AY38: =AW38*AX38 -> 7183328.2 | AZ38: 144.86 | BA38: 48628 | BB38: =AZ38*BA38 -> 7044252.1 | BC38: 141.73 | BD38: 48628 | BE38: =BC38*BD38 -> 6892046.4 | BF38: 145.68 | BG38: 48628 | BH38: =BF38*BG38 -> 7084127 | BI38: 146.23 | BJ38: 48628 | BK38: =BI38*BJ38 -> 7110872.4 | BL38: 145.67 | BM38: 48628 | BN38: =BL38*BM38 -> 7083640.8 | BO38: 147.14 | BP38: 48628 | BQ38: =BO38*BP38 -> 7155123.9 | BR38: 147.67 | BS38: 48628 | BT38: =BR38*BS38 -> 7180896.8 | BU38: 146.57 | BV38: 48628 | BW38: =BU38*BV38 -> 7127406 | BX38: 146.09 | BY38: 48628 | BZ38: =BX38*BY38 -> 7104064.5 | CA38: 144.51 | CB38: 48628 | CC38: =CA38*CB38 -> 7027232.3 | CD38: 144.15 | CE38: 48628 | CF38: =CD38*CE38 -> 7009726.2 | CG38: 144.72 | CH38: 48628 | CI38: =CG38*CH38 -> 7037444.2 | CJ38: 142.55 | CK38: 48628 | CL38: =CJ38*CK38 -> 6931921.4 | CM38: 140.39 | CN38: 48628 | CO38: =CM38*CN38 -> 6826884.9 | CP38: 141.63 | CQ38: 48628 | CR38: =CP38*CQ38 -> 6887183.6 | CS38: 144.96 | CT38: 48628 | CU38: =CS38*CT38 -> 7049114.9 | CV38: 144.05 | CW38: 48628 | CX38: =CV38*CW38 -> 7004863.4 | CY38: 139.8 | CZ38: 48628 | DA38: =CY38*CZ38 -> 6798194.4 | DB38: 142.41 | DC38: 48628 | DD38: =DB38*DC38 -> 6925113.5 | DE38: 135.12 | DF38: 48628 | DG38: =DE38*DF38 -> 6570615.4 | DH38: 138.53 | DI38: 48628 | DJ38: =DH38*DI38 -> 6736436.8 | DK38: 144.9 | DL38: 48628 | DM38: =DK38*DL38 -> 7046197.2
B39: 9 | C39: Punjab & Sind Bank | D39: 23.41 | E39: 249169 | F39: =D39*E39 -> 5833046.3 | G39: 23.51 | H39: 249169 | I39: =G39*H39 -> 5857963.2 | J39: 23.54 | K39: 249169 | L39: =J39*K39 -> 5865438.3 | M39: 23.69 | N39: 249169 | O39: =M39*N39 -> 5902813.6 | P39: 23.64 | Q39: 249169 | R39: =P39*Q39 -> 5890355.2 | S39: 24.05 | T39: 249169 | U39: =S39*T39 -> 5992514.5 | V39: 24.15 | W39: 249169 | X39: =V39*W39 -> 6017431.3 | Y39: 24.28 | Z39: 249169 | AA39: =Y39*Z39 -> 6049823.3 | AB39: 23.98 | AC39: 249169 | AD39: =AB39*AC39 -> 5975072.6 | AE39: 23.72 | AF39: 249169 | AG39: =AE39*AF39 -> 5910288.7 | AH39: 23.41 | AI39: 249169 | AJ39: =AH39*AI39 -> 5833046.3 | AK39: 23.41 | AL39: 249169 | AM39: =AK39*AL39 -> 5833046.3 | AN39: 23.29 | AO39: 249169 | AP39: =AN39*AO39 -> 5803146 | AQ39: 23.68 | AR39: 249169 | AS39: =AQ39*AR39 -> 5900321.9 | AT39: 23.19 | AU39: 249169 | AV39: =AT39*AU39 -> 5778229.1 | AW39: 24.21 | AX39: 249169 | AY39: =AW39*AX39 -> 6032381.5 | AZ39: 23.82 | BA39: 249169 | BB39: =AZ39*BA39 -> 5935205.6 | BC39: 23.38 | BD39: 249169 | BE39: =BC39*BD39 -> 5825571.2 | BF39: 24.02 | BG39: 249169 | BH39: =BF39*BG39 -> 5985039.4 | BI39: 24.01 | BJ39: 249169 | BK39: =BI39*BJ39 -> 5982547.7 | BL39: 24 | BM39: 249169 | BN39: =BL39*BM39 -> 5980056 | BO39: 25.48 | BP39: 249169 | BQ39: =BO39*BP39 -> 6348826.1 | BR39: 25.15 | BS39: 249169 | BT39: =BR39*BS39 -> 6266600.3 | BU39: 25.09 | BV39: 249169 | BW39: =BU39*BV39 -> 6251650.2 | BX39: 25.07 | BY39: 249169 | BZ39: =BX39*BY39 -> 6246666.8 | CA39: 24.84 | CB39: 249169 | CC39: =CA39*CB39 -> 6189358 | CD39: 25.01 | CE39: 249169 | CF39: =CD39*CE39 -> 6231716.7 | CG39: 24.63 | CH39: 249169 | CI39: =CG39*CH39 -> 6137032.5 | CJ39: 24.35 | CK39: 249169 | CL39: =CJ39*CK39 -> 6067265.2 | CM39: 24.24 | CN39: 249169 | CO39: =CM39*CN39 -> 6039856.6 | CP39: 24.58 | CQ39: 249169 | CR39: =CP39*CQ39 -> 6124574 | CS39: 24.91 | CT39: 249169 | CU39: =CS39*CT39 -> 6206799.8 | CV39: 24.75 | CW39: 249169 | CX39: =CV39*CW39 -> 6166932.8 | CY39: 24.81 | CZ39: 249169 | DA39: =CY39*CZ39 -> 6181882.9 | DB39: 24.77 | DC39: 249169 | DD39: =DB39*DC39 -> 6171916.1 | DE39: 24.1 | DF39: 249169 | DG39: =DE39*DF39 -> 6004972.9 | DH39: 24.46 | DI39: 249169 | DJ39: =DH39*DI39 -> 6094673.7 | DK39: 24.99 | DL39: 249169 | DM39: =DK39*DL39 -> 6226733.3
B40: 10 | C40: Central Bank of India | D40: 33.77 | E40: 153327 | F40: =D40*E40 -> 5177852.8 | G40: 34.04 | H40: 153327 | I40: =G40*H40 -> 5219251.1 | J40: 33.85 | K40: 153327 | L40: =J40*K40 -> 5190119 | M40: 33.92 | N40: 153327 | O40: =M40*N40 -> 5200851.8 | P40: 31.27 | Q40: 153327 | R40: =P40*Q40 -> 4794535.3 | S40: 31.27 | T40: 153327 | U40: =S40*T40 -> 4794535.3 | V40: 31.04 | W40: 153327 | X40: =V40*W40 -> 4759270.1 | Y40: 30.84 | Z40: 153327 | AA40: =Y40*Z40 -> 4728604.7 | AB40: 30.77 | AC40: 153327 | AD40: =AB40*AC40 -> 4717871.8 | AE40: 30.31 | AF40: 153327 | AG40: =AE40*AF40 -> 4647341.4 | AH40: 37 | AI40: 153327 | AJ40: =AH40*AI40 -> 5673099 | AK40: 30.29 | AL40: 153327 | AM40: =AK40*AL40 -> 4644274.8 | AN40: 30.4 | AO40: 153327 | AP40: =AN40*AO40 -> 4661140.8 | AQ40: 30.39 | AR40: 153327 | AS40: =AQ40*AR40 -> 4659607.5 | AT40: 30.43 | AU40: 153327 | AV40: =AT40*AU40 -> 4665740.6 | AW40: 31.08 | AX40: 153327 | AY40: =AW40*AX40 -> 4765403.2 | AZ40: 30.76 | BA40: 153327 | BB40: =AZ40*BA40 -> 4716338.5 | BC40: 30.17 | BD40: 153327 | BE40: =BC40*BD40 -> 4625875.6 | BF40: 31.04 | BG40: 153327 | BH40: =BF40*BG40 -> 4759270.1 | BI40: 31.87 | BJ40: 153327 | BK40: =BI40*BJ40 -> 4886531.5 | BL40: 32 | BM40: 153327 | BN40: =BL40*BM40 -> 4906464 | BO40: 33.87 | BP40: 153327 | BQ40: =BO40*BP40 -> 5193185.5 | BR40: 33.1 | BS40: 153327 | BT40: =BR40*BS40 -> 5075123.7 | BU40: 32.84 | BV40: 153327 | BW40: =BU40*BV40 -> 5035258.7 | BX40: 33.03 | BY40: 153327 | BZ40: =BX40*BY40 -> 5064390.8 | CA40: 32.5 | CB40: 153327 | CC40: =CA40*CB40 -> 4983127.5 | CD40: 32.51 | CE40: 153327 | CF40: =CD40*CE40 -> 4984660.8 | CG40: 32.2 | CH40: 153327 | CI40: =CG40*CH40 -> 4937129.4 | CJ40: 33.62 | CK40: 153327 | CL40: =CJ40*CK40 -> 5154853.7 | CM40: 32.53 | CN40: 153327 | CO40: =CM40*CN40 -> 4987727.3 | CP40: 32.68 | CQ40: 153327 | CR40: =CP40*CQ40 -> 5010726.4 | CS40: 32.55 | CT40: 153327 | CU40: =CS40*CT40 -> 4990793.8 | CV40: 32.8 | CW40: 153327 | CX40: =CV40*CW40 -> 5029125.6 | CY40: 32.61 | CZ40: 153327 | DA40: =CY40*CZ40 -> 4999993.5 | DB40: 32.13 | DC40: 153327 | DD40: =DB40*DC40 -> 4926396.5 | DE40: 31.25 | DF40: 153327 | DG40: =DE40*DF40 -> 4791468.8 | DH40: 31.65 | DI40: 153327 | DJ40: =DH40*DI40 -> 4852799.5 | DK40: 32.6 | DL40: 153327 | DM40: =DK40*DL40 -> 4998460.2
B41: 11 | C41: Punjab National Bank (PNB) | D41: 99.49 | E41: 47792 | F41: =D41*E41 -> 4754826.1 | G41: 101.3 | H41: 47792 | I41: =G41*H41 -> 4841329.6 | J41: 102.22 | K41: 47792 | L41: =J41*K41 -> 4885298.2 | M41: 101.92 | N41: 47792 | O41: =M41*N41 -> 4870960.6 | P41: 102.66 | Q41: 47792 | R41: =P41*Q41 -> 4906326.7 | S41: 106.26 | T41: 47792 | U41: =S41*T41 -> 5078377.9 | V41: 105.95 | W41: 47792 | X41: =V41*W41 -> 5063562.4 | Y41: 106.67 | Z41: 47792 | AA41: =Y41*Z41 -> 5097972.6 | AB41: 106.05 | AC41: 47792 | AD41: =AB41*AC41 -> 5068341.6 | AE41: 103.78 | AF41: 47792 | AG41: =AE41*AF41 -> 4959853.8 | AH41: 104.09 | AI41: 47792 | AJ41: =AH41*AI41 -> 4974669.3 | AK41: 105.9 | AL41: 47792 | AM41: =AK41*AL41 -> 5061172.8 | AN41: 106.27 | AO41: 47792 | AP41: =AN41*AO41 -> 5078855.8 | AQ41: 106.85 | AR41: 47792 | AS41: =AQ41*AR41 -> 5106575.2 | AT41: 105.71 | AU41: 47792 | AV41: =AT41*AU41 -> 5052092.3 | AW41: 109.65 | AX41: 47792 | AY41: =AW41*AX41 -> 5240392.8 | AZ41: 107.17 | BA41: 47792 | BB41: =AZ41*BA41 -> 5121868.6 | BC41: 106.17 | BD41: 47792 | BE41: =BC41*BD41 -> 5074076.6 | BF41: 106.88 | BG41: 47792 | BH41: =BF41*BG41 -> 5108009 | BI41: 107.96 | BJ41: 47792 | BK41: =BI41*BJ41 -> 5159624.3 | BL41: 107.97 | BM41: 47792 | BN41: =BL41*BM41 -> 5160102.2 | BO41: 108.87 | BP41: 47792 | BQ41: =BO41*BP41 -> 5203115 | BR41: 109.58 | BS41: 47792 | BT41: =BR41*BS41 -> 5237047.4 | BU41: 108.77 | BV41: 47792 | BW41: =BU41*BV41 -> 5198335.8 | BX41: 109.8 | BY41: 47792 | BZ41: =BX41*BY41 -> 5247561.6 | CA41: 107.43 | CB41: 47792 | CC41: =CA41*CB41 -> 5134294.6 | CD41: 107.71 | CE41: 47792 | CF41: =CD41*CE41 -> 5147676.3 | CG41: 107.87 | CH41: 47792 | CI41: =CG41*CH41 -> 5155323 | CJ41: 109.96 | CK41: 47792 | CL41: =CJ41*CK41 -> 5255208.3 | CM41: 106.69 | CN41: 47792 | CO41: =CM41*CN41 -> 5098928.5 | CP41: 107.54 | CQ41: 47792 | CR41: =CP41*CQ41 -> 5139551.7 | CS41: 106.91 | CT41: 47792 | CU41: =CS41*CT41 -> 5109442.7 | CV41: 105.35 | CW41: 47792 | CX41: =CV41*CW41 -> 5034887.2 | CY41: 104.29 | CZ41: 47792 | DA41: =CY41*CZ41 -> 4984227.7 | DB41: 103.79 | DC41: 47792 | DD41: =DB41*DC41 -> 4960331.7 | DE41: 100.95 | DF41: 47792 | DG41: =DE41*DF41 -> 4824602.4 | DH41: 103.44 | DI41: 47792 | DJ41: =DH41*DI41 -> 4943604.5 | DK41: 105.41 | DL41: 47792 | DM41: =DK41*DL41 -> 5037754.7
B42: 12 | C42: Union Bank of India | D42: 24.68 | E42: 24257 | F42: =D42*E42 -> 598662.76 | G42: 158.96 | H42: 24257 | I42: =G42*H42 -> 3855892.7 | J42: 159 | K42: 24257 | L42: =J42*K42 -> 3856863 | M42: 160.12 | N42: 24257 | O42: =M42*N42 -> 3884030.8 | P42: 160.72 | Q42: 24257 | R42: =P42*Q42 -> 3898585 | S42: 168.87 | T42: 24257 | U42: =S42*T42 -> 4096279.6 | V42: 167.55 | W42: 24257 | X42: =V42*W42 -> 4064260.4 | Y42: 168.72 | Z42: 24257 | AA42: =Y42*Z42 -> 4092641 | AB42: 167.88 | AC42: 24257 | AD42: =AB42*AC42 -> 4072265.2 | AE42: 162.54 | AF42: 24257 | AG42: =AE42*AF42 -> 3942732.8 | AH42: 162.56 | AI42: 24257 | AJ42: =AH42*AI42 -> 3943217.9 | AK42: 166.7 | AL42: 24257 | AM42: =AK42*AL42 -> 4043641.9 | AN42: 166.54 | AO42: 24257 | AP42: =AN42*AO42 -> 4039760.8 | AQ42: 167 | AR42: 24257 | AS42: =AQ42*AR42 -> 4050919 | AT42: 165.18 | AU42: 24257 | AV42: =AT42*AU42 -> 4006771.3 | AW42: 170.44 | AX42: 24257 | AY42: =AW42*AX42 -> 4134363.1 | AZ42: 166.45 | BA42: 24257 | BB42: =AZ42*BA42 -> 4037577.6 | BC42: 164.54 | BD42: 24257 | BE42: =BC42*BD42 -> 3991246.8 | BF42: 170.05 | BG42: 24257 | BH42: =BF42*BG42 -> 4124902.9 | BI42: 171.3 | BJ42: 24257 | BK42: =BI42*BJ42 -> 4155224.1 | BL42: 170.56 | BM42: 24257 | BN42: =BL42*BM42 -> 4137273.9 | BO42: 173.75 | BP42: 24257 | BQ42: =BO42*BP42 -> 4214653.8 | BR42: 176.12 | BS42: 24257 | BT42: =BR42*BS42 -> 4272142.8 | BU42: 175.76 | BV42: 24257 | BW42: =BU42*BV42 -> 4263410.3 | BX42: 176.62 | BY42: 24257 | BZ42: =BX42*BY42 -> 4284271.3 | CA42: 175.12 | CB42: 24257 | CC42: =CA42*CB42 -> 4247885.8 | CD42: 174.83 | CE42: 24257 | CF42: =CD42*CE42 -> 4240851.3 | CG42: 174.71 | CH42: 24257 | CI42: =CG42*CH42 -> 4237940.5 | CJ42: 174.56 | CK42: 24257 | CL42: =CJ42*CK42 -> 4234301.9 | CM42: 172.43 | CN42: 24257 | CO42: =CM42*CN42 -> 4182634.5 | CP42: 174.88 | CQ42: 24257 | CR42: =CP42*CQ42 -> 4242064.2 | CS42: 174.35 | CT42: 24257 | CU42: =CS42*CT42 -> 4229208 | CV42: 163.09 | CW42: 24257 | CX42: =CV42*CW42 -> 3956074.1 | CY42: 161.08 | CZ42: 24257 | DA42: =CY42*CZ42 -> 3907317.6 | DB42: 161.08 | DC42: 24257 | DD42: =DB42*DC42 -> 3907317.6 | DE42: 154.39 | DF42: 24257 | DG42: =DE42*DF42 -> 3745038.2 | DH42: 157.26 | DI42: 24257 | DJ42: =DH42*DI42 -> 3814655.8 | DK42: 164.51 | DL42: 24257 | DM42: =DK42*DL42 -> 3990519.1
C44: Total | E44: =SUM(E31:E42) -> 1525532 | F44: =SUM(F31:F42) -> 94260157 | H44: =SUM(H31:H42) -> 1525532 | I44: =SUM(I31:I42) -> 98138336 | K44: =SUM(K31:K42) -> 1525532 | L44: =SUM(L31:L42) -> 98288745 | N44: =SUM(N31:N42) -> 1525532 | O44: =SUM(O31:O42) -> 98843363 | Q44: =SUM(Q31:Q42) -> 1525532 | R44: =SUM(R31:R42) -> 98552799 | T44: =SUM(T31:T42) -> 1525532 | U44: =SUM(U31:U42) -> 1.007959e+08 | W44: =SUM(W31:W42) -> 1525532 | X44: =SUM(X31:X42) -> 94099603 | Z44: =SUM(Z31:Z42) -> 1525532 | AA44: =SUM(AA31:AA42) -> 94319304 | AC44: =SUM(AC31:AC42) -> 1525532 | AD44: =SUM(AD31:AD42) -> 93281420 | AF44: =SUM(AF31:AF42) -> 1525532 | AG44: =SUM(AG31:AG42) -> 97580703 | AI44: =SUM(AI31:AI42) -> 1525532 | AJ44: =SUM(AJ31:AJ42) -> 1.0028228e+08 | AL44: =SUM(AL31:AL42) -> 1525532 | AM44: =SUM(AM31:AM42) -> 99171828 | AO44: =SUM(AO31:AO42) -> 1525532 | AP44: =SUM(AP31:AP42) -> 99658269 | AR44: =SUM(AR31:AR42) -> 1525532 | AS44: =SUM(AS31:AS42) -> 99546214 | AU44: =SUM(AU31:AU42) -> 1525532 | AV44: =SUM(AV31:AV42) -> 98838099 | AX44: =SUM(AX31:AX42) -> 1525532 | AY44: =SUM(AY31:AY42) -> 1.0266418e+08 | BA44: =SUM(BA31:BA42) -> 1525532 | BB44: =SUM(BB31:BB42) -> 1.0117648e+08 | BD44: =SUM(BD31:BD42) -> 1525532 | BE44: =SUM(BE31:BE42) -> 99727704 | BG44: =SUM(BG31:BG42) -> 1525532 | BH44: =SUM(BH31:BH42) -> 1.0231359e+08 | BJ44: =SUM(BJ31:BJ42) -> 1525532 | BK44: =SUM(BK31:BK42) -> 1.0327724e+08 | BM44: =SUM(BM31:BM42) -> 1525532 | BN44: =SUM(BN31:BN42) -> 1.0322878e+08 | BP44: =SUM(BP31:BP42) -> 1525532 | BQ44: =SUM(BQ31:BQ42) -> 1.0638581e+08 | BS44: =SUM(BS31:BS42) -> 1525532 | BT44: =SUM(BT31:BT42) -> 1.061626e+08 | BV44: =SUM(BV31:BV42) -> 1525532 | BW44: =SUM(BW31:BW42) -> 1.0566117e+08 | BY44: =SUM(BY31:BY42) -> 1525532 | BZ44: =SUM(BZ31:BZ42) -> 1.0590413e+08 | CB44: =SUM(CB31:CB42) -> 1525532 | CC44: =SUM(CC31:CC42) -> 1.0397602e+08 | CE44: =SUM(CE31:CE42) -> 1525532 | CF44: =SUM(CF31:CF42) -> 1.043032e+08 | CH44: =SUM(CH31:CH42) -> 1525532 | CI44: =SUM(CI31:CI42) -> 1.0389547e+08 | CK44: =SUM(CK31:CK42) -> 1525532 | CL44: =SUM(CL31:CL42) -> 1.0384968e+08 | CN44: =SUM(CN31:CN42) -> 1525532 | CO44: =SUM(CO31:CO42) -> 1.0294635e+08 | CQ44: =SUM(CQ31:CQ42) -> 1525532 | CR44: =SUM(CR31:CR42) -> 1.0347899e+08 | CT44: =SUM(CT31:CT42) -> 1525532 | CU44: =SUM(CU31:CU42) -> 1.0379007e+08 | CW44: =SUM(CW31:CW42) -> 1525532 | CX44: =SUM(CX31:CX42) -> 1.019412e+08 | CZ44: =SUM(CZ31:CZ42) -> 1525532 | DA44: =SUM(DA31:DA42) -> 1.0080066e+08 | DC44: =SUM(DC31:DC42) -> 1525532 | DD44: =SUM(DD31:DD42) -> 99981658 | DF44: =SUM(DF31:DF42) -> 1525532 | DG44: =SUM(DG31:DG42) -> 97391504 | DI44: =SUM(DI31:DI42) -> 1525532 | DJ44: =SUM(DJ31:DJ42) -> 99143379 | DL44: =SUM(DL31:DL42) -> 1525532 | DM44: =SUM(DM31:DM42) -> 1.0180029e+08
C45: Total Fund Units ( Assumed ) | F45: 10000000 | I45: 10000000 | L45: 10000000 | O45: 10000000 | R45: 10000000 | U45: 10000000 | X45: 10000000 | AA45: 10000000 | AD45: 10000000 | AG45: 10000000 | AJ45: 10000000 | AM45: 10000000 | AP45: 10000000 | AS45: 10000000 | AV45: 10000000 | AY45: 10000000 | BB45: 10000000 | BE45: 10000000 | BH45: 10000000 | BK45: 10000000 | BN45: 10000000 | BQ45: 10000000 | BT45: 10000000 | BW45: 10000000 | BZ45: 10000000 | CC45: 10000000 | CF45: 10000000 | CI45: 10000000 | CL45: 10000000 | CO45: 10000000 | CR45: 10000000 | CU45: 10000000 | CX45: 10000000 | DA45: 10000000 | DD45: 10000000 | DG45: 10000000 | DJ45: 10000000 | DM45: 10000000
C46: NAV | F46: =F44/F45 -> 9.4260157 | I46: =I44/I45 -> 9.8138336 | L46: =L44/L45 -> 9.8288745 | O46: =O44/O45 -> 9.8843363 | R46: =R44/R45 -> 9.8552799 | U46: =U44/U45 -> 10.07959 | X46: =X44/X45 -> 9.4099603 | AA46: =AA44/AA45 -> 9.4319304 | AD46: =AD44/AD45 -> 9.328142 | AG46: =AG44/AG45 -> 9.7580703 | AJ46: =AJ44/AJ45 -> 10.028228 | AM46: =AM44/AM45 -> 9.9171828 | AP46: =AP44/AP45 -> 9.9658269 | AS46: =AS44/AS45 -> 9.9546214 | AV46: =AV44/AV45 -> 9.8838099 | AY46: =AY44/AY45 -> 10.266418 | BB46: =BB44/BB45 -> 10.117648 | BE46: =BE44/BE45 -> 9.9727704 | BH46: =BH44/BH45 -> 10.231359 | BK46: =BK44/BK45 -> 10.327724 | BN46: =BN44/BN45 -> 10.322878 | BQ46: =BQ44/BQ45 -> 10.638581 | BT46: =BT44/BT45 -> 10.61626 | BW46: =BW44/BW45 -> 10.566117 | BZ46: =BZ44/BZ45 -> 10.590413 | CC46: =CC44/CC45 -> 10.397602 | CF46: =CF44/CF45 -> 10.43032 | CI46: =CI44/CI45 -> 10.389547 | CL46: =CL44/CL45 -> 10.384968 | CO46: =CO44/CO45 -> 10.294635 | CR46: =CR44/CR45 -> 10.347899 | CU46: =CU44/CU45 -> 10.379007 | CX46: =CX44/CX45 -> 10.19412 | DA46: =DA44/DA45 -> 10.080066 | DD46: =DD44/DD45 -> 9.9981658 | DG46: =DG44/DG45 -> 9.7391504 | DJ46: =DJ44/DJ45 -> 9.9143379 | DM46: =DM44/DM45 -> 10.180029

Sheet INDEX & NAV
B2: DAY | C2: DATE | D2: INDEX | E2: NAV
B4: M | C4: 46153 | D4: ='Banking Sector - PSU'!K21 -> 948.28964 | E4: N/A
B5: T | C5: 46154 | D5: ='Banking Sector - PSU'!Q21 -> 991.25756 | E5: N/A
B6: W | C6: 46155 | D6: ='Banking Sector - PSU'!V21 -> 998.45023 | E6: N/A
B7: T | C7: 46156 | D7: ='Banking Sector - PSU'!AA21 -> 1011.5426 | E7: N/A
B8: F | C8: 46157 | D8: ='Banking Sector - PSU'!AF21 -> 983.14742 | E8: N/A
B10: M | C10: 46160 | D10: ='Banking Sector - PSU'!AK21 -> 979.49558 | E10: ='SECTOR FUND & AUM'!F46 -> 9.4260157
B11: T | C11: 46161 | D11: ='Banking Sector - PSU'!AP21 -> 1010.5477 | E11: ='SECTOR FUND & AUM'!I46 -> 9.8138336
B12: W | C12: 46162 | D12: ='Banking Sector - PSU'!AU21 -> 1000.7211 | E12: ='SECTOR FUND & AUM'!L46 -> 9.8288745
B13: T | C13: 46163 | D13: ='Banking Sector - PSU'!AZ21 -> 1002.2513 | E13: ='SECTOR FUND & AUM'!O46 -> 9.8843363
B14: F | C14: 46164 | D14: ='Banking Sector - PSU'!BE21 -> 999.49589 | E14: ='SECTOR FUND & AUM'!R46 -> 9.8552799
B16: M | C16: 46167 | D16: ='Banking Sector - PSU'!BJ21 -> 1025.752 | E16: ='SECTOR FUND & AUM'!U46 -> 10.07959
B17: T | C17: 46168 | D17: ='Banking Sector - PSU'!BO21 -> 996.79975 | E17: ='SECTOR FUND & AUM'!X46 -> 9.4099603
B18: W | C18: 46169 | D18: ='Banking Sector - PSU'!BT21 -> 1001.7072 | E18: ='SECTOR FUND & AUM'!AA46 -> 9.4319304
B20: F | C20: 46171 | D20: ='Banking Sector - PSU'!BY21 -> 992.01925 | E20: ='SECTOR FUND & AUM'!AD46 -> 9.328142
B22: M | C22: 46174 | D22: ='Banking Sector - PSU'!CD21 -> 983.87151 | E22: ='SECTOR FUND & AUM'!AG46 -> 9.7580703
B23: T | C23: 46175 | D23: ='Banking Sector - PSU'!CI21 -> 1012.532 | E23: ='SECTOR FUND & AUM'!AJ46 -> 10.028228
B24: W | C24: 46176 | D24: ='Banking Sector - PSU'!CN21 -> 998.76001 | E24: ='SECTOR FUND & AUM'!AM46 -> 9.9171828
B25: T | C25: 46177 | D25: ='Banking Sector - PSU'!CS21 -> 1015.1246 | E25: ='SECTOR FUND & AUM'!AP46 -> 9.9658269
B26: F | C26: 46178 | D26: ='Banking Sector - PSU'!CX21 -> 1001.7026 | E26: ='SECTOR FUND & AUM'!AS46 -> 9.9546214
B28: M | C28: 46181 | D28: ='Banking Sector - PSU'!DC21 -> 996.60024 | E28: ='SECTOR FUND & AUM'!AV46 -> 9.8838099
B29: T | C29: 46182 | D29: ='Banking Sector - PSU'!DH21 -> 1031.043 | E29: ='SECTOR FUND & AUM'!AY46 -> 10.266418
B30: W | C30: 46183 | D30: ='Banking Sector - PSU'!DM21 -> 989.65006 | E30: ='SECTOR FUND & AUM'!BB46 -> 10.117648
B31: T | C31: 46184 | D31: ='Banking Sector - PSU'!DR21 -> 992.30862 | E31: ='SECTOR FUND & AUM'!BE46 -> 9.9727704
B32: F | C32: 46185 | D32: ='Banking Sector - PSU'!DW21 -> 1008.9739 | E32: ='SECTOR FUND & AUM'!BH46 -> 10.231359
B34: M | C34: 46188 | D34: ='Banking Sector - PSU'!EB21 -> 1005.8916 | E34: ='SECTOR FUND & AUM'!BK46 -> 10.327724
B35: T | C35: 46189 | D35: ='Banking Sector - PSU'!EG21 -> 997.15303 | E35: ='SECTOR FUND & AUM'!BN46 -> 10.322878
B36: W | C36: 46190 | D36: ='Banking Sector - PSU'!EL21 -> 1017.6935 | E36: ='SECTOR FUND & AUM'!BQ46 -> 10.638581
B37: T | C37: 46191 | D37: ='Banking Sector - PSU'!EQ21 -> 1008.3618 | E37: ='SECTOR FUND & AUM'!BT46 -> 10.61626
B38: F | C38: 46192 | D38: ='Banking Sector - PSU'!EV21 -> 1000.6884 | E38: ='SECTOR FUND & AUM'!BW46 -> 10.566117
B40: M | C40: 46195 | D40: ='Banking Sector - PSU'!FA21 -> 1004.9202 | E40: ='SECTOR FUND & AUM'!BZ46 -> 10.590413
B41: T | C41: 46196 | D41: ='Banking Sector - PSU'!FF21 -> 982.1842 | E41: ='SECTOR FUND & AUM'!CC46 -> 10.397602
B42: W | C42: 46197 | D42: ='Banking Sector - PSU'!FK21 -> 1005.865 | E42: ='SECTOR FUND & AUM'!CF46 -> 10.43032
B43: T | C43: 46198 | D43: ='Banking Sector - PSU'!FP21 -> 1003.1079 | E43: ='SECTOR FUND & AUM'!CI46 -> 10.389547
B45: M | C45: 46202 | D45: ='Banking Sector - PSU'!FU21 -> 993.75859 | E45: ='SECTOR FUND & AUM'!CL46 -> 10.384968
B46: T | C46: 46203 | D46: ='Banking Sector - PSU'!FZ21 -> 990.3998 | E46: ='SECTOR FUND & AUM'!CO46 -> 10.294635
B47: W | C47: 46204 | D47: ='Banking Sector - PSU'!GE21 -> 1007.4394 | E47: ='SECTOR FUND & AUM'!CR46 -> 10.347899
B48: T | C48: 46205 | D48: ='Banking Sector - PSU'!GJ21 -> 1001.8733 | E48: ='SECTOR FUND & AUM'!CU46 -> 10.379007
B49: F | C49: 46206 | D49: ='Banking Sector - PSU'!GO21 -> 1005.9417 | E49: ='SECTOR FUND & AUM'!CX46 -> 10.19412
B51: M | C51: 46209 | D51: ='Banking Sector - PSU'!GT21 -> 994.28403 | E51: ='SECTOR FUND & AUM'!DA46 -> 10.080066
B52: T | C52: 46210 | D52: ='Banking Sector - PSU'!GY21 -> 997.2174 | E52: ='SECTOR FUND & AUM'!DD46 -> 9.9981658
B53: W | C53: 46211 | D53: ='Banking Sector - PSU'!HD21 -> 975.23633 | E53: ='SECTOR FUND & AUM'!DG46 -> 9.7391504
B54: T | C54: 46212 | D54: ='Banking Sector - PSU'!HI21 -> 1013.6197 | E54: ='SECTOR FUND & AUM'!DJ46 -> 9.9143379
B55: F | C55: 46213 | D55: ='Banking Sector - PSU'!HN21 -> 1019.0481 | E55: ='SECTOR FUND & AUM'!DM46 -> 10.180029

Sheet WORKING
B2: DATES | C2: INDEX | AB2: DATES | AC2: NAV
B3: 46153 | C3: 948.28 | AB3: 46160 | AC3: 9.42
B4: 46154 | C4: 991.25 | AB4: 46161 | AC4: 9.81
B5: 46155 | C5: 998.45 | AB5: 46162 | AC5: 9.82
B6: 46156 | C6: 1011.54 | AB6: 46163 | AC6: 9.85
B7: 46157 | C7: 983.15 | AB7: 46164 | AC7: 9.86
B8: 46160 | C8: 979.49 | AB8: 46167 | AC8: 10.08
B9: 46161 | C9: 1010.54 | AB9: 46168 | AC9: 9.41
B10: 46162 | C10: 1000.72 | AB10: 46169 | AC10: 9.43
B11: 46163 | C11: 1002.25 | AB11: 46171 | AC11: 9.33
B12: 46164 | C12: 999.5 | AB12: 46174 | AC12: 9.76
B13: 46167 | C13: 1025.75 | AB13: 46175 | AC13: 10.03
B14: 46168 | C14: 996.8 | AB14: 46176 | AC14: 9.92
... B40: 46206 | C40: 1005.94 | AB40: 46213 | AC40: 10.18
B41: 46209 | C41: 994.38
B42: 46210 | C42: 997.22
B43: 46211 | C43: 975.23
B44: 46212 | C44: 1013.62
B45: 46213 | C45: 1019.05

Sheet TechnicalAnalysis_LongTerm
B3: TECHNICAL ANALYSIS - LONG TERM
B6: 1 | J6: 2 | R6: 3
C19: INDIAN OVERSEAS BANK | K19: BANK OF MAHARASHTRA | S19: INDIAN BANK
B21: 4 | J21: 5 | R21: 6
C34: STATE BANK OF INDIA | K34: BANK OF BARODA | S34: CANARA BANK
B36: 7 | J36: 8 | R36: 9
C49: UCO BANK | K49: BANK OF INDIA | S49: PUNJAB & SIND BANK
B51: 10 | J51: 11 | R51: 12
C64: CENTRAL BANK OF INDIA | K64: PUNJAB NATIONAL BANK | S64: UNION BANK OF INDIA

Sheet TechnicalAnalysis_SwingTrading
B3: TECHNICAL ANALYSIS - SWING TRADING
B6: 1 | J6: 2 | R6: 3
C20: INDIAN OVERSEAS BANK | K20: BANK OF MAHARASHTRA | S20: INDIAN BANK
B22: 4 | J22: 5 | R22: 6
C36: STATE BANK OF INDIA | K36: BANK OF BARODA | S36: CANARA BANK
B38: 7 | J38: 8 | R38: 9
C52: UCO BANK | K52: BANK OF INDIA | S52: PUNJAB & SIND BANK
B54: 10 | J54: 11 | R54: 12
C68: CENTRAL BANK OF INDIA | K68: PUNJAB NATIONAL BANK | S68: UNION BANK OF INDIA

Sheet TechnicalAnalysis_Short Term
B3: TECHNICAL ANALYSIS - SHORT TERM
B7: 1 | J7: 2 | R7: 3
C20: INDIAN OVERSEAS BANK | K20: BANK OF MAHARASHTRA | S20: INDIAN BANK
B22: 4 | J22: 5 | R22: 6
C35: STATE BANK OF INDIA | K35: BANK OF BARODA | S35: CANARA BANK
B37: 7 | J37: 8 | R37: 9
C50: UCO BANK | K50: BANK OF INDIA | S50: PUNJAB & SIND BANK
B52: 10 | J52: 11 | R52: 12
C65: CENTRAL BANK OF INDIA | K65: PUNJAB NATIONAL BANK | S65: UNION BANK OF INDIA

Sheet TechnicalAnalysis_Conclusion
D2: LONG TERM | H2: SWING TRADING | L2: SHORT TERM
B4: COMPANIES | D4: PATTERN | E4: CURRENT TREND | F4: RECOMMENDATION | H4: PATTERN | I4: CURRENT TREND | J4: RECOMMENDATION | L4: PATTERN | M4: CURRENT TREND | N4: RECOMMENDATION
A6: 1 | B6: Indian Overseas Bank (IOB) | D6: Double Top | E6: Down Trend | F6: Sell | H6: Rectangle | I6: Down Trend | J6: Sell | L6: Inverted Hammer | M6: Down Trend | N6: Sell
A7: 2 | B7: Bank of Maharashtra | D7: Cup with Handle | E7: Up Trend | F7: Buy | H7: Price Channel | I7: Up Trend | J7: Buy | L7: Hanging Man | M7: Down Trend | N7: Sell
A8: 3 | B8: Indian Bank | D8: Rounding Bottom | E8: Up Trend | F8: Buy | H8: Price Channel | I8: Down Trend | J8: Sell | L8: Inverted Hammer | M8: Down Trend | N8: Sell
A9: 4 | B9: State Bank of India (SBI) | D9: Bump & Run | E9: Down Trend | F9: Sell | H9: Price Channel | I9: Down Trend | J9: Sell | L9: Bearish Engulfing | M9: Down Trend | N9: Sell
A10: 5 | B10: Bank of Baroda (BOB) | D10: Double Top | E10: Down Trend | F10: Sell | H10: Rectangle | I10: Down Trend | J10: Sell | L10: Hammer | M10: Up Trend | N10: Buy
A11: 6 | B11: Canara Bank | D11: Cup with Handle | E11: Up Trend | F11: Buy | H11: Price Channel | I11: Down Trend | J11: Sell | L11: Hanging Man | M11: Down Trend | N11: Sell
A12: 7 | B12: UCO Bank | D12: Bump & Run | E12: Down Trend | F12: Sell | H12: Descending Triangle | I12: Down Trend | J12: Sell | L12: Bearish Engulfing | M12: Down Trend | N12: Sell
A13: 8 | B13: Bank of India (BOI) | D13: Rounding Bottom | E13: Up Trend | F13: Buy | H13: Symmetric Triangle | I13: Down Trend | J13: Sell | L13: Bearish Engulfing | M13: Down Trend | N13: Sell
A14: 9 | B14: Punjab & Sind Bank | D14: Double Top | E14: Down Trend | F14: Sell | H14: Symmetric Triangle | I14: Down Trend | J14: Sell | L14: Doji | M14: Down Trend | N14: Sell
A15: 10 | B15: Central Bank of India | D15: Head & Shoulders Top | E15: Down Trend | F15: Sell | H15: Price Channel | I15: Down Trend | J15: Sell | L15: Doji | M15: Down Trend | N15: Sell
A16: 11 | B16: Punjab National Bank (PNB) | D16: Bump & Run | E16: Down Trend | F16: Sell | H16: Price Channel | I16: Up Trend | J16: Buy | L16: Shooting Star | M16: Down Trend | N16: Sell
A17: 12 | B17: Union Bank of India | D17: Cup with Handle | E17: Up Trend | F17: Buy | H17: Rectangle | I17: Up Trend | J17: Buy | L17: Bearish Engulfing | M17: Down Trend | N17: Sell
